Workbook

Sheet 滚动稳健标准化季频
B1: GDP:不变价:当季同比 | C1: 中国:工业产能利用率:当季值
A2: 46022 | B2: 4.5 | C2: 74.9
A3: 45930 | B3: 4.8 | C3: 74.6
A4: 45838 | B4: 5.2 | C4: 74
A5: 45747 | B5: 5.4 | C5: 74.1
A6: 45657 | B6: 5.4 | C6: 76.2
A7: 45565 | B7: 4.6 | C7: 75.1
A8: 45473 | B8: 4.7 | C8: 74.9
A9: 45382 | B9: 5.3 | C9: 73.6
A10: 45291 | B10: 5.3 | C10: 75.903011
A11: 45199 | B11: 5 | C11: 75.6
A12: 45107 | B12: 6.5 | C12: 74.5
A13: 45016 | B13: 4.7 | C13: 74.3
... A53: 41364 | B53: 7.9 | C53: 75.3
A54: 41274 | B54: 8.1
A55: 41182 | B55: 7.5
A56: 41090 | B56: 7.7
A57: 40999 | B57: 8.1
A58: 40908 | B58: 8.7
A59: 40816 | B59: 9.3
A60: 40724 | B60: 9.9
A61: 40633 | B61: 10.1
A62: 40543 | B62: 9.9
A63: 40451 | B63: 9.9
A64: 40359 | B64: 10.7
A65: 40268 | B65: 12.2

Sheet 季频数据发布日期
B1: GDP同比 | C1: 产能利用率
A2: 46022 | B2: 46041 | C2: 46041
A3: 45930 | B3: 45950 | C3: 45950
A4: 45838 | B4: 45853 | C4: 45853
A5: 45747 | B5: 45763 | C5: 45763
A6: 45657 | B6: 45674 | C6: 45674
A7: 45565 | B7: 45583 | C7: 45583
A8: 45473 | B8: 2024-07-16 | C8: 2024-07-16
A9: 45382 | B9: 2024-04-17 | C9: 2024-04-17
A10: 45291 | B10: 2024-01-18 | C10: 2024-01-18
A11: 45199 | B11: 2023-10-19 | C11: 2023-10-19
A12: 45107 | B12: 2023-07-15 | C12: 2023-07-15
A13: 45016 | B13: 2023-04-19 | C13: 2023-04-19
A14: 44926 | B14: 2023-01-18 | C14: 2023-01-18
A15: 44834 | B15: 2022-10-24 | C15: 2022-10-24
A16: 44742 | B16: 2022-07-16 | C16: 2022-07-16
A17: 44651 | B17: 2022-04-19 | C17: 2022-04-19
A18: 44561 | B18: 2022-01-18 | C18: 2022-01-18
A19: 44469 | B19: 2021-10-19 | C19: 2021-10-19
... A45: 42094 | B45: 2015-04-16 | C45: 2015-04-16
A46: 42004 | B46: 42025 | C46: 42025
A47: 41912 | B47: 41934 | C47: 41934
A48: 41820 | B48: 41837 | C48: 41837
A49: 41729 | B49: 41746 | C49: 41746
A50: 41639 | B50: 41660 | C50: 41660
A51: 41547 | B51: 41566 | C51: 41566
A52: 41455 | B52: 41471 | C52: 41471
A53: 41364 | B53: 41380 | C53: 41380
A54: 41274 | B54: 41293 | C54: 41293
A55: 41182 | B55: 41205 | C55: 41205
A56: 41090 | B56: 41103 | C56: 41103
A57: 40999 | B57: 41008 | C57: 41008
... A65: 40268 | B65: 40283 | C65: 40283

Sheet 滚动稳健标准化月频
B1: 工业增加值同比 | C1: 社会消费品零售总额同比 | D1: 固定资产投资完成额:基础设施建设:累计同比 | E1: 房地产开发投资完成额:累计同比 | F1: CPI同比 | G1: PPI同比 | H1: M2同比 | I1: PMI-50 | J1: 出口金额:当月同比 | K1: 进口金额:当月同比 | L1: 商品房销售面积:累计同比 | M1: 70个大中城市:房屋销售价格指数:新建商品住宅:当月同比 | N1: 社融同比 | O1: M1旧口径 | P1: 商业银行托管同比 | Q1: 广义基金托管同比 | R1: 证券公司托管同比 | S1: 保险托管同比
A2: 46022 | B2: 5.9 | C2: 0.9 | D2: -1.48 | E2: -17.2 | F2: 0.8 | G2: -1.9 | H2: 8.5 | I2: 0.1 | J2: 6.6 | K2: 5.7 | L2: -8.7 | M2: -3 | N2: 8.3 | O2: 2.0337177 | P2: 10.699649 | Q2: 10.447595 | R2: 10.699649 | S2: 11.523763
A3: 45991 | B3: 6 | C3: 1.3 | D3: 0.13 | E3: -15.9 | F3: 0.7 | G3: -2.2 | H3: 8 | I3: -0.8 | J3: 5.9 | K3: 1.9 | L3: -7.8 | M3: -2.8 | N3: 8.5 | O3: 3.7767342 | P3: 9.96805 | Q3: 16.034983 | R3: -5.4740288 | S3: 10.478727
A4: 45961 | B4: 6.1 | C4: 2.9 | D4: 1.51 | E4: -14.7 | F4: 0.2 | G4: -2.1 | H4: 8.2 | I4: -1 | J4: -1.1 | K4: 1 | L4: -6.8 | M4: -2.6 | N4: 8.5 | O4: 5.3708974 | P4: 8.5902049 | Q4: 19.379329 | R4: 2.1788192 | S4: 9.7894459
A5: 45930 | B5: 6.2 | C5: 3 | D5: 3.34 | E5: -13.9 | F5: -0.3 | G5: -2.3 | H5: 8.4 | I5: -0.2 | J5: 8.3 | K5: 7.4 | L5: -5.5 | M5: -2.7 | N5: 8.7 | O5: 6.2475147 | P5: 9.8730293 | Q5: 16.796831 | R5: -1.5955517 | S5: 12.041835
A6: 45900 | B6: 6.2 | C6: 3.4 | D6: 5.42 | E6: -12.9 | F6: -0.4 | G6: -2.9 | H6: 8.8 | I6: -0.6 | J6: 4.4 | K6: 1.3 | L6: -4.7 | M6: -3 | N6: 8.8 | O6: 5.7873906 | P6: 10.947557 | Q6: 18.696161 | R6: 0.13670903 | S6: 12.107477
A7: 45869 | B7: 6.3 | C7: 3.7 | D7: 7.29 | E7: -12 | F7: 0 | G7: -3.6 | H7: 8.8 | I7: -0.7 | J7: 7.2 | K7: 4.1 | L7: -4 | M7: -3.4 | N7: 9 | O7: 4.8925303 | P7: 11.263827 | Q7: 18.472467 | R7: 1.9077217 | S7: 12.342808
A8: 45838 | B8: 6.4 | C8: 4.8 | D8: 8.9 | E8: -11.2 | F8: 0.1 | G8: -3.6 | H8: 8.3 | I8: -0.3 | J8: 5.8 | K8: 1.1 | L8: -3.5 | M8: -3.7 | N8: 8.9 | O8: 3.1413411 | P8: 9.159834 | Q8: 21.137358 | R8: 7.6424667 | S8: 11.877984
A9: 45808 | B9: 6.3 | C9: 6.4 | D9: 10.42 | E9: -10.7 | F9: -0.1 | G9: -3.3 | H9: 7.9 | I9: -0.5 | J9: 4.8 | K9: -3.4 | L9: -2.9 | M9: -4.1 | N9: 8.7 | O9: 0.73960821 | P9: 8.8462778 | Q9: 26.298124 | R9: 8.5058697 | S9: 16.145584
A10: 45777 | B10: 6.4 | C10: 5.1 | D10: 10.85 | E10: -10.3 | F10: -0.1 | G10: -2.7 | H10: 8 | I10: -1 | J10: 8.1 | K10: -0.2 | L10: -2.8 | M10: -4.5 | N10: 8.7 | O10: -1.0194591 | P10: 8.1598741 | Q10: 26.666418 | R10: 15.820812 | S10: 19.016841
A11: 45747 | B11: 6.5 | C11: 5.9 | D11: 11.5 | E11: -9.9 | F11: -0.1 | G11: -2.5 | H11: 7 | I11: 0.5 | J11: 12.4 | K11: -4.3 | L11: -3 | M11: -5 | N11: 8.4 | O11: -0.82758331 | P11: 7.2527487 | Q11: 26.878507 | R11: 2.049759 | S11: 20.856684
A12: 45716 | B12: 5.9 | C12: 4 | D12: 9.95 | E12: -9.8 | F12: -0.7 | G12: -2.2 | H12: 7 | I12: 0.2 | J12: -3 | K12: 1.5 | L12: -5.1 | M12: -5.2 | N12: 8.2 | O12: -2.5016335 | P12: 8.0077588 | Q12: 20.47689 | R12: -3.3971229 | S12: 19.800815
A13: 45688 | F13: 0.5 | G13: -2.3 | H13: 7 | I13: -0.9 | J13: 6 | K13: -16.5 | M13: -5.4 | N13: 8 | O13: -5.6892337 | P13: 6.6180465 | Q13: 21.875279 | R13: -3.9444617 | S13: 16.22303
A14: 45657 | B14: 5.8 | C14: 3.7 | D14: 9.19 | E14: -10.6 | F14: 0.1 | G14: -2.3 | H14: 7.3 | I14: 0.1 | J14: 10.7 | K14: 1 | L14: -12.9 | M14: -5.7 | N14: 8 | O14: -1.408156 | P14: 7.9805223 | Q14: 25.485484 | R14: -1.6210693 | S14: 15.994563
A15: 45626 | B15: 5.8 | C15: 3 | D15: 9.39 | E15: -10.4 | F15: 0.2 | G15: -2.5 | H15: 7.1 | I15: 0.3 | J15: 6.6 | K15: -4 | L15: -14.3 | M15: -6.1 | N15: 7.8 | O15: -3.6986424 | P15: 8.6761002 | Q15: 20.132138 | R15: 3.9107764 | S15: 16.150596
A16: 45596 | B16: 5.8 | C16: 4.8 | D16: 9.35 | E16: -10.3 | F16: 0.3 | G16: -2.9 | H16: 7.5 | I16: 0.1 | J16: 12.7 | K16: -2.4 | L16: -15.8 | M16: -6.2 | N16: 7.8 | O16: -6.1269958 | P16: 10.273363 | Q16: 16.213508 | R16: 3.9810565 | S16: 16.539718
A17: 45565 | B17: 5.8 | C17: 3.2 | D17: 9.26 | E17: -10.1 | F17: 0.4 | G17: -2.8 | H17: 6.8 | I17: -0.2 | J17: 2.4 | K17: 0.2 | L17: -17.1 | M17: -6.1 | N17: 8 | O17: -7.400336 | P17: 11.713019 | Q17: 15.262087 | R17: 2.4290872 | S17: 16.546661
A18: 45535 | B18: 5.8 | C18: 2.1 | D18: 7.87 | E18: -10.2 | F18: 0.6 | G18: -1.8 | H18: 6.3 | I18: -0.9 | J18: 8.6 | K18: 0.2 | L18: -18 | M18: -5.7 | N18: 8.1 | O18: -7.2617872 | P18: 11.74941 | Q18: 10.894768 | R18: 5.9387486 | S18: 15.684167
A19: 45504 | B19: 5.9 | C19: 2.7 | D19: 8.14 | E19: -10.2 | F19: 0.5 | G19: -0.8 | H19: 6.3 | I19: -0.6 | J19: 6.9 | K19: 6.8 | L19: -18.6 | M19: -5.3 | N19: 8.2 | O19: -6.6333616 | P19: 11.410724 | Q19: 13.044991 | R19: 8.2460315 | S19: 16.363089
A20: 45473 | B20: 6 | C20: 2 | D20: 7.7 | E20: -10.1 | F20: 0.2 | G20: -0.8 | H20: 6.2 | I20: -0.5 | J20: 8.5 | K20: -2.5 | L20: -19 | M20: -4.9 | N20: 8.1 | O20: -5.0294979 | P20: 12.27401 | Q20: 12.789793 | R20: 1.8571329 | S20: 14.405241
A21: 45443 | B21: 6.2 | C21: 3.7 | D21: 6.679178 | E21: -10.1 | F21: 0.3 | G21: -1.4 | H21: 7 | I21: -0.5 | J21: 7.4 | K21: 2 | L21: -20.3 | M21: -4.3 | N21: 8.4 | O21: -4.2073876 | P21: 12.458108 | Q21: 9.2025089 | R21: 3.8349613 | S21: 17.500432
A22: 45412 | B22: 6.3 | C22: 2.3 | D22: 7.783003 | E22: -9.8 | F22: 0.3 | G22: -2.5 | H22: 7.2 | I22: 0.4 | J22: 1.3 | K22: 8.3 | L22: -20.2 | M22: -3.5 | N22: 8.3 | O22: -1.4476585 | P22: 11.303859 | Q22: 7.8501127 | R22: 1.8546229 | S22: 17.293061
A23: 45382 | B23: 6.1 | C23: 3.1 | D23: 8.754397 | E23: -9.5 | F23: 0.1 | G23: -2.8 | H23: 8.3 | I23: 0.8 | J23: -7.6 | K23: -2 | L23: -19.4 | M23: -2.7 | N23: 8.7 | O23: 1.1428597 | P23: 11.901275 | Q23: 7.7602431 | R23: 7.585381 | S23: 14.428907
A24: 45351 | B24: 7 | C24: 5.5 | D24: 8.955393 | E24: -9 | F24: 0.7 | G24: -2.7 | H24: 8.7 | I24: -0.9 | J24: 6.3 | K24: -8 | L24: -20.5 | M24: -1.9 | N24: 9 | O24: 1.2124761 | P24: 11.371534 | Q24: 7.8711607 | R24: 16.878664 | S24: 15.882845
A25: 45322 | F25: -0.8 | G25: -2.5 | H25: 8.7 | I25: -0.8 | J25: 7.7 | K25: 15.6 | M25: -1.2 | N25: 9.5 | O25: 5.9497676 | P25: 13.260741 | Q25: 5.710548 | R25: 20.593313 | S25: 16.354411
A26: 45291 | B26: 4.6 | C26: 7.4 | D26: 8.24 | E26: -9.6 | F26: -0.3 | G26: -2.7 | H26: 9.7 | I26: -1 | J26: 2.147524 | K26: 0.287854 | L26: -8.5 | M26: -0.9 | N26: 9.5 | O26: 1.3202446 | P26: 14.166638 | Q26: 1.3229547 | R26: 17.892917 | S26: 16.354831
A27: 45260 | B27: 4.3 | C27: 10.1 | D27: 7.9642 | E27: -9.4 | F27: -0.5 | G27: -3 | H27: 10 | I27: -0.6 | J27: 0.693013 | K27: -0.563534 | L27: -8 | M27: -0.7 | N27: 9.4 | O27: 1.3283709 | P27: 15.394724 | Q27: -2.4728486 | R27: 21.932331 | S27: 16.123432
A28: 45230 | B28: 4.1 | C28: 7.6 | D28: 8.27 | E28: -9.3 | F28: -0.2 | G28: -2.6 | H28: 10.3 | I28: -0.5 | J28: -6.612764 | K28: 3.034364 | L28: -7.8 | M28: -0.6 | N28: 9.3 | O28: 1.8961324 | P28: 16.377643 | Q28: -6.4372468 | R28: 21.122868 | S28: 16.437054
A29: 45199 | B29: 4 | C29: 5.5 | D29: 8.64 | E29: -9.1 | F29: 0 | G29: -2.5 | H29: 10.3 | I29: 0.2 | J29: -6.846969 | K29: -6.251377 | L29: -7.5 | M29: -0.6 | N29: 9 | O29: 2.0929637 | P29: 14.504944 | Q29: -6.3689529 | R29: 23.111007 | S29: 15.029226
A30: 45169 | B30: 3.9 | C30: 4.6 | D30: 8.959009 | E30: -8.8 | F30: 0.1 | G30: -3 | H30: 10.6 | I30: -0.3 | J30: -8.552899 | K30: -7.186193 | L30: -7.1 | M30: -0.6 | N30: 9 | O30: 2.2544975 | P30: 14.187769 | Q30: -2.8733033 | R30: 19.402642 | S30: 16.809046
A31: 45138 | B31: 3.8 | C31: 2.5 | D31: 9.410929 | E31: -8.5 | F31: -0.3 | G31: -4.4 | H31: 10.7 | I31: -0.7 | J31: -14.256267 | K31: -12.145378 | L31: -6.5 | M31: -0.6 | N31: 8.9 | O31: 2.3248487 | P31: 12.820627 | Q31: -3.1908495 | R31: 17.703097 | S31: 14.909369
A32: 45107 | B32: 3.8 | C32: 3.1 | D32: 10.15 | E32: -7.9 | F32: 0 | G32: -5.4 | H32: 11.3 | I32: -1 | J32: -12.377592 | K32: -7.075619 | L32: -5.3 | M32: -0.4 | N32: 9 | O32: 3.146719 | P32: 11.516213 | Q32: -3.788913 | R32: 22.912451 | S32: 16.077857
A33: 45077 | B33: 3.6 | C33: 12.7 | D33: 9.53 | E33: -7.2 | F33: 0.2 | G33: -4.6 | H33: 11.6 | I33: -1.2 | J33: -7.561723 | K33: -5.27686 | L33: -0.9 | M33: -0.5 | N33: 9.5 | O33: 4.6729358 | P33: 13.839501 | Q33: -2.407132 | R33: 16.195374 | S33: 16.924573
A34: 45046 | B34: 3.6 | C34: 18.4 | D34: 9.8 | E34: -6.2 | F34: 0.1 | G34: -3.6 | H34: 12.4 | I34: -0.8 | J34: 7.105757 | K34: -8.822314 | L34: -0.4 | M34: -0.7 | N34: 10 | O34: 5.2854077 | P34: 14.746352 | Q34: -2.5554125 | R34: 20.911411 | S34: 17.063757
A35: 45016 | B35: 3 | C35: 10.6 | D35: 10.82 | E35: -5.8 | F35: 0.7 | G35: -2.5 | H35: 12.7 | I35: 1.9 | J35: 10.84 | K35: -2.018112 | L35: -1.8 | M35: -1.4 | N35: 10 | O35: 5.1151266 | P35: 14.516471 | Q35: -4.3492631 | R35: 17.879691 | S35: 18.688837
A36: 44985 | B36: 2.4 | C36: 3.5 | D36: 12.18 | E36: -5.7 | F36: 1 | G36: -1.4 | H36: 12.9 | I36: 2.6 | J36: -2.86551 | K36: 4.241862 | L36: -3.6 | M36: -1.9 | N36: 9.9 | O36: 5.8439386 | P36: 15.649806 | Q36: -3.3241251 | R36: 22.984936 | S36: 15.696755
A37: 44957 | F37: 2.1 | G37: -0.8 | H37: 12.6 | I37: 0.1 | J37: -12.023126 | K37: -21.078238 | M37: -2.3 | N37: 9.4 | O37: 6.7368543 | P37: 14.917961 | Q37: -0.94058148 | R37: 18.169752 | S37: 14.945609
A38: 44926 | B38: 3.6 | C38: -1.8 | D38: 11.52 | E38: -10 | F38: 1.8 | G38: -0.7 | H38: 11.8 | I38: -3 | J38: -12.59 | K38: -7.53 | L38: -24.3 | M38: -2.3 | N38: 9.6 | O38: 3.7426301 | P38: 14.546514 | Q38: 2.501316 | R38: 17.739632 | S38: 13.275508
A39: 44895 | B39: 3.8 | C39: -5.9 | D39: 11.65 | E39: -9.8 | F39: 1.6 | G39: -1.3 | H39: 12.4 | I39: -2 | J39: -10.38 | K39: -11.14 | L39: -23.3 | M39: -2.3 | N39: 10 | O39: 4.6370812 | P39: 14.493838 | Q39: 5.8238041 | R39: 11.851642 | S39: 14.598686
A40: 44865 | B40: 4 | C40: -0.5 | D40: 11.39 | E40: -8.8 | F40: 2.1 | G40: -1.3 | H40: 11.8 | I40: -0.8 | J40: -1.84 | K40: -1.31 | L40: -22.3 | M40: -2.4 | N40: 10.3 | O40: 5.7594489 | P40: 13.475943 | Q40: 14.674844 | R40: 15.961803 | S40: 15.041913
A41: 44834 | B41: 3.9 | C41: 2.5 | D41: 11.2 | E41: -8 | F41: 2.8 | G41: 0.9 | H41: 12.1 | I41: 0.1 | J41: 4.45 | K41: -0.45 | L41: -22.2 | M41: -2.3 | N41: 10.6 | O41: 6.3859404 | P41: 13.90778 | Q41: 17.85236 | R41: 15.089835 | S41: 17.354008
A42: 44804 | B42: 3.6 | C42: 5.4 | D42: 10.37 | E42: -7.4 | F42: 2.5 | G42: 2.3 | H42: 12.2 | I42: -0.6 | J42: 5.87 | K42: -0.57 | L42: -23 | M42: -2.1 | N42: 10.5 | O42: 6.0553154 | P42: 14.037973 | Q42: 17.44197 | R42: 12.476089 | S42: 16.877466
A43: 44773 | B43: 3.5 | C43: 2.7 | D43: 9.58 | E43: -6.4 | F43: 2.7 | G43: 4.2 | H43: 12 | I43: -1 | J43: 16.42 | K43: 1.23 | L43: -23.1 | M43: -1.7 | N43: 10.7 | O43: 6.6839915 | P43: 15.746169 | Q43: 19.683225 | R43: 17.015478 | S43: 17.876235
A44: 44742 | B44: 3.4 | C44: 3.1 | D44: 9.25 | E44: -5.4 | F44: 2.5 | G44: 6.1 | H44: 11.4 | I44: 0.2 | J44: 15.38 | K44: -0.33 | L44: -22.2 | M44: -1.3 | N44: 10.8 | O44: 5.7877074 | P44: 16.269407 | Q44: 19.46599 | R44: 21.493178 | S44: 19.336991
A45: 44712 | B45: 3.3 | C45: -6.7 | D45: 8.16 | E45: -4 | F45: 2.1 | G45: 6.4 | H45: 11.1 | I45: -0.4 | J45: 15.45 | K45: 3.35 | L45: -23.6 | M45: -0.8 | N45: 10.5 | O45: 4.5846144 | P45: 13.937884 | Q45: 19.664266 | R45: 21.454759 | S45: 21.613439
A46: 44681 | B46: 4 | C46: -11.1 | D46: 8.26 | E46: -2.7 | F46: 2.1 | G46: 8 | H46: 10.5 | I46: -2.6 | J46: 2.23 | K46: 0.02 | L46: -20.9 | M46: -0.1 | N46: 10.2 | O46: 5.0736718 | P46: 13.506224 | Q46: 20.355124 | R46: 22.429977 | S46: 22.431798
A47: 44651 | B47: 6.5 | C47: -3.525412 | D47: 10.48 | E47: 0.7 | F47: 1.5 | G47: 8.3 | H47: 9.7 | I47: -0.5 | J47: 13.44 | K47: 0.45 | L47: -13.8 | M47: 0.7 | N47: 10.5 | O47: 4.6989143 | P47: 13.387134 | Q47: 21.294929 | R47: 31.999371 | S47: 23.58413
A48: 44620 | B48: 7.5 | C48: 6.7 | D48: 8.61 | E48: 3.7 | F48: 0.9 | G48: 8.8 | H48: 9.2 | I48: 0.2 | J48: 5.09 | K48: 11.36 | L48: -9.6 | M48: 1.2 | N48: 10.2 | O48: 4.7388786 | P48: 11.988938 | Q48: 24.720381 | R48: 29.710479 | S48: 24.157562
A49: 44592 | F49: 0.9 | G49: 9.1 | H49: 9.8 | I49: 0.1 | J49: 22.74 | K49: 20.79 | M49: 1.7 | N49: 10.5 | O49: -1.8710258 | P49: 10.656041 | Q49: 22.925168 | R49: 30.208953 | S49: 25.485629
A50: 44561 | B50: 9.6 | C50: 1.7 | D50: 0.21 | E50: 4.4 | F50: 1.5 | G50: 10.3 | H50: 9 | I50: 0.3 | J50: 20.58 | K50: 19.7 | L50: 1.9 | M50: 2 | N50: 10.3 | O50: 3.494729 | P50: 10.452251 | Q50: 19.785483 | R50: 33.295983 | S50: 28.361832
A51: 44530 | B51: 10.1 | C51: 3.9 | D51: -0.17 | E51: 6 | F51: 2.3 | G51: 12.9 | H51: 8.5 | I51: 0.1 | J51: 21.49 | K51: 31.32 | L51: 4.8 | M51: 2.4 | N51: 10.1 | O51: 3.0470255 | P51: 8.736978 | Q51: 24.12869 | R51: 30.199941 | S51: 28.269525
A52: 44500 | B52: 10.9 | C52: 4.9 | D52: 0.72 | E52: 7.2 | F52: 1.5 | G52: 13.5 | H52: 8.7 | I52: -0.8 | J52: 26.62 | K52: 20.01 | L52: 7.3 | M52: 2.8 | N52: 10 | O52: 2.7741642 | P52: 7.9918605 | Q52: 19.097833 | R52: 19.152645 | S52: 29.952621
A53: 44469 | B53: 11.8 | C53: 4.4 | D53: 1.52 | E53: 8.8 | F53: 0.7 | G53: 10.7 | H53: 8.3 | I53: -0.4 | J53: 27.7 | K53: 16.67 | L53: 11.3 | M53: 3.3 | N53: 10 | O53: 3.7079695 | P53: 7.8503846 | Q53: 15.495996 | R53: 19.352713 | S53: 29.754439
A54: 44439 | B54: 13.1 | C54: 2.5 | D54: 2.58 | E54: 10.9 | F54: 0.8 | G54: 9.5 | H54: 8.2 | I54: 0.1 | J54: 25.09 | K54: 32.41 | L54: 15.9 | M54: 3.7 | N54: 10.3 | O54: 4.2192 | P54: 7.2122963 | Q54: 15.080028 | R54: 28.747986 | S54: 33.308092
A55: 44408 | B55: 14.4 | C55: 8.5 | D55: 4.19 | E55: 12.7 | F55: 1 | G55: 9 | H55: 8.3 | I55: 0.4 | J55: 18.76 | K55: 28.27 | L55: 21.5 | M55: 4.1 | N55: 10.7 | O55: 4.9348382 | P55: 8.4168863 | Q55: 13.622061 | R55: 28.921429 | S55: 39.563329
A56: 44377 | B56: 15.9 | C56: 12.1 | D56: 7.15 | E56: 15 | F56: 1.1 | G56: 8.8 | H56: 8.6 | I56: 0.9 | J56: 31.69 | K56: 37.28 | L56: 27.7 | M56: 4.3 | N56: 11 | O56: 5.4874076 | P56: 10.73041 | Q56: 11.224469 | R56: 24.067375 | S56: 39.301622
A57: 44347 | B57: 17.8 | C57: 12.4 | D57: 10.36 | E57: 18.3 | F57: 1.3 | G57: 9 | H57: 8.3 | I57: 1 | J57: 27.52 | K57: 52.19 | L57: 36.3 | M57: 4.5 | N57: 11 | O57: 6.1463742 | P57: 11.596837 | Q57: 10.446306 | R57: 25.172459 | S57: 39.45505
A58: 44316 | B58: 20.3 | C58: 17.7 | D58: 16.91 | E58: 21.6 | F58: 0.9 | G58: 6.8 | H58: 8.1 | I58: 1.1 | J58: 31.89 | K58: 44.05 | L58: 48.1 | M58: 4.4 | N58: 11.7 | O58: 6.1863353 | P58: 13.395451 | Q58: 8.3904382 | R58: 16.505539 | S58: 41.98127
A59: 44286 | B59: 24.5 | C59: 34.2 | D59: 26.76 | E59: 25.6 | F59: 0.4 | G59: 4.4 | H59: 9.4 | I59: 1.9 | J59: 30.32 | K59: 39.12 | L59: 63.8 | M59: 4.4 | N59: 12.3 | O59: 7.1407459 | P59: 14.058277 | Q59: 10.08154 | R59: 16.075759 | S59: 37.126996
A60: 44255 | B60: 35.1 | C60: 33.8 | D60: 34.95 | E60: 38.3 | F60: -0.2 | G60: 1.7 | H60: 10.1 | I60: 0.6 | J60: 154.28 | K60: 18.97 | L60: 104.9 | M60: 4.1 | N60: 13.3 | O60: 7.3795325 | P60: 14.658421 | Q60: 9.954543 | R60: 8.2252691 | S60: 36.522822
A61: 44227 | F61: -0.3 | G61: 0.3 | H61: 9.4 | I61: 1.3 | J61: 24.48 | K61: 28.71 | M61: 3.7 | N61: 13 | O61: 14.670462 | P61: 14.787637 | Q61: 10.748602 | R61: 15.869919 | S61: 35.871413
A62: 44196 | B62: 2.8 | C62: 4.6 | D62: 3.41 | E62: 7 | F62: 0.2 | G62: -0.4 | H62: 10.1 | I62: 1.9 | J62: 18.04 | K62: 7.58 | L62: 2.6 | M62: 3.7 | N62: 13.3 | O62: 8.6060855 | P62: 17.660795 | Q62: 22.270842 | R62: 27.761562 | S62: 37.678907
A63: 44165 | B63: 2.3 | C63: 5 | D63: 3.32 | E63: 6.8 | F63: -0.5 | G63: -1.5 | H63: 10.7 | I63: 2.1 | J63: 20.53 | K63: 4.56 | L63: 1.3 | M63: 4 | N63: 13.6 | O63: 9.9816884 | P63: 18.403301 | Q63: 22.4176 | R63: 30.908021 | S63: 29.268367
A64: 44135 | B64: 1.8 | C64: 4.3 | D64: 3.01 | E64: 6.3 | F64: 0.5 | G64: -2.1 | H64: 10.5 | I64: 1.4 | J64: 10.92 | K64: 4.83 | L64: 0 | M64: 4.2 | N64: 13.683537 | O64: 9.1443222 | P64: 18.374104 | Q64: 24.745586 | R64: 37.622933 | S64: 26.617117
A65: 44104 | B65: 1.2 | C65: 3.3 | D65: 2.42 | E65: 5.6 | F65: 1.7 | G65: -2.1 | H65: 10.9 | I65: 1.5 | J65: 9.35 | K65: 13.47 | L65: -1.8 | M65: 4.5 | N65: 13.536403 | O65: 8.1082558 | P65: 18.471084 | Q65: 25.45154 | R65: 35.237683 | S65: 25.245364
A66: 44074 | B66: 0.4 | C66: 0.5 | D66: 2.02 | E66: 4.6 | F66: 2.4 | G66: -2 | H66: 10.4 | I66: 1 | J66: 9.08 | K66: -1.6 | L66: -3.3 | M66: 4.7 | N66: 13.27581 | O66: 7.990511 | P66: 17.371266 | Q66: 27.073851 | R66: 25.658599 | S66: 21.005414
A67: 44043 | B67: -0.4 | C67: -1.1 | D67: 1.19 | E67: 3.4 | F67: 2.7 | G67: -2.4 | H67: 10.7 | I67: 1.1 | J67: 6.79 | K67: -0.69 | L67: -5.8 | M67: 4.8 | N67: 12.855811 | O67: 6.8981118 | P67: 15.649414 | Q67: 27.939465 | R67: 22.059699 | S67: 14.414137
A68: 44012 | B68: -1.3 | C68: -1.8 | D68: -0.07 | E68: 1.9 | F68: 2.5 | G68: -3 | H68: 11.1 | I68: 0.9 | J68: 0.18 | K68: 3.29 | L68: -8.4 | M68: 4.9 | N68: 12.749171 | O68: 6.4509482 | P68: 14.527846 | Q68: 29.605559 | R68: 26.704948 | S68: 14.384148
A69: 43982 | B69: -2.8 | C69: -2.8 | D69: -3.31 | E69: -0.3 | F69: 2.4 | G69: -3.7 | H69: 11.1 | I69: 0.6 | J69: -3.5 | K69: -16.18 | L69: -12.3 | M69: 4.9 | N69: 12.530283 | O69: 6.752097 | P69: 13.352449 | Q69: 32.003721 | R69: 26.729766 | S69: 13.6666
A70: 43951 | B70: -4.9 | C70: -7.5 | D70: -8.78 | E70: -3.3 | F70: 3.3 | G70: -3.1 | H70: 11.1 | I70: 0.8 | J70: 3.04 | K70: -14.39 | L70: -19.3 | M70: 5.2 | N70: 11.996104 | O70: 5.4633865 | P70: 11.737968 | Q70: 33.805859 | R70: 34.343364 | S70: 10.93881
A71: 43921 | B71: -8.4 | C71: -15.8 | D71: -16.36 | E71: -7.7 | F71: 4.3 | G71: -1.5 | H71: 10.1 | I71: 2 | J71: -6.89 | K71: -1.36 | L71: -26.3 | M71: 5.4 | N71: 11.490402 | O71: 5.0175265 | P71: 12.400901 | Q71: 27.950292 | R71: 27.617697 | S71: 15.425135
A72: 43890 | B72: -13.5 | C72: -20.5 | D72: -26.86 | E72: -16.3 | F72: 5.2 | G72: -0.4 | H72: 8.8 | I72: -14.3 | J72: -40.61 | K72: 7.56 | L72: -39.9 | M72: 5.9 | N72: 10.653492 | O72: 4.8389057 | P72: 14.28969 | Q72: 24.042236 | R72: 33.671045 | S72: 13.117972
A73: 43861 | F73: 5.4 | G73: 0.1 | H73: 8.4 | I73: 0 | J73: -2.94 | K73: -12.66 | M73: 6.5 | N73: 10.707235 | O73: -0.019551408 | P73: 15.505696 | Q73: 21.804078 | R73: 25.569194 | S73: 11.458123
A74: 43830 | B74: 5.7 | C74: 8 | D74: 3.33 | E74: 9.9 | F74: 4.5 | G74: -0.5 | H74: 8.7 | I74: 0.2 | J74: 8.05 | K74: 16.67 | L74: -0.1 | M74: 6.8 | N74: 10.692756 | O74: 4.408894 | P74: 90.982115 | Q74: 15.706773 | R74: 19.42633 | S74: 11.012378
A75: 43799 | B75: 5.6 | C75: 8 | D75: 3.47 | E75: 10.2 | F75: 4.5 | G75: -1.4 | H75: 8.2 | I75: 0.2 | J75: -1.27 | K75: 1 | L75: 0.2 | M75: 7.3 | N75: 10.669227 | O75: 3.493634 | P75: 95.705247 | Q75: 12.363852 | R75: 27.988105 | S75: 16.051931
A76: 43769 | B76: 5.6 | C76: 7.2 | D76: 3.26 | E76: 10.3 | F76: 3.8 | G76: -1.6 | H76: 8.4 | I76: -0.7 | J76: -0.83 | K76: -6.11 | L76: 0.1 | M76: 8 | N76: 10.581898 | O76: 3.3354214 | P76: 98.314607 | Q76: 14.049922 | R76: 30.506236 | S76: 15.269854
A77: 43738 | B77: 5.6 | C77: 7.8 | D77: 3.44 | E77: 10.5 | F77: 3 | G77: -1.2 | H77: 8.4 | I77: -0.2 | J77: -3.19 | K77: -8.2 | L77: -0.1 | M77: 8.6 | N77: 10.666387 | O77: 3.4468555 | P77: 98.003654 | Q77: 16.323974 | R77: 33.741534 | S77: 14.171234
A78: 43708 | B78: 5.6 | C78: 7.5 | D78: 3.19 | E78: 10.5 | F78: 2.8 | G78: -0.8 | H78: 8.2 | I78: -0.5 | J78: -0.96 | K78: -5.5 | L78: -0.6 | M78: 9.1 | N78: 10.676172 | O78: 3.431655 | P78: 100.84424 | Q78: 13.439234 | R78: 34.215259 | S78: 11.819406
A79: 43677 | B79: 5.8 | C79: 7.6 | D79: 2.91 | E79: 10.6 | F79: 2.8 | G79: -0.3 | H79: 8.1 | I79: -0.3 | J79: 3.44 | K79: -4.9 | L79: -1.3 | M79: 10.1 | N79: 10.848681 | O79: 3.0596487 | P79: 100.06608 | Q79: 12.523707 | R79: 31.331664 | S79: 10.375162
A80: 43646 | B80: 6 | C80: 9.8 | D80: 2.95 | E80: 10.9 | F80: 2.7 | G80: 0 | H80: 8.5 | I80: -0.6 | J80: -1.45 | K80: -6.8 | L80: -1.8 | M80: 10.8 | N80: 11.193425 | O80: 4.3665228 | P80: 97.187426 | Q80: 14.77934 | R80: 24.121855 | S80: 6.2963484
A81: 43616 | B81: 6 | C81: 8.6 | D81: 2.6 | E81: 11.2 | F81: 2.7 | G81: 0.6 | H81: 8.5 | I81: -0.6 | J81: 1.1 | K81: -8.19 | L81: -1.6 | M81: 11.3 | N81: 11.025001 | O81: 3.4352501 | P81: 98.489572 | Q81: 11.604524 | R81: 23.136629 | S81: 2.1522722
A82: 43585 | B82: 6.2 | C82: 7.2 | D82: 2.97 | E82: 11.9 | F82: 2.5 | G82: 0.9 | H82: 8.5 | I82: 0.1 | J82: -2.68 | K82: 4.52 | L82: -0.3 | M82: 11.4 | N82: 10.805549 | O82: 2.886459 | P82: 97.854189 | Q82: 12.784927 | R82: 27.580495 | S82: 1.545063
A83: 43555 | B83: 6.5 | C83: 8.7 | D83: 2.95 | E83: 11.8 | F83: 2.3 | G83: 0.4 | H83: 8.6 | I83: 0.5 | J83: 13.99 | K83: -7.14 | L83: -0.9 | M83: 11.3 | N83: 11.162118 | O83: 4.5909498 | P83: 96.307566 | Q83: 16.240295 | R83: 35.870168 | S83: -1.3179039
A84: 43524 | B84: 5.3 | C84: 8.2 | D84: 2.5 | E84: 11.6 | F84: 1.5 | G84: 0.1 | H84: 8 | I84: -0.8 | J84: -20.65 | K84: -4.32 | L84: -3.6 | M84: 11.1 | N84: 10.64569 | O84: 1.9639813 | P84: 92.459421 | Q84: 20.244283 | R84: 49.967561 | S84: 2.103476
A85: 43496 | F85: 1.7 | G85: 0.1 | H85: 8.4 | I85: -0.5 | J85: 9.29 | K85: -0.82 | M85: 10.8 | N85: 10.851788 | O85: 0.44019193 | P85: 90.424879 | Q85: 23.456409 | R85: 68.985479 | S85: 4.0970163
A86: 43465 | B86: 6.2 | C86: 8.160814 | D86: 1.79 | E86: 9.5 | F86: 1.9 | G86: 0.9 | H86: 8.1 | I86: -0.6 | J86: -4.61 | K86: -7.67 | L86: 1.3 | M86: 10.6 | N86: 10.259731 | O86: 1.4519854 | P86: 11.42422 | Q86: 17.497807 | R86: 69.847649 | S86: 2.8314266
A87: 43434 | B87: 6.3 | C87: 8.1 | D87: 1.19 | E87: 9.7 | F87: 2.2 | G87: 2.7 | H87: 8 | I87: 0 | J87: 3.92 | K87: 2.84 | L87: 1.4 | M87: 10.3 | N87: 10.307183 | O87: 1.481354 | P87: 7.9892334 | Q87: 18.224488 | R87: 68.894292 | S87: 2.9102111
A88: 43404 | B88: 6.4 | C88: 8.6 | D88: 0.92 | E88: 9.7 | F88: 2.5 | G88: 3.3 | H88: 8 | I88: 0.2 | J88: 14.29 | K88: 20.38 | L88: 2.2 | M88: 9.7 | N88: 10.789977 | O88: 2.690454 | P88: 8.4199988 | Q88: 14.499398 | R88: 59.856164 | S88: 4.3679747
A89: 43373 | B89: 6.4 | C89: 9.2 | D89: 0.26 | E89: 9.9 | F89: 2.5 | G89: 3.6 | H89: 8.3 | I89: 0.8 | J89: 13.87 | K89: 14.4 | L89: 2.9 | M89: 8.9 | N89: 11.208433 | O89: 3.9993277 | P89: 9.2079232 | Q89: 12.312077 | R89: 48.481914 | S89: 2.6651083
A90: 43343 | B90: 6.5 | C90: 9 | D90: 0.66 | E90: 10.1 | F90: 2.3 | G90: 4.1 | H90: 8.2 | I90: 1.3 | J90: 9.55 | K90: 20.67 | L90: 4 | M90: 8 | N90: 11.516139 | O90: 3.9008241 | P90: 7.8480534 | Q90: 16.063437 | R90: 56.366375 | S90: -0.55982761
A91: 43312 | B91: 6.6 | C91: 8.8 | D91: 1.8 | E91: 10.2 | F91: 2.1 | G91: 4.6 | H91: 8.5 | I91: 1.2 | J91: 11.6 | K91: 26.92 | L91: 4.2 | M91: 6.6 | N91: 11.485086 | O91: 5.1205679 | P91: 7.2543076 | Q91: 17.252652 | R91: 56.855699 | S91: -5.3212833
A92: 43281 | B92: 6.7 | C92: 9 | D92: 3.31 | E92: 9.7 | F92: 1.9 | G92: 4.7 | H92: 8 | I92: 1.5 | J92: 10.7 | K92: 13.78 | L92: 3.3 | M92: 5.8 | N92: 11.76127 | O92: 6.6081326 | P92: 7.5792499 | Q92: 20.090858 | R92: 59.342455 | S92: -12.343939
A93: 43251 | B93: 6.9 | C93: 8.5 | D93: 5.02 | E93: 10.2 | F93: 1.8 | G93: 4.1 | H93: 8.3 | I93: 1.9 | J93: 11.9 | K93: 26.15 | L93: 2.9 | M93: 5.4 | N93: 12.199076 | O93: 6.0208587 | P93: 6.4118962 | Q93: 27.161341 | R93: 63.681292 | S93: -19.110156
A94: 43220 | B94: 6.9 | C94: 9.4 | D94: 7.63 | E94: 10.3 | F94: 1.8 | G94: 3.4 | H94: 8.3 | I94: 1.4 | J94: 11.91 | K94: 22.28 | L94: 1.3 | M94: 5.3 | N94: 12.652969 | O94: 7.1947692 | P94: 5.5384549 | Q94: 21.881849 | R94: 40.080628 | S94: -20.35527
A95: 43190 | B95: 6.8 | C95: 10.1 | D95: 8.34 | E95: 10.4 | F95: 2.1 | G95: 3.1 | H95: 8.2 | I95: 1.5 | J95: -2.98 | K95: 14.79 | L95: 3.6 | M95: 5.5 | N95: 12.690308 | O95: 7.113772 | P95: 6.1143251 | Q95: 21.06545 | R95: 34.970285 | S95: -20.151327
A96: 43159 | B96: 7.2 | C96: 9.7 | D96: 11.34 | E96: 9.9 | F96: 2.9 | G96: 3.7 | H96: 8.8 | I96: 0.3 | J96: 43.5 | K96: 6.59 | L96: 4.1 | M96: 5.8 | N96: 13.388317 | O96: 8.5007437 | P96: 5.6483148 | Q96: 19.237748 | R96: 35.087648 | S96: -16.174197
A97: 43131 | F97: 1.5 | G97: 4.3 | H97: 8.6 | I97: 1.3 | J97: 10.65 | K97: 37.66 | M97: 5.4 | N97: 13.433579 | O97: 14.966502 | P97: 1.4269667 | Q97: 28.01141 | R97: 40.265893 | S97: -15.295265
A98: 43100 | B98: 6.6 | C98: 9.4 | D98: 14.9312 | E98: 7 | F98: 1.8 | G98: 4.9 | H98: 8.1 | I98: 1.6 | J98: 10.73 | K98: 4.84 | L98: 7.7 | M98: 5.8 | N98: 15.321147 | O98: 11.762832 | P98: 1.9337336 | Q98: 30.052095 | R98: 38.31583 | S98: -11.299125
A99: 43069 | B99: 6.6 | C99: 10.2 | D99: 15.8284 | E99: 7.5 | F99: 1.7 | G99: 5.8 | H99: 9.1 | I99: 1.8 | J99: 11.51 | K99: 17.9 | L99: 7.9 | M99: 5.5 | N99: 15.535774 | O99: 12.654356 | P99: 6.4412431 | Q99: 25.585695 | R99: 25.285196 | S99: -14.385833
A100: 43039 | B100: 6.7 | C100: 10 | D100: 15.8539 | E100: 7.8 | F100: 1.9 | G100: 6.9 | H100: 8.9 | I100: 1.6 | J100: 6.26 | K100: 17.36 | L100: 8.2 | M100: 5.7 | N100: 15.867627 | O100: 13.004831 | P100: 5.9344294 | Q100: 25.527189 | R100: 34.065989 | S100: -20.896409
...

Sheet 月频数据发布日期
B1: 工业增加值同比 | C1: 社会消费品零售总额同比 | D1: 固定资产投资完成额:基础设施建设:累计同比 | E1: 房地产开发投资完成额:累计同比 | F1: CPI同比 | G1: PPI同比 | H1: 社融同比 | I1: M1同比 | J1: M2同比 | K1: PMI-50 | L1: 进口金额 | M1: 出口金额 | N1: 商业银行托管同比 | O1: 广义基金托管同比 | P1: 证券公司托管同比 | Q1: 保险托管同比
A2: 46022 | B2: 46041 | C2: 46041 | D2: 46041 | E2: 46041 | F2: 46031 | G2: 46031 | H2: 46037 | I2: 46037 | J2: 46037 | K2: 46022 | L2: 46036 | M2: 46036 | N2: 46037 | O2: 46037 | P2: 46037 | Q2: 46037
A3: 45991 | B3: 46006 | C3: 46006 | D3: 46006 | E3: 46006 | F3: 46001 | G3: 46001 | H3: 46006 | I3: 46006 | J3: 46006 | K3: 45991 | L3: 45999 | M3: 45999 | N3: 46010 | O3: 46010 | P3: 46010 | Q3: 46010
A4: 45961 | B4: 45975 | C4: 45975 | D4: 45975 | E4: 45975 | F4: 45970 | G4: 45970 | H4: 45974 | I4: 45974 | J4: 45974 | K4: 45961 | L4: 45968 | M4: 45968 | N4: 45978 | O4: 45978 | P4: 45978 | Q4: 45978
A5: 45930 | B5: 45950 | C5: 45950 | D5: 45950 | E5: 45950 | F5: 45945 | G5: 45945 | H5: 45945 | I5: 45945 | J5: 45945 | K5: 45930 | L5: 45943 | M5: 45943 | N5: 45952 | O5: 45952 | P5: 45952 | Q5: 45952
A6: 45900 | B6: 45915 | C6: 45915 | D6: 45915 | E6: 45915 | F6: 45910 | G6: 45910 | H6: 45912 | I6: 45912 | J6: 45912 | K6: 45900 | L6: 45908 | M6: 45908 | N6: 45919 | O6: 45919 | P6: 45919 | Q6: 45919
A7: 45869 | B7: 45884 | C7: 45884 | D7: 45884 | E7: 45884 | F7: 45878 | G7: 45878 | H7: 45882 | I7: 45882 | J7: 45882 | K7: 45869 | L7: 45876 | M7: 45876 | N7: 45887 | O7: 45887 | P7: 45887 | Q7: 45887
A8: 45838 | B8: 45853 | C8: 45853 | D8: 45853 | E8: 45853 | F8: 45847 | G8: 45847 | H8: 45852 | I8: 45852 | J8: 45852 | K8: 45838 | L8: 45852 | M8: 45852 | N8: 45861 | O8: 45861 | P8: 45861 | Q8: 45861
A9: 45808 | B9: 45824 | C9: 45824 | D9: 45824 | E9: 45824 | F9: 45817 | G9: 45817 | H9: 45821 | I9: 45821 | J9: 45821 | K9: 45808 | L9: 45824 | M9: 45824 | N9: 45826 | O9: 45826 | P9: 45826 | Q9: 45826
A10: 45777 | B10: 45796 | C10: 45796 | D10: 45796 | E10: 45796 | F10: 45787 | G10: 45787 | H10: 45791 | I10: 45791 | J10: 45791 | K10: 45777 | L10: 45786 | M10: 45786 | N10: 45798 | O10: 45798 | P10: 45798 | Q10: 45798
A11: 45747 | B11: 45763 | C11: 45763 | D11: 45763 | E11: 45763 | F11: 45757 | G11: 45757 | H11: 45760 | I11: 45760 | J11: 45760 | K11: 45747 | L11: 45761 | M11: 45761 | N11: 45770 | O11: 45770 | P11: 45770 | Q11: 45770
A12: 45716 | B12: 45733 | C12: 45733 | D12: 45733 | E12: 45733 | F12: 45725 | G12: 45725 | H12: 45730 | I12: 45730 | J12: 45730 | K12: 45717 | L12: 45734 | M12: 45734 | N12: 45735 | O12: 45735 | P12: 45735 | Q12: 45735
A13: 45688 | B13: 45733 | C13: 45733 | D13: 45733 | E13: 45733 | F13: 45697 | G13: 45697 | H13: 45702 | I13: 45702 | J13: 45702 | K13: 45684 | L13: 45734 | M13: 45734 | N13: 45707 | O13: 45707 | P13: 45707 | Q13: 45707
A14: 45657 | B14: 45674 | C14: 45674 | D14: 45674 | E14: 45674 | F14: 45667 | G14: 45667 | H14: 45671 | I14: 45671 | J14: 45671 | K14: 45657 | L14: 45675 | M14: 45675 | N14: 45675 | O14: 45675 | P14: 45675 | Q14: 45675
A15: 45626 | B15: 45642 | C15: 45642 | D15: 45642 | E15: 45642 | F15: 45635 | G15: 45635 | H15: 45639 | I15: 45639 | J15: 45639 | K15: 45626 | L15: 45644 | M15: 45644 | N15: 2024-12-20 | O15: 2024-12-20 | P15: 2024-12-20 | Q15: 2024-12-20
A16: 45596 | B16: 45611 | C16: 45611 | D16: 45611 | E16: 45611 | F16: 45605 | G16: 45605 | H16: 45607 | I16: 45607 | J16: 45607 | K16: 45596 | L16: 45614 | M16: 45614 | N16: 2024-11-20 | O16: 2024-11-20 | P16: 2024-11-20 | Q16: 2024-11-20
A17: 45565 | B17: 45583 | C17: 45583 | D17: 45583 | E17: 45583 | F17: 45578 | G17: 45578 | H17: 45579 | I17: 45579 | J17: 45579 | K17: 45565 | L17: 45583 | M17: 45583 | N17: 2024-10-20 | O17: 2024-10-20 | P17: 2024-10-20 | Q17: 2024-10-20
A18: 45535 | B18: 45549 | C18: 45549 | D18: 45549 | E18: 45549 | F18: 2024-09-09 | G18: 2024-09-09 | H18: 2024-09-13 | I18: 2024-09-13 | J18: 2024-09-13 | K18: 45535 | L18: 45553 | M18: 45553 | N18: 2024-09-20 | O18: 2024-09-20 | P18: 2024-09-20 | Q18: 2024-09-20
A19: 45504 | B19: 45519 | C19: 45519 | D19: 45519 | E19: 45519 | F19: 2024-08-09 | G19: 2024-08-09 | H19: 2024-08-13 | I19: 2024-08-13 | J19: 2024-08-13 | K19: 45504 | L19: 45522 | M19: 45522 | N19: 2024-08-20 | O19: 2024-08-20 | P19: 2024-08-20 | Q19: 2024-08-20
A20: 45473 | B20: 45488 | C20: 45488 | D20: 45488 | E20: 45488 | F20: 2024-07-10 | G20: 2024-07-10 | H20: 2024-07-12 | I20: 2024-07-12 | J20: 2024-07-12 | K20: 45473 | L20: 45491 | M20: 45491 | N20: 2024-07-20 | O20: 2024-07-20 | P20: 2024-07-20 | Q20: 2024-07-20
A21: 45443 | B21: 45460 | C21: 45460 | D21: 45460 | E21: 45460 | F21: 2024-06-12 | G21: 2024-06-12 | H21: 2024-06-14 | I21: 2024-06-14 | J21: 2024-06-14 | K21: 45443 | L21: 45461 | M21: 45461 | N21: 2024-06-20 | O21: 2024-06-20 | P21: 2024-06-20 | Q21: 2024-06-20
A22: 45412 | B22: 45429 | C22: 45429 | D22: 45429 | E22: 45429 | F22: 2024-05-11 | G22: 2024-05-11 | H22: 2024-05-11 | I22: 2024-05-11 | J22: 2024-05-11 | K22: 45412 | L22: 45430 | M22: 45430 | N22: 2024-05-20 | O22: 2024-05-20 | P22: 2024-05-20 | Q22: 2024-05-20
A23: 45382 | B23: 45398 | C23: 45398 | D23: 45398 | E23: 45398 | F23: 2024-04-11 | G23: 2024-04-11 | H23: 2024-04-12 | I23: 2024-04-12 | J23: 2024-04-12 | K23: 45382 | L23: 45400 | M23: 45400 | N23: 2024-04-20 | O23: 2024-04-20 | P23: 2024-04-20 | Q23: 2024-04-20
A24: 45351 | B24: 45369 | C24: 45369 | D24: 45369 | E24: 45369 | F24: 2024-03-09 | G24: 2024-03-09 | H24: 2024-03-15 | I24: 2024-03-15 | J24: 2024-03-15 | K24: 45352 | L24: 45369 | M24: 45369 | N24: 2024-03-20 | O24: 2024-03-20 | P24: 2024-03-20 | Q24: 2024-03-20
A25: 45322 | B25: 45309 | C25: 45309 | D25: 45309 | E25: 45309 | F25: 2024-02-08 | G25: 2024-02-08 | H25: 2024-02-09 | I25: 2024-02-09 | J25: 2024-02-09 | K25: 45322 | L25: 45369 | M25: 45369 | N25: 2024-02-20 | O25: 2024-02-20 | P25: 2024-02-20 | Q25: 2024-02-20
A26: 45291 | B26: 45308 | C26: 45308 | D26: 45308 | E26: 45308 | F26: 2024-01-12 | G26: 2024-01-12 | H26: 2024-01-12 | I26: 2024-01-12 | J26: 2024-01-12 | K26: 45291 | L26: 45309 | M26: 45309 | N26: 2024-01-20 | O26: 2024-01-20 | P26: 2024-01-20 | Q26: 2024-01-20
A27: 45260 | B27: 45275 | C27: 45275 | D27: 45275 | E27: 45275 | F27: 2023-12-09 | G27: 2023-12-09 | H27: 2023-12-13 | I27: 2023-12-13 | J27: 2023-12-13 | K27: 45260 | L27: 45278 | M27: 45278 | N27: 2023-12-20 | O27: 2023-12-20 | P27: 2023-12-20 | Q27: 2023-12-20
A28: 45230 | B28: 2023-11-15 | C28: 2023-11-15 | D28: 2023-11-15 | E28: 2023-11-15 | F28: 2023-11-09 | G28: 2023-11-09 | H28: 2023-11-13 | I28: 2023-11-13 | J28: 2023-11-13 | K28: 45230 | L28: 45248 | M28: 45248 | N28: 2023-11-20 | O28: 2023-11-20 | P28: 2023-11-20 | Q28: 2023-11-20
A29: 45199 | B29: 2023-10-18 | C29: 2023-10-18 | D29: 2023-10-18 | E29: 2023-10-18 | F29: 2023-10-13 | G29: 2023-10-13 | H29: 2023-10-13 | I29: 2023-10-13 | J29: 2023-10-13 | K29: 45199 | L29: 45217 | M29: 45217 | N29: 2023-10-20 | O29: 2023-10-20 | P29: 2023-10-20 | Q29: 2023-10-20
A30: 45169 | B30: 2023-09-15 | C30: 2023-09-15 | D30: 2023-09-15 | E30: 2023-09-15 | F30: 2023-09-09 | G30: 2023-09-09 | H30: 2023-09-11 | I30: 2023-09-11 | J30: 2023-09-11 | K30: 45169 | L30: 45187 | M30: 45187 | N30: 2023-09-20 | O30: 2023-09-20 | P30: 2023-09-20 | Q30: 2023-09-20
A31: 45138 | B31: 2023-08-15 | C31: 2023-08-15 | D31: 2023-08-15 | E31: 2023-08-15 | F31: 2023-08-09 | G31: 2023-08-09 | H31: 2023-08-11 | I31: 2023-08-11 | J31: 2023-08-11 | K31: 45138 | L31: 45156 | M31: 45156 | N31: 2023-08-20 | O31: 2023-08-20 | P31: 2023-08-20 | Q31: 2023-08-20
A32: 45107 | B32: 2023-07-17 | C32: 2023-07-17 | D32: 2023-07-17 | E32: 2023-07-17 | F32: 2023-07-10 | G32: 2023-07-10 | H32: 2023-07-11 | I32: 2023-07-11 | J32: 2023-07-11 | K32: 45107 | L32: 45125 | M32: 45125 | N32: 2023-07-20 | O32: 2023-07-20 | P32: 2023-07-20 | Q32: 2023-07-20
A33: 45077 | B33: 2023-06-15 | C33: 2023-06-15 | D33: 2023-06-15 | E33: 2023-06-15 | F33: 2023-06-09 | G33: 2023-06-09 | H33: 2023-06-13 | I33: 2023-06-13 | J33: 2023-06-13 | K33: 45077 | L33: 45095 | M33: 45095 | N33: 2023-06-20 | O33: 2023-06-20 | P33: 2023-06-20 | Q33: 2023-06-20
A34: 45046 | B34: 2023-05-16 | C34: 2023-05-16 | D34: 2023-05-16 | E34: 2023-05-16 | F34: 2023-05-11 | G34: 2023-05-11 | H34: 2023-05-11 | I34: 2023-05-11 | J34: 2023-05-11 | K34: 45046 | L34: 45064 | M34: 45064 | N34: 2023-05-20 | O34: 2023-05-20 | P34: 2023-05-20 | Q34: 2023-05-20
A35: 45016 | B35: 2023-04-18 | C35: 2023-04-18 | D35: 2023-04-18 | E35: 2023-04-18 | F35: 2023-04-11 | G35: 2023-04-11 | H35: 2023-04-11 | I35: 2023-04-11 | J35: 2023-04-11 | K35: 45016 | L35: 45034 | M35: 45034 | N35: 2023-04-20 | O35: 2023-04-20 | P35: 2023-04-20 | Q35: 2023-04-20
A36: 44985 | B36: 2023-03-15 | C36: 2023-03-15 | D36: 2023-03-15 | E36: 2023-03-15 | F36: 2023-03-09 | G36: 2023-03-09 | H36: 2023-03-10 | I36: 2023-03-10 | J36: 2023-03-10 | K36: 44986 | L36: 45003 | M36: 45003 | N36: 2023-03-20 | O36: 2023-03-20 | P36: 2023-03-20 | Q36: 2023-03-20
A37: 44957 | B37: 44944 | C37: 44944 | D37: 44944 | E37: 44944 | F37: 2023-02-10 | G37: 2023-02-10 | H37: 2023-02-10 | I37: 2023-02-10 | J37: 2023-02-10 | K37: 44957 | L37: 45003 | M37: 45003 | N37: 2023-02-20 | O37: 2023-02-20 | P37: 2023-02-20 | Q37: 2023-02-20
A38: 44926 | B38: 2023-01-17 | C38: 2023-01-17 | D38: 2023-01-17 | E38: 2023-01-17 | F38: 2023-01-12 | G38: 2023-01-12 | H38: 2023-01-10 | I38: 2023-01-10 | J38: 2023-01-10 | K38: 44926 | L38: 44944 | M38: 44944 | N38: 2023-01-20 | O38: 2023-01-20 | P38: 2023-01-20 | Q38: 2023-01-20
A39: 44895 | B39: 2022-12-15 | C39: 2022-12-15 | D39: 2022-12-15 | E39: 2022-12-15 | F39: 2022-12-09 | G39: 2022-12-09 | H39: 2022-12-12 | I39: 2022-12-12 | J39: 2022-12-12 | K39: 44895 | L39: 44913 | M39: 44913 | N39: 2022-12-20 | O39: 2022-12-20 | P39: 2022-12-20 | Q39: 2022-12-20
A40: 44865 | B40: 2022-11-15 | C40: 2022-11-15 | D40: 2022-11-15 | E40: 2022-11-15 | F40: 2022-11-09 | G40: 2022-11-09 | H40: 2022-11-10 | I40: 2022-11-10 | J40: 2022-11-10 | K40: 44865 | L40: 44883 | M40: 44883 | N40: 2022-11-20 | O40: 2022-11-20 | P40: 2022-11-20 | Q40: 2022-11-20
A41: 44834 | B41: 2022-10-24 | C41: 2022-10-24 | D41: 2022-10-24 | E41: 2022-10-24 | F41: 2022-10-14 | G41: 2022-10-14 | H41: 2022-10-11 | I41: 2022-10-11 | J41: 2022-10-11 | K41: 44834 | L41: 44852 | M41: 44852 | N41: 2022-10-20 | O41: 2022-10-20 | P41: 2022-10-20 | Q41: 2022-10-20
A42: 44804 | B42: 2022-09-16 | C42: 2022-09-16 | D42: 2022-09-16 | E42: 2022-09-16 | F42: 2022-09-09 | G42: 2022-09-09 | H42: 2022-09-09 | I42: 2022-09-09 | J42: 2022-09-09 | K42: 44804 | L42: 44822 | M42: 44822 | N42: 2022-09-20 | O42: 2022-09-20 | P42: 2022-09-20 | Q42: 2022-09-20
A43: 44773 | B43: 2022-08-15 | C43: 2022-08-15 | D43: 2022-08-15 | E43: 2022-08-15 | F43: 2022-08-10 | G43: 2022-08-10 | H43: 2022-08-12 | I43: 2022-08-12 | J43: 2022-08-12 | K43: 44773 | L43: 44791 | M43: 44791 | N43: 2022-08-20 | O43: 2022-08-20 | P43: 2022-08-20 | Q43: 2022-08-20
A44: 44742 | B44: 2022-07-15 | C44: 2022-07-15 | D44: 2022-07-15 | E44: 2022-07-15 | F44: 2022-07-09 | G44: 2022-07-09 | H44: 2022-07-11 | I44: 2022-07-11 | J44: 2022-07-11 | K44: 44742 | L44: 44760 | M44: 44760 | N44: 2022-07-20 | O44: 2022-07-20 | P44: 2022-07-20 | Q44: 2022-07-20
A45: 44712 | B45: 2022-06-15 | C45: 2022-06-15 | D45: 2022-06-15 | E45: 2022-06-15 | F45: 2022-06-10 | G45: 2022-06-10 | H45: 2022-06-10 | I45: 2022-06-10 | J45: 2022-06-10 | K45: 44712 | L45: 44730 | M45: 44730 | N45: 2022-06-20 | O45: 2022-06-20 | P45: 2022-06-20 | Q45: 2022-06-20
A46: 44681 | B46: 2022-05-16 | C46: 2022-05-16 | D46: 2022-05-16 | E46: 2022-05-16 | F46: 2022-05-11 | G46: 2022-05-11 | H46: 2022-05-13 | I46: 2022-05-13 | J46: 2022-05-13 | K46: 44681 | L46: 44699 | M46: 44699 | N46: 2022-05-20 | O46: 2022-05-20 | P46: 2022-05-20 | Q46: 2022-05-20
A47: 44651 | B47: 2022-04-18 | C47: 2022-04-18 | D47: 2022-04-18 | E47: 2022-04-18 | F47: 2022-04-11 | G47: 2022-04-11 | H47: 2022-04-11 | I47: 2022-04-11 | J47: 2022-04-11 | K47: 44651 | L47: 44669 | M47: 44669 | N47: 2022-04-20 | O47: 2022-04-20 | P47: 2022-04-20 | Q47: 2022-04-20
A48: 44620 | B48: 2022-03-15 | C48: 2022-03-15 | D48: 2022-03-15 | E48: 2022-03-15 | F48: 2022-03-09 | G48: 2022-03-09 | H48: 2022-03-11 | I48: 2022-03-11 | J48: 2022-03-11 | K48: 44621 | L48: 44638 | M48: 44638 | N48: 2022-03-20 | O48: 2022-03-20 | P48: 2022-03-20 | Q48: 2022-03-20
A49: 44592 | B49: 44579 | C49: 44579 | D49: 44579 | E49: 44579 | F49: 2022-02-16 | G49: 2022-02-16 | H49: 2022-02-10 | I49: 2022-02-10 | J49: 2022-02-10 | K49: 44591 | L49: 44638 | M49: 44638 | N49: 2022-02-20 | O49: 2022-02-20 | P49: 2022-02-20 | Q49: 2022-02-20
A50: 44561 | B50: 2022-01-17 | C50: 2022-01-17 | D50: 2022-01-17 | E50: 2022-01-17 | F50: 2022-01-12 | G50: 2022-01-12 | H50: 2022-01-12 | I50: 2022-01-12 | J50: 2022-01-12 | K50: 44561 | L50: 44579 | M50: 44579 | N50: 2022-01-20 | O50: 2022-01-20 | P50: 2022-01-20 | Q50: 2022-01-20
A51: 44530 | B51: 2021-12-15 | C51: 2021-12-15 | D51: 2021-12-15 | E51: 2021-12-15 | F51: 2021-12-09 | G51: 2021-12-09 | H51: 2021-12-09 | I51: 2021-12-09 | J51: 2021-12-09 | K51: 44530 | L51: 44548 | M51: 44548 | N51: 2021-12-20 | O51: 2021-12-20 | P51: 2021-12-20 | Q51: 2021-12-20
A52: 44500 | B52: 2021-11-15 | C52: 2021-11-15 | D52: 2021-11-15 | E52: 2021-11-15 | F52: 2021-11-10 | G52: 2021-11-10 | H52: 2021-11-10 | I52: 2021-11-10 | J52: 2021-11-10 | K52: 44500 | L52: 44518 | M52: 44518 | N52: 2021-11-20 | O52: 2021-11-20 | P52: 2021-11-20 | Q52: 2021-11-20
A53: 44469 | B53: 2021-10-18 | C53: 2021-10-18 | D53: 2021-10-18 | E53: 2021-10-18 | F53: 2021-10-14 | G53: 2021-10-14 | H53: 2021-10-13 | I53: 2021-10-13 | J53: 2021-10-13 | K53: 44469 | L53: 44487 | M53: 44487 | N53: 2021-10-20 | O53: 2021-10-20 | P53: 2021-10-20 | Q53: 2021-10-20
A54: 44439 | B54: 2021-09-15 | C54: 2021-09-15 | D54: 2021-09-15 | E54: 2021-09-15 | F54: 2021-09-09 | G54: 2021-09-09 | H54: 2021-09-10 | I54: 2021-09-10 | J54: 2021-09-10 | K54: 44439 | L54: 44457 | M54: 44457 | N54: 2021-09-20 | O54: 2021-09-20 | P54: 2021-09-20 | Q54: 2021-09-20
A55: 44408 | B55: 2021-08-16 | C55: 2021-08-16 | D55: 2021-08-16 | E55: 2021-08-16 | F55: 2021-08-09 | G55: 2021-08-09 | H55: 2021-08-11 | I55: 2021-08-11 | J55: 2021-08-11 | K55: 44408 | L55: 44457 | M55: 44457 | N55: 2021-08-20 | O55: 2021-08-20 | P55: 2021-08-20 | Q55: 2021-08-20
A56: 44377 | B56: 2021-07-15 | C56: 2021-07-15 | D56: 2021-07-15 | E56: 2021-07-15 | F56: 2021-07-09 | G56: 2021-07-09 | H56: 2021-07-09 | I56: 2021-07-09 | J56: 2021-07-09 | K56: 44377 | L56: 44395 | M56: 44395 | N56: 2021-07-20 | O56: 2021-07-20 | P56: 2021-07-20 | Q56: 2021-07-20
A57: 44347 | B57: 2021-06-16 | C57: 2021-06-16 | D57: 2021-06-16 | E57: 2021-06-16 | F57: 2021-06-09 | G57: 2021-06-09 | H57: 2021-06-10 | I57: 2021-06-10 | J57: 2021-06-10 | K57: 44347 | L57: 44365 | M57: 44365 | N57: 2021-06-20 | O57: 2021-06-20 | P57: 2021-06-20 | Q57: 2021-06-20
A58: 44316 | B58: 2021-05-17 | C58: 2021-05-17 | D58: 2021-05-17 | E58: 2021-05-17 | F58: 2021-05-11 | G58: 2021-05-11 | H58: 2021-05-12 | I58: 2021-05-12 | J58: 2021-05-12 | K58: 44316 | L58: 44365 | M58: 44365 | N58: 2021-05-20 | O58: 2021-05-20 | P58: 2021-05-20 | Q58: 2021-05-20
A59: 44286 | B59: 2021-04-16 | C59: 2021-04-16 | D59: 2021-04-16 | E59: 2021-04-16 | F59: 2021-04-09 | G59: 2021-04-09 | H59: 2021-04-12 | I59: 2021-04-12 | J59: 2021-04-12 | K59: 44286 | L59: 44304 | M59: 44304 | N59: 2021-04-20 | O59: 2021-04-20 | P59: 2021-04-20 | Q59: 2021-04-20
A60: 44255 | B60: 2021-03-15 | C60: 2021-03-15 | D60: 2021-03-15 | E60: 2021-03-15 | F60: 2021-03-10 | G60: 2021-03-10 | H60: 2021-03-10 | I60: 2021-03-10 | J60: 2021-03-10 | K60: 44255 | L60: 44273 | M60: 44273 | N60: 2021-03-20 | O60: 2021-03-20 | P60: 2021-03-20 | Q60: 2021-03-20
A61: 44227 | B61: 44215 | C61: 44215 | D61: 44215 | E61: 44215 | F61: 2021-02-10 | G61: 2021-02-10 | H61: 2021-02-09 | I61: 2021-02-09 | J61: 2021-02-09 | K61: 44227 | L61: 44273 | M61: 44273 | N61: 2021-02-20 | O61: 2021-02-20 | P61: 2021-02-20 | Q61: 2021-02-20
A62: 44196 | B62: 2021-01-18 | C62: 2021-01-18 | D62: 2021-01-18 | E62: 2021-01-18 | F62: 2021-01-11 | G62: 2021-01-11 | H62: 2021-01-12 | I62: 2021-01-12 | J62: 2021-01-12 | K62: 44196 | L62: 44214 | M62: 44214 | N62: 2021-01-20 | O62: 2021-01-20 | P62: 2021-01-20 | Q62: 2021-01-20
A63: 44165 | B63: 2020-12-15 | C63: 2020-12-15 | D63: 2020-12-15 | E63: 2020-12-15 | F63: 2020-12-09 | G63: 2020-12-09 | H63: 2020-12-09 | I63: 2020-12-09 | J63: 2020-12-09 | K63: 44165 | L63: 44188 | M63: 44188 | N63: 2020-12-20 | O63: 2020-12-20 | P63: 2020-12-20 | Q63: 2020-12-20
A64: 44135 | B64: 44151 | C64: 44151 | D64: 44151 | E64: 44151 | F64: 2020-11-10 | G64: 2020-11-10 | H64: 2020-11-11 | I64: 2020-11-11 | J64: 2020-11-11 | K64: 44135 | L64: 44158 | M64: 44158 | N64: 2020-11-20 | O64: 2020-11-20 | P64: 2020-11-20 | Q64: 2020-11-20
A65: 44104 | B65: 44123 | C65: 44123 | D65: 44123 | E65: 44123 | F65: 2020-10-15 | G65: 2020-10-15 | H65: 2020-10-14 | I65: 2020-10-14 | J65: 2020-10-14 | K65: 44104 | L65: 44127 | M65: 44127 | N65: 2020-10-20 | O65: 2020-10-20 | P65: 2020-10-20 | Q65: 2020-10-20
A66: 44074 | B66: 44089 | C66: 44089 | D66: 44089 | E66: 44089 | F66: 2020-09-09 | G66: 2020-09-09 | H66: 2020-09-11 | I66: 2020-09-11 | J66: 2020-09-11 | K66: 44074 | L66: 44097 | M66: 44097 | N66: 2020-09-20 | O66: 2020-09-20 | P66: 2020-09-20 | Q66: 2020-09-20
A67: 44043 | B67: 44057 | C67: 44057 | D67: 44057 | E67: 44057 | F67: 2020-08-10 | G67: 2020-08-10 | H67: 2020-08-11 | I67: 2020-08-11 | J67: 2020-08-11 | K67: 44043 | L67: 44066 | M67: 44066 | N67: 2020-08-20 | O67: 2020-08-20 | P67: 2020-08-20 | Q67: 2020-08-20
A68: 44012 | B68: 44028 | C68: 44028 | D68: 44028 | E68: 44028 | F68: 2020-07-09 | G68: 2020-07-09 | H68: 2020-07-10 | I68: 2020-07-10 | J68: 2020-07-10 | K68: 44012 | L68: 44035 | M68: 44035 | N68: 2020-07-20 | O68: 2020-07-20 | P68: 2020-07-20 | Q68: 2020-07-20
A69: 43982 | B69: 43997 | C69: 43997 | D69: 43997 | E69: 43997 | F69: 2020-06-10 | G69: 2020-06-10 | H69: 2020-06-10 | I69: 2020-06-10 | J69: 2020-06-10 | K69: 43982 | L69: 44005 | M69: 44005 | N69: 2020-06-20 | O69: 2020-06-20 | P69: 2020-06-20 | Q69: 2020-06-20
A70: 43951 | B70: 43966 | C70: 43966 | D70: 43966 | E70: 43966 | F70: 2020-05-12 | G70: 2020-05-12 | H70: 2020-05-11 | I70: 2020-05-11 | J70: 2020-05-11 | K70: 43951 | L70: 43974 | M70: 43974 | N70: 2020-05-20 | O70: 2020-05-20 | P70: 2020-05-20 | Q70: 2020-05-20
A71: 43921 | B71: 43938 | C71: 43938 | D71: 43938 | E71: 43938 | F71: 2020-04-10 | G71: 2020-04-10 | H71: 2020-04-10 | I71: 2020-04-10 | J71: 2020-04-10 | K71: 43921 | L71: 43944 | M71: 43944 | N71: 2020-04-20 | O71: 2020-04-20 | P71: 2020-04-20 | Q71: 2020-04-20
A72: 43890 | B72: 43906 | C72: 43906 | D72: 43906 | E72: 43906 | F72: 2020-03-10 | G72: 2020-03-10 | H72: 2020-03-11 | I72: 2020-03-11 | J72: 2020-03-11 | K72: 43890 | L72: 44215 | M72: 44215 | N72: 2020-03-20 | O72: 2020-03-20 | P72: 2020-03-20 | Q72: 2020-03-20
A73: 43861 | B73: 43848 | C73: 43848 | D73: 43848 | E73: 43848 | F73: 2020-02-10 | G73: 2020-02-10 | H73: 2020-02-20 | I73: 2020-02-20 | J73: 2020-02-20 | K73: 43861 | L73: 44215 | M73: 44215 | N73: 2020-02-20 | O73: 2020-02-20 | P73: 2020-02-20 | Q73: 2020-02-20
A74: 43830 | B74: 43847 | C74: 43847 | D74: 43847 | E74: 43847 | F74: 2020-01-09 | G74: 2020-01-09 | H74: 2020-01-16 | I74: 2020-01-16 | J74: 2020-01-16 | K74: 43830 | L74: 43853 | M74: 43853 | N74: 2020-01-20 | O74: 2020-01-20 | P74: 2020-01-20 | Q74: 2020-01-20
A75: 43799 | B75: 43815 | C75: 43815 | D75: 43815 | E75: 43815 | F75: 2019-12-10 | G75: 2019-12-10 | H75: 2019-12-10 | I75: 2019-12-10 | J75: 2019-12-10 | K75: 43799 | L75: 43822 | M75: 43822 | N75: 2019-12-20 | O75: 2019-12-20 | P75: 2019-12-20 | Q75: 2019-12-20
... A97: 43131 | B97: 43119 | C97: 43119 | D97: 43119 | E97: 43119 | F97: 2018-02-09 | G97: 2018-02-09 | H97: 2018-02-12 | I97: 2018-02-12 | J97: 2018-02-12 | K97: 43131 | L97: 43154 | M97: 43154 | N97: 2018-02-20 | O97: 2018-02-20 | P97: 2018-02-20 | Q97: 2018-02-20
A98: 43100 | B98: 2018-01-18 | C98: 2018-01-18 | D98: 2018-01-18 | E98: 2018-01-18 | F98: 2018-01-10 | G98: 2018-01-10 | H98: 2018-01-12 | I98: 2018-01-12 | J98: 2018-01-12 | K98: 43100 | L98: 43123 | M98: 43123 | N98: 2018-01-20 | O98: 2018-01-20 | P98: 2018-01-20 | Q98: 2018-01-20
A99: 43069 | B99: 2017-12-14 | C99: 2017-12-14 | D99: 2017-12-14 | E99: 2017-12-14 | F99: 2017-12-09 | G99: 2017-12-09 | H99: 2017-12-11 | I99: 2017-12-11 | J99: 2017-12-11 | K99: 43069 | L99: 43092 | M99: 43092 | N99: 2017-12-20 | O99: 2017-12-20 | P99: 2017-12-20 | Q99: 2017-12-20
A100: 43039 | B100: 2017-11-14 | C100: 2017-11-14 | D100: 2017-11-14 | E100: 2017-11-14 | F100: 2017-11-09 | G100: 2017-11-09 | H100: 2017-11-13 | I100: 2017-11-13 | J100: 2017-11-13 | K100: 43039 | L100: 43062 | M100: 43062 | N100: 2017-11-20 | O100: 2017-11-20 | P100: 2017-11-20 | Q100: 2017-11-20
A101: 43008 | B101: 2017-10-19 | C101: 2017-10-19 | D101: 2017-10-19 | E101: 2017-10-19 | F101: 2017-10-16 | G101: 2017-10-16 | H101: 2017-10-14 | I101: 2017-10-14 | J101: 2017-10-14 | K101: 43008 | L101: 43031 | M101: 43031 | N101: 2017-10-20 | O101: 2017-10-20 | P101: 2017-10-20 | Q101: 2017-10-20
A102: 42978 | B102: 2017-09-14 | C102: 2017-09-14 | D102: 2017-09-14 | E102: 2017-09-14 | F102: 2017-09-09 | G102: 2017-09-09 | H102: 2017-09-15 | I102: 2017-09-15 | J102: 2017-09-15 | K102: 42978 | L102: 43001 | M102: 43001 | N102: 2017-09-20 | O102: 2017-09-20 | P102: 2017-09-20 | Q102: 2017-09-20
A103: 42947 | B103: 2017-08-14 | C103: 2017-08-14 | D103: 2017-08-14 | E103: 2017-08-14 | F103: 2017-08-09 | G103: 2017-08-09 | H103: 2017-08-15 | I103: 2017-08-15 | J103: 2017-08-15 | K103: 42947 | L103: 43001 | M103: 43001 | N103: 2017-08-20 | O103: 2017-08-20 | P103: 2017-08-20 | Q103: 2017-08-20
A104: 42916 | B104: 2017-07-17 | C104: 2017-07-17 | D104: 2017-07-17 | E104: 2017-07-17 | F104: 2017-07-10 | G104: 2017-07-10 | H104: 2017-07-12 | I104: 2017-07-12 | J104: 2017-07-12 | K104: 42916 | L104: 43001 | M104: 43001 | N104: 2017-07-20 | O104: 2017-07-20 | P104: 2017-07-20 | Q104: 2017-07-20
A105: 42886 | B105: 2017-06-14 | C105: 2017-06-14 | D105: 2017-06-14 | E105: 2017-06-14 | F105: 2017-06-09 | G105: 2017-06-09 | H105: 2017-06-14 | I105: 2017-06-14 | J105: 2017-06-14 | K105: 42886 | L105: 42909 | M105: 42909 | N105: 2017-06-20 | O105: 2017-06-20 | P105: 2017-06-20 | Q105: 2017-06-20
A106: 42855 | B106: 2017-05-15 | C106: 2017-05-15 | D106: 2017-05-15 | E106: 2017-05-15 | F106: 2017-05-10 | G106: 2017-05-10 | H106: 2017-05-12 | I106: 2017-05-12 | J106: 2017-05-12 | K106: 42855 | L106: 42878 | M106: 42878 | N106: 2017-05-20 | O106: 2017-05-20 | P106: 2017-05-20 | Q106: 2017-05-20
A107: 42825 | B107: 2017-04-17 | C107: 2017-04-17 | D107: 2017-04-17 | E107: 2017-04-17 | F107: 2017-04-12 | G107: 2017-04-12 | H107: 2017-04-14 | I107: 2017-04-14 | J107: 2017-04-14 | K107: 42825 | L107: 42848 | M107: 42848 | N107: 2017-04-20 | O107: 2017-04-20 | P107: 2017-04-20 | Q107: 2017-04-20
A108: 42794 | B108: 2017-03-14 | C108: 2017-03-14 | D108: 2017-03-14 | E108: 2017-03-14 | F108: 2017-03-09 | G108: 2017-03-09 | H108: 2017-03-09 | I108: 2017-03-09 | J108: 2017-03-09 | K108: 42795 | L108: 42817 | M108: 42817 | N108: 2017-03-20 | O108: 2017-03-20 | P108: 2017-03-20 | Q108: 2017-03-20
A109: 42766 | B109: 42756 | C109: 42756 | D109: 42756 | E109: 42756 | F109: 2017-02-14 | G109: 2017-02-14 | H109: 2017-02-14 | I109: 2017-02-14 | J109: 2017-02-14 | K109: 42767 | L109: 42789 | M109: 42789 | N109: 2017-02-20 | O109: 2017-02-20 | P109: 2017-02-20 | Q109: 2017-02-20
A110: 42735 | B110: 2017-01-20 | C110: 2017-01-20 | D110: 2017-01-20 | E110: 2017-01-20 | F110: 2017-01-10 | G110: 2017-01-10 | H110: 2017-01-12 | I110: 2017-01-12 | J110: 2017-01-12 | K110: 42736 | L110: 42758 | M110: 42758 | N110: 2017-01-20 | O110: 2017-01-20 | P110: 2017-01-20 | Q110: 2017-01-20
A111: 42704 | B111: 2016-12-13 | C111: 2016-12-13 | D111: 2016-12-13 | E111: 2016-12-13 | F111: 2016-12-09 | G111: 2016-12-09 | H111: 2016-12-14 | I111: 2016-12-14 | J111: 2016-12-14 | K111: 42705 | L111: 42725 | M111: 42725 | N111: 2016-12-20 | O111: 2016-12-20 | P111: 2016-12-20 | Q111: 2016-12-20
A112: 42674 | B112: 2016-11-14 | C112: 2016-11-14 | D112: 2016-11-14 | E112: 2016-11-14 | F112: 2016-11-09 | G112: 2016-11-09 | H112: 2016-11-11 | I112: 2016-11-11 | J112: 2016-11-11 | K112: 42675 | L112: 42698 | M112: 42698 | N112: 2016-11-20 | O112: 2016-11-20 | P112: 2016-11-20 | Q112: 2016-11-20
A113: 42643 | B113: 2016-10-19 | C113: 2016-10-19 | D113: 2016-10-19 | E113: 2016-10-19 | F113: 2016-10-14 | G113: 2016-10-14 | H113: 2016-10-18 | I113: 2016-10-18 | J113: 2016-10-18 | K113: 42644 | L113: 42664 | M113: 42664 | N113: 2016-10-20 | O113: 2016-10-20 | P113: 2016-10-20 | Q113: 2016-10-20
A114: 42613 | B114: 2016-09-13 | C114: 2016-09-13 | D114: 2016-09-13 | E114: 2016-09-13 | F114: 2016-09-09 | G114: 2016-09-09 | H114: 2016-09-14 | I114: 2016-09-14 | J114: 2016-09-14 | K114: 42614 | L114: 42634 | M114: 42634 | N114: 2016-09-20 | O114: 2016-09-20 | P114: 2016-09-20 | Q114: 2016-09-20
A115: 42582 | B115: 2016-08-12 | C115: 2016-08-12 | D115: 2016-08-12 | E115: 2016-08-12 | F115: 2016-08-09 | G115: 2016-08-09 | H115: 2016-08-12 | I115: 2016-08-12 | J115: 2016-08-12 | K115: 42583 | L115: 42603 | M115: 42603 | N115: 2016-08-20 | O115: 2016-08-20 | P115: 2016-08-20 | Q115: 2016-08-20
A116: 42551 | B116: 2016-07-15 | C116: 2016-07-15 | D116: 2016-07-15 | E116: 2016-07-15 | F116: 2016-07-10 | G116: 2016-07-10 | H116: 2016-07-15 | I116: 2016-07-15 | J116: 2016-07-15 | K116: 42552 | L116: 42603 | M116: 42603 | N116: 2016-07-20 | O116: 2016-07-20 | P116: 2016-07-20 | Q116: 2016-07-20
A117: 42521 | B117: 2016-06-13 | C117: 2016-06-13 | D117: 2016-06-13 | E117: 2016-06-13 | F117: 2016-06-09 | G117: 2016-06-09 | H117: 2016-06-15 | I117: 2016-06-15 | J117: 2016-06-15 | K117: 42522 | L117: 42542 | M117: 42542 | N117: 2016-06-20 | O117: 2016-06-20 | P117: 2016-06-20 | Q117: 2016-06-20
A118: 42490 | B118: 2016-05-14 | C118: 2016-05-14 | D118: 2016-05-14 | E118: 2016-05-14 | F118: 2016-05-10 | G118: 2016-05-10 | H118: 2016-05-13 | I118: 2016-05-13 | J118: 2016-05-13 | K118: 42491 | L118: 42542 | M118: 42542 | N118: 2016-05-20 | O118: 2016-05-20 | P118: 2016-05-20 | Q118: 2016-05-20
A119: 42460 | B119: 2016-04-15 | C119: 2016-04-15 | D119: 2016-04-15 | E119: 2016-04-15 | F119: 2016-04-11 | G119: 2016-04-11 | H119: 2016-04-15 | I119: 2016-04-15 | J119: 2016-04-15 | K119: 42461 | L119: 42481 | M119: 42481 | N119: 2016-04-20 | O119: 2016-04-20 | P119: 2016-04-20 | Q119: 2016-04-20
A120: 42429 | B120: 2016-03-12 | C120: 2016-03-12 | D120: 2016-03-12 | E120: 2016-03-12 | F120: 2016-03-10 | G120: 2016-03-10 | H120: 2016-03-16 | I120: 2016-03-16 | J120: 2016-03-16 | K120: 42430 | L120: 42481 | M120: 42481 | N120: 2016-03-20 | O120: 2016-03-20 | P120: 2016-03-20 | Q120: 2016-03-20
A121: 42400 | B121: 42389 | C121: 42389 | D121: 42389 | E121: 42389 | F121: 2016-02-18 | G121: 2016-02-18 | H121: 2016-02-23 | I121: 2016-02-23 | J121: 2016-02-23 | K121: 42401 | L121: 42421 | M121: 42421 | N121: 2016-02-20 | O121: 2016-02-20 | P121: 2016-02-20 | Q121: 2016-02-20
...

Sheet Sheet1
C1: 工业增加值同比
C2: 社会消费品零售总额同比
C3: 固定资产投资完成额:基础设施建设:累计同比
C4: 房地产开发投资完成额:累计同比
C5: CPI同比
C6: PPI同比
C7: 社融同比
C8: M1同比
C9: M2同比
C10: PMI-50
C11: 进口金额
C12: 出口金额
... C16: 保险托管同比

Sheet 滚动稳健标准化周频
B1: 中国:开工率:石油沥青装置:周:结束日5:前一个观测值 | C1: 中国:日均产量:粗钢:周:结束日5:前一个观测值 | D1: 唐山:高炉开工率:周:结束日5:前一个观测值 | E1: 中国:开工率:汽车轮胎(半钢胎):周:结束日5:前一个观测值 | F1: 中国:100大中城市:成交土地占地面积:当周值:周:结束日5:前一个观测值 | G1: 上海出口集装箱运价指数:综合指数:周:结束日5:前一个观测值
A2: 46045 | B2: 26.8 | C2: 244 | D2: 90.77 | E2: 74.56 | F2: 701.3603 | G2: 1457.86
A3: 46038 | B3: 27.2 | C3: 248 | D3: 90.77 | E3: 73.44 | F3: 874.8991 | G3: 1574.12
A4: 46031 | B4: 25.4 | C4: 202 | D4: 89.99 | E4: 65.89 | F4: 811.5168 | G4: 1647.39
A5: 46024 | B5: 27.4 | C5: 227 | D5: 93.64 | E5: 68.25 | F5: 1146.3192 | G5: 1656.32
A6: 46017 | B6: 31.3 | C6: 227 | D6: 93.64 | E6: 72.05 | F6: 3450.6099 | G6: 1656.32
A7: 46010 | B7: 27.6 | C7: 227 | D7: 92.71 | E7: 71.39 | F7: 4410.2299 | G7: 1552.92
A8: 46003 | B8: 27.8 | C8: 228 | D8: 91.8 | E8: 71.57 | F8: 4556.0992 | G8: 1506.46
A9: 45996 | B9: 27.9 | C9: 216 | D9: 93.51 | E9: 70.92 | F9: 2637.8166 | G9: 1397.63
A10: 45989 | B10: 27.8 | C10: 231 | D10: 91.08 | E10: 69.19 | F10: 2318.5822 | G10: 1403.13
A11: 45982 | B11: 24.8 | C11: 231 | D11: 91.2 | E11: 71.07 | F11: 2514.3444 | G11: 1393.56
A12: 45975 | B12: 29 | C12: 235 | D12: 91.2 | E12: 73.68 | F12: 1349.7759 | G12: 1451.38
A13: 45968 | B13: 29.7 | C13: 235 | D13: 91.87 | E13: 73.67 | F13: 627.567 | G13: 1495.1
... A557: 42160 | B557: 64 | C557: 222.82 | D557: 94.03 | E557: 74.7 | F557: 2099.1411 | G557: 623.47
A558: 42153 | C558: 222.82 | D558: 94.47 | E558: 75.03 | F558: 1790.5242 | G558: 661.55
A559: 42146 | C559: 228.5 | D559: 94.47 | E559: 74.6 | F559: 1817.4815 | G559: 676.05
A560: 42139 | C560: 226.9 | D560: 94.03 | E560: 73.73 | F560: 1722.0566 | G560: 757.66
A561: 42132 | C561: 226.9 | D561: 93.72 | E561: 72.65 | F561: 1203.7514 | G561: 830.13
A562: 42125 | C562: 235.14 | D562: 93.26 | E562: 72.14 | F562: 1044.421 | G562: 761.02
A563: 42118 | C563: 228.5 | D563: 94.01 | E563: 72.65 | F563: 1241.0576 | G563: 702.46
A564: 42111 | C564: 228.5 | D564: 94.01 | E564: 71.36 | F564: 799.2488 | G564: 721.61
A565: 42104 | C565: 225.7 | D565: 94.01 | E565: 70.7 | F565: 839.2069 | G565: 792.92
A566: 42097 | C566: 209.3 | D566: 92.45 | E566: 69.52 | F566: 1009.2706 | G566: 763.95
A567: 42090 | C567: 212.89 | D567: 90.64 | E567: 69.09 | F567: 977.0021 | G567: 804.59
A568: 42083 | C568: 212.89 | D568: 90.11 | E568: 67.21 | F568: 2417.7039 | G568: 821.39
A569: 42076 | C569: 219.68 | D569: 90.02 | E569: 63.48 | F569: 2351.5698 | G569: 887.61
... A633: 41628 | C633: 201.43 | D633: 91.93 | E633: 83 | F633: 5773.2322 | G633: 1115.29
A634: 41621 | C634: 201.29 | E634: 83 | F634: 5271.7945 | G634: 1117.3
A635: 41614 | C635: 209.1 | E635: 81.6 | F635: 3236.158 | G635: 970.85
A636: 41607 | C636: 209.1 | E636: 82 | F636: 3659.4169 | G636: 996.52
A637: 41600 | C637: 213.2 | E637: 84 | F637: 3116.6104 | G637: 1039.5
A638: 41593 | C638: 214.4 | E638: 83 | F638: 3263.6429 | G638: 1089.35
A639: 41586 | C639: 214.4 | E639: 82 | F639: 1973.7647 | G639: 1090.16
A640: 41579 | C640: 209.84 | E640: 84 | F640: 4520.2896 | G640: 1128.75
A641: 41572 | C641: 210.68 | E641: 83 | F641: 3386.7039 | G641: 892.47
A642: 41565 | C642: 210.68 | E642: 83 | F642: 3612.2993 | G642: 881.74
A643: 41558 | C643: 212.81 | E643: 83 | F643: 3148.7936 | G643: 894.41
A644: 41551 | C644: 215.2 | E644: 81.9 | F644: 609.8928 | G644: 936.89
A645: 41544 | C645: 215.2 | E645: 81.9 | F645: 5139.9758 | G645: 936.89
... A840: 40179 | C840: 165 | E840: 73.79 | F840: 2760.8009 | G840: 1072.58

Sheet 滚动稳健标准化日频
B1: DR001 | C1: DR007 | D1: R001 | E1: R007 | F1: 1Y存单发行利率 | G1: FR007:1年 | H1: 成交量:R001 | I1: R001成交量占比 | J1: 美元指数 | K1: 中间价 | L1: 即期汇率 | M1: 1年信用利差 | N1: 3年信用利差 | O1: 5年信用利差 | P1: 国债期货成交量：10年 | Q1: 国债期货持仓量:10年 | R1: 国债期货收盘价(活跃合约):10年 | S1: 票房收入 | T1: 30城商品房成交面积 | U1: 精对苯二甲酸开工率 | V1: PTA负荷率 | W1: 玻璃市场价 | X1: 波罗的海 | Y1: 秦皇岛港口吞吐量 | Z1: 期货结算价(活跃合约):焦煤 | AA1: 期货结算价(活跃合约):螺纹钢 | AB1: 水泥价格指数 | AC1: 南华工业品指数 | AD1: 2年美债 | AE1: 10年美债 | AF1: 道琼斯 | AG1: 标普500 | AH1: 纳斯达克 | AI1: 沪深300 | AJ1: 上证综指 | AK1: 科创50 | AL1: 恒生科技 | AM1: COMEX金价 | AN1: 阴极铜价格 | AO1: ICE布油 | AP1: 股债相对 | AQ1: 债券净融资 | AR1: 净买入：券商自营 | AS1: 净买入：保险 | AT1: 净买入：基金 | AU1: 净买入：理财 | AV1: 净买入：货币基金 | AW1: 十年国债活跃券成交量
A2: 46050 | B2: 1.367 | C2: 1.5479 | D2: 1.4381 | E2: 1.6122 | F2: 1.6623 | G2: 1.5113 | H2: 69529.542 | I2: 0.86613942 | J2: 96.352 | K2: 6.9755 | L2: 6.9453 | M2: 14.5 | N2: 20.32 | O2: 28.96 | P2: 63228 | Q2: 285206 | R2: 108.21 | S2: 2962.21 | T2: 23.458495 | U2: 75.83 | V2: 75.86 | W2: 1139.7 | X2: 2016 | Y2: 52.3 | Z2: 1121 | AA2: 3122 | AB2: 98.91 | AC2: 3705.54 | AD2: 3.56 | AE2: 4.26 | AF2: 49015.6 | AG2: 6978.03 | AH2: 23857.45 | AI2: 4717.9914 | AJ2: 4151.2378 | AK2: 1554.8037 | AL2: 5900.16 | AM2: 5411 | AN2: 103060 | AO2: 67.69 | AP2: 1.4088857 | AQ2: 541.58469 | AR2: -189.85 | AS2: -16.19 | AT2: -188.53 | AU2: 17.87 | AV2: -90.54 | AW2: 30900
A3: 46049 | B3: 1.3674 | C3: 1.5833 | D3: 1.4492 | E3: 1.6291 | F3: 1.7014 | G3: 1.5081 | H3: 72140.532 | I3: 0.86716405 | J3: 95.7725 | K3: 6.9858 | L3: 6.9576 | M3: 14.21 | N3: 19.62 | O3: 27.63 | P3: 63355 | Q3: 283423 | R3: 108.185 | S3: 2837.54 | T3: 18.63719 | U3: 75.83 | V3: 75.86 | W3: 1139.7 | X3: 1999 | Y3: 51.7 | Z3: 1129.5 | AA3: 3133 | AB3: 99.21 | AC3: 3660.54 | AD3: 3.53 | AE3: 4.24 | AF3: 49003.41 | AG3: 6978.6 | AH3: 23817.1 | AI3: 4705.6918 | AJ3: 4139.9041 | AK3: 1555.9783 | AL3: 5754.72 | AM3: 5179.6 | AN3: 102600 | AO3: 66.76 | AP3: 1.4036918 | AQ3: 3156.5098 | AR3: -328.3 | AS3: 73.99 | AT3: -81.43 | AU3: 55.9 | AV3: -112.04 | AW3: 29200
A4: 46048 | B4: 1.4174 | C4: 1.5738 | D4: 1.4898 | E4: 1.6245 | F4: 1.6479 | G4: 1.503 | H4: 73452.027 | I4: 0.86906572 | J4: 97.0506 | K4: 6.9843 | L4: 6.9572 | M4: 14.78 | N4: 20.99 | O4: 27.58 | P4: 68194 | Q4: 280314 | R4: 108.18 | S4: 2868.59 | T4: 17.180802 | U4: 75.83 | V4: 75.86 | W4: 1139.7 | X4: 1780 | Y4: 45.3 | Z4: 1151 | AA4: 3151 | AB4: 99.38 | AC4: 3689.42 | AD4: 3.56 | AE4: 4.22 | AF4: 49412.4 | AG4: 6950.23 | AH4: 23601.357 | AI4: 4706.964 | AJ4: 4132.6052 | AK4: 1532.796 | AL4: 5725.99 | AM4: 5004.8 | AN4: 101880 | AO4: 64.9 | AP4: 1.4080693 | AQ4: 1571.4509 | AR4: -78.81 | AS4: 5.24 | AT4: 288.58 | AU4: 13.07 | AV4: 249.6 | AW4: 21800
A5: 46047 | B5: 1.3983 | C5: 1.4935 | D5: 1.4654 | E5: 1.536 | F5: 1.6982 | G5: 1.5 | H5: 75804.152 | I5: 0.91708349 | J5: 97.5053 | K5: 6.9929 | L5: 6.9642 | M5: 14.62 | N5: 22.49 | O5: 28.05 | P5: 77051 | Q5: 279387 | R5: 108.195 | S5: 6583.28 | T5: 13.015356 | U5: 75.83 | V5: 75.86 | W5: 1139.7 | X5: 1762 | Y5: 46.1 | Z5: 1144 | AA5: 3134 | AB5: 99.62 | AC5: 3660.83 | AD5: 3.6 | AE5: 4.24 | AF5: 49098.71 | AG5: 6915.61 | AH5: 23501.24 | AI5: 4702.4966 | AJ5: 4136.1642 | AK5: 1553.7073 | AL5: 5798.01 | AM5: 4983.1 | AN5: 101340 | AO5: 65.44 | AP5: 1.4083506 | AQ5: -546.15
A6: 46046 | B6: 1.3983 | C6: 1.4935 | D6: 1.4654 | E6: 1.536 | F6: 1.6982 | G6: 1.5 | H6: 75804.152 | I6: 0.91708349 | J6: 97.5053 | K6: 6.9929 | L6: 6.9642 | M6: 14.62 | N6: 22.49 | O6: 28.05 | P6: 77051 | Q6: 279387 | R6: 108.195 | S6: 8542.73 | T6: 14.632958 | U6: 75.83 | V6: 75.86 | W6: 1139.7 | X6: 1762 | Y6: 50.4 | Z6: 1144 | AA6: 3134 | AB6: 99.62 | AC6: 3660.83 | AD6: 3.6 | AE6: 4.24 | AF6: 49098.71 | AG6: 6915.61 | AH6: 23501.24 | AI6: 4702.4966 | AJ6: 4136.1642 | AK6: 1553.7073 | AL6: 5798.01 | AM6: 4983.1 | AN6: 101340 | AO6: 65.44 | AP6: 1.4313586 | AQ6: -257
A7: 46045 | B7: 1.3983 | C7: 1.4935 | D7: 1.4654 | E7: 1.536 | F7: 1.6982 | G7: 1.5 | H7: 75804.152 | I7: 0.91708349 | J7: 97.5053 | K7: 6.9929 | L7: 6.9642 | M7: 14.62 | N7: 22.49 | O7: 28.05 | P7: 77051 | Q7: 279387 | R7: 108.195 | S7: 5835.06 | T7: 20.008017 | U7: 75.83 | V7: 75.86 | W7: 1139.7 | X7: 1762 | Y7: 49.8 | Z7: 1144 | AA7: 3134 | AB7: 99.62 | AC7: 3660.83 | AD7: 3.6 | AE7: 4.24 | AF7: 49098.71 | AG7: 6915.61 | AH7: 23501.24 | AI7: 4702.4966 | AJ7: 4136.1642 | AK7: 1553.7073 | AL7: 5798.01 | AM7: 4983.1 | AN7: 101340 | AO7: 65.44 | AP7: 1.4684665 | AQ7: 2387.3605 | AR7: -113.79 | AS7: 119.34 | AT7: 0.63 | AU7: 32.62 | AV7: -85.35 | AW7: 26700
A8: 46044 | B8: 1.4171 | C8: 1.5074 | D8: 1.4822 | E8: 1.5473 | F8: 1.71 | G8: 1.5087 | H8: 76209.496 | I8: 0.90231415 | J8: 98.2778 | K8: 7.0019 | L8: 6.9628 | M8: 13.7 | N8: 21.88 | O8: 27.41 | P8: 51902 | Q8: 274115 | R8: 108.15 | S8: 2354.49 | T8: 18.73942 | U8: 75.83 | V8: 75.86 | W8: 1124.2 | X8: 1761 | Y8: 41.4 | Z8: 1125 | AA8: 3124 | AB8: 99.75 | AC8: 3624.02 | AD8: 3.61 | AE8: 4.26 | AF8: 49384.01 | AG8: 6913.35 | AH8: 23436.02 | AI8: 4723.7091 | AJ8: 4122.576 | AK8: 1541.638 | AL8: 5762.44 | AM8: 4938.4 | AN8: 100700 | AO8: 64.62 | AP8: 1.4500407 | AQ8: 2082.9928 | AR8: -308.44 | AS8: 147.66 | AT8: 252.28 | AU8: 67.51 | AV8: 91.29 | AW8: 13000
A9: 46043 | B9: 1.3212 | C9: 1.4952 | D9: 1.395 | E9: 1.5396 | F9: 1.6989 | G9: 1.5037 | H9: 79428.574 | I9: 0.90436783 | J9: 98.7693 | K9: 7.0014 | L9: 6.965 | M9: 13.15 | N9: 23.21 | O9: 29.27 | P9: 83496 | Q9: 272588 | R9: 108.2 | S9: 2395.37 | T9: 17.64838 | U9: 75.83 | V9: 75.86 | W9: 1124.2 | X9: 1803 | Y9: 44.6 | Z9: 1119.5 | AA9: 3113 | AB9: 99.92 | AC9: 3596.59 | AD9: 3.6 | AE9: 4.26 | AF9: 49077.23 | AG9: 6875.62 | AH9: 23224.82 | AI9: 4723.0692 | AJ9: 4116.94 | AK9: 1535.3934 | AL9: 5746.3 | AM9: 4836.2 | AN9: 101280 | AO9: 64.62 | AP9: 1.4587156 | AQ9: 2340.9651 | AR9: 133.08 | AS9: 78.05 | AT9: 414.88 | AU9: 14.2 | AV9: 0.7 | AW9: 36700
A10: 46042 | B10: 1.3712 | C10: 1.4948 | D10: 1.4212 | E10: 1.5429 | F10: 1.7274 | G10: 1.5051 | H10: 78171.836 | I10: 0.89889331 | J10: 98.5413 | K10: 7.0006 | L10: 6.9603 | M10: 13.42 | N10: 24.42 | O10: 31.16 | P10: 68508 | Q10: 267617 | R10: 108.18 | S10: 2360.53 | T10: 19.53622 | U10: 75.83 | V10: 75.86 | W10: 1124.2 | X10: 1729 | Y10: 44.8 | Z10: 1150 | AA10: 3128 | AB10: 99.98 | AC10: 3586.63 | AD10: 3.6 | AE10: 4.3 | AF10: 48488.59 | AG10: 6796.86 | AH10: 22954.32 | AI10: 4718.8782 | AJ10: 4113.649 | AK10: 1482.9941 | AL10: 5683.44 | AM10: 4769.1 | AN10: 101230 | AO10: 64 | AP10: 1.4572193 | AQ10: 122.7449 | AR10: -81.3 | AS10: 206.68 | AT10: 68.54 | AU10: 50.55 | AV10: -71.97 | AW10: 37700
A11: 46041 | B11: 1.3182 | C11: 1.4772 | D11: 1.3752 | E11: 1.5288 | F11: 1.7121 | G11: 1.5039 | H11: 77963.24 | I11: 0.90165598 | J11: 99.0423 | K11: 7.0051 | L11: 6.9636 | M11: 14.88 | N11: 24.68 | O11: 30.39 | P11: 57602 | Q11: 258387 | R11: 108.04 | S11: 2344.16 | T11: 16.040475 | U11: 75.83 | V11: 75.86 | W11: 1124.2 | X11: 1650 | Y11: 42 | Z11: 1177 | AA11: 3148 | AB11: 100.47 | AC11: 3604.8 | AD11: 3.59 | AE11: 4.24 | AF11: 49359.33 | AG11: 6940.01 | AH11: 23515.39 | AI11: 4734.4556 | AJ11: 4114.0001 | AK11: 1506.8571 | AL11: 5749.98 | AM11: 4601.1 | AN11: 101180 | AO11: 64.18 | AP11: 1.4514217 | AQ11: 2255.5053 | AR11: -132.26 | AS11: 215.94 | AT11: 264.2 | AU11: 12.51 | AV11: -193.48 | AW11: 14600
A12: 46040 | B12: 1.3199 | C12: 1.443 | D12: 1.3734 | E12: 1.5137 | F12: 1.7086 | G12: 1.4988 | H12: 80478.201 | I12: 0.91888155 | J12: 99.3691 | K12: 7.0078 | L12: 6.969 | M12: 15.44 | N12: 26.17 | O12: 31.14 | P12: 74124 | Q12: 259760 | R12: 108.065 | S12: 6015.85 | T12: 10.721303 | U12: 75.83 | V12: 75.86 | W12: 1124.2 | X12: 1567 | Y12: 51.3 | Z12: 1184 | AA12: 3173 | AB12: 100.49 | AC12: 3621.64 | AD12: 3.59 | AE12: 4.24 | AF12: 49359.33 | AG12: 6940.01 | AH12: 23515.39 | AI12: 4731.8728 | AJ12: 4101.9127 | AK12: 1514.0681 | AL12: 5822.18 | AM12: 4601.1 | AN12: 100770 | AO12: 64.2 | AP12: 1.4485997 | AQ12: -469.32701
A13: 46039 | B13: 1.3199 | C13: 1.443 | D13: 1.3734 | E13: 1.5137 | F13: 1.7086 | G13: 1.4988 | H13: 80478.201 | I13: 0.91888155 | J13: 99.3691 | K13: 7.0078 | L13: 6.969 | M13: 15.44 | N13: 26.17 | O13: 31.14 | P13: 74124 | Q13: 259760 | R13: 108.065 | S13: 7682.96 | T13: 12.056278 | U13: 75.83 | V13: 75.86 | W13: 1124.2 | X13: 1567 | Y13: 22.8 | Z13: 1184 | AA13: 3173 | AB13: 100.49 | AC13: 3621.64 | AD13: 3.59 | AE13: 4.24 | AF13: 49359.33 | AG13: 6940.01 | AH13: 23515.39 | AI13: 4731.8728 | AJ13: 4101.9127 | AK13: 1514.0681 | AL13: 5822.18 | AM13: 4601.1 | AN13: 100770 | AO13: 64.2 | AP13: 1.4496852 | AQ13: -369.64
A14: 46038 | B14: 1.3199 | C14: 1.443 | D14: 1.3734 | E14: 1.5137 | F14: 1.7086 | G14: 1.4988 | H14: 80478.201 | I14: 0.91888155 | J14: 99.3691 | K14: 7.0078 | L14: 6.969 | M14: 15.44 | N14: 26.17 | O14: 31.14 | P14: 74124 | Q14: 259760 | R14: 108.065 | S14: 3645.23 | T14: 20.14013 | U14: 75.83 | V14: 75.86 | W14: 1124.2 | X14: 1567 | Y14: 43 | Z14: 1184 | AA14: 3173 | AB14: 100.49 | AC14: 3621.64 | AD14: 3.59 | AE14: 4.24 | AF14: 49359.33 | AG14: 6940.01 | AH14: 23515.39 | AI14: 4731.8728 | AJ14: 4101.9127 | AK14: 1514.0681 | AL14: 5822.18 | AM14: 4601.1 | AN14: 100770 | AO14: 64.2 | AP14: 1.4496852 | AQ14: -1593.0804 | AR14: -251.23 | AS14: 235.24 | AT14: 187.68 | AU14: 22.23 | AV14: -108.59 | AW14: 29800
A15: 46037 | B15: 1.3672 | C15: 1.5024 | D15: 1.4154 | E15: 1.5497 | F15: 1.726 | G15: 1.5104 | H15: 80140.549 | I15: 0.91492584 | J15: 99.3424 | K15: 7.0064 | L15: 6.9698 | M15: 15.84 | N15: 26.15 | O15: 31.69 | P15: 91991 | Q15: 254914 | R15: 108.035 | S15: 2541.32 | T15: 23.4045 | U15: 76.76 | V15: 75.86 | W15: 1124.2 | X15: 1532 | Y15: 59.4 | Z15: 1188.5 | AA15: 3161 | AB15: 100.57 | AC15: 3672.4 | AD15: 3.56 | AE15: 4.17 | AF15: 49442.44 | AG15: 6944.47 | AH15: 23530.02 | AI15: 4751.4293 | AJ15: 4112.6012 | AK15: 1493.945 | AL15: 5828.35 | AM15: 4620.5 | AN15: 102810 | AO15: 63.87 | AP15: 1.4054681 | AQ15: -4632.2433 | AR15: -141.7 | AS15: 150.1 | AT15: -24.1 | AU15: 41.8 | AV15: -253.3 | AW15: 41200
A16: 46036 | B16: 1.392 | C16: 1.5668 | D16: 1.4913 | E16: 1.6037 | F16: 1.7135 | G16: 1.5232 | H16: 72499.29 | I16: 0.89386849 | J16: 99.0753 | K16: 7.012 | L16: 6.9734 | M16: 16.19 | N16: 26.84 | O16: 33.48 | P16: 84940 | Q16: 252823 | R16: 107.93 | S16: 2586.7 | T16: 18.393312 | U16: 76.76 | V16: 75.86 | W16: 1124.2 | X16: 1566 | Y16: 53.2 | Z16: 1199.5 | AA16: 3164 | AB16: 100.56 | AC16: 3680.51 | AD16: 3.51 | AE16: 4.15 | AF16: 49149.63 | AG16: 6926.6 | AH16: 23471.75 | AI16: 4741.9306 | AJ16: 4126.0932 | AK16: 1500.911 | AL16: 5908.26 | AM16: 4633.9 | AN16: 104120 | AO16: 65.39 | AP16: 1.4064021 | AQ16: 1991.9842 | AR16: -31.48 | AS16: 180.08 | AT16: -48.49 | AU16: 22.59 | AV16: -290.41 | AW16: 52700
A17: 46035 | B17: 1.3913 | C17: 1.5474 | D17: 1.4719 | E17: 1.5746 | F17: 1.7234 | G17: 1.5239 | H17: 76278.752 | I17: 0.89214609 | J17: 99.1842 | K17: 7.0103 | L17: 6.9765 | M17: 16.2 | N17: 26.58 | O17: 32.92 | P17: 58261 | Q17: 251204 | R17: 107.85 | S17: 2609.05 | T17: 20.120729 | U17: 77.41 | V17: 75.86 | W17: 1124.2 | X17: 1608 | Y17: 31.5 | Z17: 1215 | AA17: 3161 | AB17: 100.58 | AC17: 3651.95 | AD17: 3.53 | AE17: 4.18 | AF17: 49191.99 | AG17: 6963.74 | AH17: 23709.87 | AI17: 4761.0324 | AJ17: 4138.7585 | AK17: 1469.5699 | AL17: 5869.79 | AM17: 4594.4 | AN17: 102290 | AO17: 65.46 | AP17: 1.3898699 | AQ17: -315.31195 | AR17: -169.85 | AS17: 170.83 | AT17: -22.98 | AU17: 105.84 | AV17: -250.8 | AW17: 39800
A18: 46034 | B18: 1.327 | C18: 1.4902 | D18: 1.3895 | E18: 1.5249 | F18: 1.6925 | G18: 1.5115 | H18: 80679.937 | I18: 0.90260258 | J18: 98.8943 | K18: 7.0108 | L18: 6.9742 | M18: 15.82 | N18: 25.97 | O18: 32.57 | P18: 68816 | Q18: 249332 | R18: 107.845 | S18: 2977.56 | T18: 21.984487 | U18: 77.41 | V18: 75.86 | W18: 1124.2 | X18: 1659 | Y18: 46.8 | Z18: 1221.5 | AA18: 3158 | AB18: 100.87 | AC18: 3674.29 | AD18: 3.54 | AE18: 4.19 | AF18: 49590.2 | AG18: 6977.27 | AH18: 23733.9 | AI18: 4789.9155 | AJ18: 4165.287 | AK18: 1511.836 | AL18: 5863.2 | AM18: 4608.8 | AN18: 103800 | AO18: 64.3 | AP18: 1.3775626 | AQ18: 1608.2534 | AR18: 124.91 | AS18: 176.72 | AT18: 139.96 | AU18: 44.23 | AV18: -149.15 | AW18: 35300
A19: 46033 | B19: 1.2727 | C19: 1.4727 | D19: 1.348 | E19: 1.5157 | F19: 1.7034 | G19: 1.5073 | H19: 80887.952 | I19: 0.91689334 | J19: 99.1368 | K19: 7.0128 | L19: 6.9821 | M19: 16.59 | N19: 25.74 | O19: 32.72 | P19: 78508 | Q19: 251267 | R19: 107.765 | S19: 7755.54 | T19: 10.272454 | U19: 77.41 | V19: 75.86 | W19: 1124.2 | X19: 1688 | Y19: 44 | Z19: 1188 | AA19: 3146 | AB19: 101.44 | AC19: 3635.84 | AD19: 3.54 | AE19: 4.18 | AF19: 49504.07 | AG19: 6966.28 | AH19: 23671.35 | AI19: 4758.9221 | AJ19: 4120.426 | AK19: 1475.9676 | AL19: 5687.14 | AM19: 4518.4 | AN19: 101410 | AO19: 63.02 | AP19: 1.3598126 | AQ19: -2154.51
A20: 46032 | B20: 1.2727 | C20: 1.4727 | D20: 1.348 | E20: 1.5157 | F20: 1.7034 | G20: 1.5073 | H20: 80887.952 | I20: 0.91689334 | J20: 99.1368 | K20: 7.0128 | L20: 6.9821 | M20: 16.59 | N20: 25.74 | O20: 32.72 | P20: 78508 | Q20: 251267 | R20: 107.765 | S20: 9928.65 | T20: 12.637534 | U20: 77.41 | V20: 75.86 | W20: 1124.2 | X20: 1688 | Y20: 30.6 | Z20: 1188 | AA20: 3146 | AB20: 101.44 | AC20: 3635.84 | AD20: 3.54 | AE20: 4.18 | AF20: 49504.07 | AG20: 6966.28 | AH20: 23671.35 | AI20: 4758.9221 | AJ20: 4120.426 | AK20: 1475.9676 | AL20: 5687.14 | AM20: 4518.4 | AN20: 101410 | AO20: 63.02 | AP20: 1.3690768 | AQ20: -539.10548
A21: 46031 | B21: 1.2727 | C21: 1.4727 | D21: 1.348 | E21: 1.5157 | F21: 1.7034 | G21: 1.5073 | H21: 80887.952 | I21: 0.91689334 | J21: 99.1368 | K21: 7.0128 | L21: 6.9821 | M21: 16.59 | N21: 25.74 | O21: 32.72 | P21: 78508 | Q21: 251267 | R21: 107.765 | S21: 4750.67 | T21: 20.747488 | U21: 77.41 | V21: 75.86 | W21: 1132.5 | X21: 1688 | Y21: 39.2 | Z21: 1188 | AA21: 3146 | AB21: 101.44 | AC21: 3635.84 | AD21: 3.54 | AE21: 4.18 | AF21: 49504.07 | AG21: 6966.28 | AH21: 23671.35 | AI21: 4758.9221 | AJ21: 4120.426 | AK21: 1475.9676 | AL21: 5687.14 | AM21: 4518.4 | AN21: 101410 | AO21: 63.02 | AP21: 1.3690768 | AQ21: 2015.6134 | AR21: -98.87 | AS21: 178.99 | AT21: 82.43 | AU21: 19.67 | AV21: -47.56 | AW21: 94400
A22: 46030 | B22: 1.2695 | C22: 1.474 | D22: 1.3424 | E22: 1.5261 | F22: 1.7613 | G22: 1.5105 | H22: 81319.747 | I22: 0.910043 | J22: 98.864 | K22: 7.0197 | L22: 6.9807 | M22: 15.76 | N22: 26.01 | O22: 30.9 | P22: 82422 | Q22: 247814 | R22: 107.79 | S22: 3113.64 | T22: 16.963707 | U22: 77.41 | V22: 75.86 | W22: 1132.5 | X22: 1718 | Y22: 47.4 | Z22: 1204 | AA22: 3179 | AB22: 101.54 | AC22: 3603.79 | AD22: 3.49 | AE22: 4.19 | AF22: 49266.11 | AG22: 6921.46 | AH22: 23480.02 | AI22: 4737.6536 | AJ22: 4082.9788 | AK22: 1455.1729 | AL22: 5678.34 | AM22: 4487.9 | AN22: 101220 | AO22: 62.7 | AP22: 1.3690768 | AQ22: 603.60017 | AR22: -196.2 | AS22: 196.5 | AT22: -716.3 | AU22: 15.1 | AV22: 213.1 | AW22: 96300
A23: 46029 | B23: 1.2674 | C23: 1.4625 | D23: 1.3365 | E23: 1.5323 | F23: 1.7024 | G23: 1.5115 | H23: 79864.408 | I23: 0.90183443 | J23: 98.7426 | K23: 7.0187 | L23: 6.9912 | M23: 16.1 | N23: 24.05 | O23: 28.87 | P23: 94286 | Q23: 244065 | R23: 107.61 | S23: 3283.49 | T23: 18.78898 | U23: 77.41 | V23: 75.86 | W23: 1132.5 | X23: 1776 | Y23: 49.8 | Z23: 1136 | AA23: 3154 | AB23: 101.68 | AC23: 3657.23 | AD23: 3.47 | AE23: 4.15 | AF23: 48996.08 | AG23: 6920.93 | AH23: 23584.27 | AI23: 4776.6658 | AJ23: 4085.7723 | AK23: 1443.388 | AL23: 5738.52 | AM23: 4467.1 | AN23: 103410 | AO23: 60.39 | AP23: 1.4290972 | AQ23: 2667.031 | AR23: -306.45 | AS23: 149.78 | AT23: -1335.96 | AU23: 77.72 | AV23: 81.1 | AW23: 100100
A24: 46028 | B24: 1.2628 | C24: 1.4326 | D24: 1.3302 | E24: 1.493 | F24: 1.7166 | G24: 1.5096 | H24: 76100.988 | I24: 0.89303915 | J24: 98.5997 | K24: 7.0173 | L24: 6.9813 | M24: 16.25 | N24: 26.2 | O24: 30.42 | P24: 89378 | Q24: 244047 | R24: 107.7 | S24: 3473.11 | T24: 18.868596 | U24: 77.41 | V24: 75.86 | W24: 1132.5 | X24: 1830 | Y24: 50 | Z24: 1078 | AA24: 3098 | AB24: 101.72 | AC24: 3609.73 | AD24: 3.47 | AE24: 4.18 | AF24: 49462.08 | AG24: 6944.82 | AH24: 23547.17 | AI24: 4790.6938 | AJ24: 4083.6672 | AK24: 1429.3023 | AL24: 5825.26 | AM24: 4505.7 | AN24: 105320 | AO24: 60.51 | AP24: 1.4367731 | AQ24: -93.352284 | AR24: -391.54 | AS24: 114.44 | AT24: -975.48 | AU24: 9.26 | AV24: -55.77 | AW24: 107000
A25: 46027 | B25: 1.2624 | C25: 1.4312 | D25: 1.3315 | E25: 1.4861 | F25: 1.8 | G25: 1.5043 | H25: 65977.614 | I25: 0.88686873 | J25: 98.3291 | K25: 7.023 | L25: 6.9806 | M25: 15.6 | N25: 27.68 | O25: 33.53 | P25: 86423 | Q25: 239562 | R25: 107.855 | S25: 3906.22 | T25: 18.960583 | U25: 77.41 | V25: 75.86 | W25: 1132.5 | X25: 1851 | Y25: 54.3 | Z25: 1097 | AA25: 3113 | AB25: 102.24 | AC25: 3544.39 | AD25: 3.46 | AE25: 4.17 | AF25: 48977.18 | AG25: 6902.05 | AH25: 23395.82 | AI25: 4717.7457 | AJ25: 4023.4167 | AK25: 1403.4142 | AL25: 5741.63 | AM25: 4459.7 | AN25: 101350 | AO25: 61.77 | AP25: 1.4755166 | AQ25: 1382.402 | AR25: -291.14 | AS25: 24.87 | AT25: -201.94 | AU25: -79.58 | AV25: -141.42 | AW25: 71600
A26: 46026 | B26: 1.2419 | C26: 1.4286 | D26: 1.26 | E26: 1.4525 | F26: 1.855 | G26: 1.5025 | H26: 23494.355 | I26: 0.95674233 | J26: 98.4594 | K26: 7.0288 | L26: 6.989 | M26: 19.62 | N26: 30.21 | O26: 35.08 | P26: 99072 | Q26: 236119 | R26: 107.86 | S26: 5151.76 | T26: 16.224458 | U26: 77.41 | V26: 75.86 | W26: 1132.5 | X26: 1882 | Y26: 50.9 | Z26: 1115.5 | AA26: 3127 | AB26: 102.39 | AC26: 3549.74 | AD26: 3.47 | AE26: 4.19 | AF26: 48382.39 | AG26: 6858.47 | AH26: 23235.63 | AI26: 4629.9395 | AJ26: 3968.8401 | AK26: 1344.2002 | AL26: 5736.44 | AM26: 4341.9 | AN26: 98240 | AO26: 60.8 | AP26: 1.5072991 | AQ26: 137.05
A27: 46025 | B27: 1.3325 | C27: 1.9821 | D27: 1.4568 | E27: 2.1559 | F27: 1.855 | G27: 1.5029 | H27: 14784.273 | I27: 0.34939368 | J27: 98.4594 | K27: 7.0288 | L27: 6.989 | M27: 21.61 | N27: 29.41 | O27: 35.83 | P27: 99072 | Q27: 236119 | R27: 107.86 | S27: 13804.51 | T27: 5.810898 | U27: 76.24 | V27: 75.86 | W27: 1132.5 | X27: 1882 | Y27: 51.8 | Z27: 1115.5 | AA27: 3127 | AB27: 102.66 | AC27: 3549.74 | AD27: 3.47 | AE27: 4.19 | AF27: 48382.39 | AG27: 6858.47 | AH27: 23235.63 | AI27: 4629.9395 | AJ27: 3968.8401 | AK27: 1344.2002 | AL27: 5736.44 | AM27: 4341.9 | AN27: 98240 | AO27: 60.8 | AP27: 1.5035457 | AQ27: -297.15278
A28: 46024 | B28: 1.3325 | C28: 1.9821 | D28: 1.4568 | E28: 2.1559 | F28: 1.855 | G28: 1.5029 | H28: 14784.273 | I28: 0.34939368 | J28: 98.4594 | K28: 7.0288 | L28: 6.989 | M28: 21.61 | N28: 29.41 | O28: 35.83 | P28: 99072 | Q28: 236119 | R28: 107.86 | S28: 26384.35 | T28: 5.589372 | U28: 76.24 | V28: 75.86 | W28: 1132.5 | X28: 1882 | Y28: 52 | Z28: 1115.5 | AA28: 3127 | AB28: 102.66 | AC28: 3549.74 | AD28: 3.47 | AE28: 4.19 | AF28: 48382.39 | AG28: 6858.47 | AH28: 23235.63 | AI28: 4629.9395 | AJ28: 3968.8401 | AK28: 1344.2002 | AL28: 5736.44 | AM28: 4341.9 | AN28: 98240 | AO28: 60.8 | AP28: 1.5035457 | AQ28: -121.16
A29: 46023 | B29: 1.3325 | C29: 1.9821 | D29: 1.4568 | E29: 2.1559 | F29: 1.855 | G29: 1.5029 | H29: 14784.273 | I29: 0.34939368 | J29: 98.249 | K29: 7.0288 | L29: 6.989 | M29: 21.61 | N29: 29.41 | O29: 35.83 | P29: 99072 | Q29: 236119 | R29: 107.86 | S29: 33780.57 | T29: 8.526592 | U29: 76.24 | V29: 75.86 | W29: 1132.5 | X29: 1877 | Y29: 41.1 | Z29: 1115.5 | AA29: 3127 | AB29: 102.66 | AC29: 3549.74 | AD29: 3.47 | AE29: 4.18 | AF29: 48063.29 | AG29: 6845.5 | AH29: 23241.99 | AI29: 4629.9395 | AJ29: 3968.8401 | AK29: 1344.2002 | AL29: 5515.98 | AM29: 4332.1 | AN29: 98240 | AO29: 60.91 | AP29: 1.5035457 | AQ29: -4.4
A30: 46022 | B30: 1.3325 | C30: 1.9821 | D30: 1.4568 | E30: 2.1559 | F30: 1.855 | G30: 1.5029 | H30: 14784.273 | I30: 0.34939368 | J30: 98.2696 | K30: 7.0288 | L30: 6.989 | M30: 21.61 | N30: 29.41 | O30: 35.83 | P30: 99072 | Q30: 236119 | R30: 107.86 | S30: 21130.4 | T30: 72.300309 | U30: 76.24 | V30: 75.86 | W30: 1132.5 | X30: 1877 | Y30: 47.6 | Z30: 1115.5 | AA30: 3127 | AB30: 102.66 | AC30: 3549.74 | AD30: 3.47 | AE30: 4.18 | AF30: 48063.29 | AG30: 6845.5 | AH30: 23241.99 | AI30: 4629.9395 | AJ30: 3968.8401 | AK30: 1344.2002 | AL30: 5515.98 | AM30: 4332.1 | AN30: 98240 | AO30: 60.91 | AP30: 1.5035457 | AQ30: -880.88499 | AR30: -315.49 | AS30: 129.55 | AT30: 280.87 | AU30: 44.89 | AV30: -177.96 | AW30: 38100
A31: 46021 | B31: 1.2395 | C31: 1.6874 | D31: 1.3782 | E31: 2.062 | F31: 1.64 | G31: 1.5003 | H31: 46068.609 | I31: 0.73376175 | J31: 98.2181 | K31: 7.0348 | L31: 6.9901 | M31: 22.17 | N31: 27.54 | O31: 36.49 | P31: 76849 | Q31: 242485 | R31: 107.94 | S31: 3679.1 | T31: 68.045113 | U31: 73.6 | V31: 75.86 | W31: 1153.1 | X31: 1877 | Y31: 53.3 | Z31: 1110 | AA31: 3137 | AB31: 102.38 | AC31: 3561.07 | AD31: 3.45 | AE31: 4.14 | AF31: 48367.06 | AG31: 6896.24 | AH31: 23419.08 | AI31: 4651.2818 | AJ31: 3965.1159 | AK31: 1359.8734 | AL31: 5578.38 | AM31: 4352.3 | AN31: 98090 | AO31: 61.28 | AP31: 1.4968787 | AQ31: -1904.6373 | AR31: -658.53 | AS31: 206.08 | AT31: 152.44 | AU31: 18.31 | AV31: -336.29 | AW31: 26600
A32: 46020 | B32: 1.2417 | C32: 1.5944 | D32: 1.3376 | E32: 1.936 | F32: 1.7679 | G32: 1.4978 | H32: 61077.193 | I32: 0.80160476 | J32: 97.9975 | K32: 7.0331 | L32: 7.0098 | M32: 23.27 | N32: 28.11 | O32: 37.46 | P32: 125650 | Q32: 247291 | R32: 107.975 | S32: 3410.02 | T32: 49.922603 | U32: 72.84 | V32: 75.86 | W32: 1153.1 | X32: 1877 | Y32: 57.1 | Z32: 1108.5 | AA32: 3137 | AB32: 102.38 | AC32: 3534.24 | AD32: 3.45 | AE32: 4.12 | AF32: 48461.93 | AG32: 6905.74 | AH32: 23474.35 | AI32: 4639.3721 | AJ32: 3965.2796 | AK32: 1346.3188 | AL32: 5483.01 | AM32: 4350.2 | AN32: 98860 | AO32: 61.26 | AP32: 1.4995157 | AQ32: 355.90133 | AR32: -226.02 | AS32: 13.87 | AT32: 371.36 | AU32: 62 | AV32: 33.18 | AW32: 52000
A33: 46019
A34: 46018
A35: 46017 | AR35: -155.28 | AS35: 11.19 | AT35: 423.46 | AU35: 32.05 | AV35: -218.1 | AW35: 30500
A36: 46016 | B36: 1.2589 | C36: 1.4842 | D36: 1.3559 | E36: 1.5245 | F36: 1.7845 | G36: 1.4875 | H36: 74364.354 | I36: 0.87095749 | J36: 97.9079 | K36: 7.0392 | L36: 7.0066 | M36: 24.3 | N36: 26.47 | O36: 35.53 | P36: 58691 | Q36: 258693 | R36: 108.195 | S36: 5422.05 | T36: 36.78298 | U36: 75.24 | V36: 75.86 | W36: 1153.1 | X36: 1877 | Y36: 58 | Z36: 1127 | AA36: 3131 | AB36: 102.46 | AC36: 3533.48 | AD36: 3.47 | AE36: 4.15 | AF36: 48731.16 | AG36: 6932.05 | AH36: 23613.31 | AI36: 4642.5357 | AJ36: 3959.6211 | AK36: 1349.0577 | AL36: 5499.3 | AM36: 4505.4 | AN36: 96210 | AO36: 61.84 | AP36: 1.5196889 | AQ36: -1511.1207 | AR36: 163 | AS36: -8.9 | AT36: 231.9 | AU36: -49.4 | AV36: 29.3 | AW36: 34400
A37: 46015 | B37: 1.2622 | C37: 1.38 | D37: 1.3568 | E37: 1.5198 | F37: 1.72 | G37: 1.4885 | H37: 77935.849 | I37: 0.89188692 | J37: 97.9535 | K37: 7.0471 | L37: 7.0161 | M37: 21.27 | N37: 27.31 | O37: 36.8 | P37: 73502 | Q37: 254485 | R37: 108.23 | S37: 5520.63 | T37: 42.552236 | U37: 75.24 | V37: 75.86 | W37: 1153.1 | X37: 1877 | Y37: 55.4 | Z37: 1124 | AA37: 3126 | AB37: 102.75 | AC37: 3543.43 | AD37: 3.47 | AE37: 4.15 | AF37: 48731.16 | AG37: 6932.05 | AH37: 23613.31 | AI37: 4634.0586 | AJ37: 3940.947 | AK37: 1352.1261 | AL37: 5499.3 | AM37: 4505.4 | AN37: 96100 | AO37: 61.84 | AP37: 1.5165613 | AQ37: =VLOOKUP(A37,[1]净融资函数!$B:$E,4,0) -> 1166.9123 | AR37: 224.3 | AS37: -44.8 | AT37: 234.1 | AU37: 18.4 | AV37: -227.4 | AW37: 34400
A38: 46014 | B38: 1.2691 | C38: 1.4105 | D38: 1.3542 | E38: 1.5028 | F38: 1.7668 | G38: 1.4857 | H38: 77084.354 | I38: 0.88763336 | J38: 97.9093 | K38: 7.0523 | L38: 7.0287 | M38: 20.74 | N38: 27.78 | O38: 39.1 | P38: 103305 | Q38: 252339 | R38: 108.22 | S38: 4776.4 | T38: 58.274063 | U38: 73.81 | V38: 75.86 | W38: 1153.1 | X38: 1889 | Y38: 48 | Z38: 1125 | AA38: 3134 | AB38: 102.78 | AC38: 3507.98 | AD38: 3.48 | AE38: 4.18 | AF38: 48442.41 | AG38: 6909.79 | AH38: 23561.84 | AI38: 4620.7341 | AJ38: 3919.9786 | AK38: 1340.015 | AL38: 5488.89 | AM38: 4515 | AN38: 93930 | AO38: 61.92 | AP38: 1.5180362 | AQ38: =VLOOKUP(A38,[1]净融资函数!$B:$E,4,0) -> -35.626754 | AR38: -123.4 | AS38: 122.3 | AT38: -148.4 | AU38: 70.1 | AV38: -142.3 | AW38: 40300
A39: 46013 | B39: 1.2705 | C39: 1.4337 | D39: 1.3547 | E39: 1.5063 | F39: 1.7465 | G39: 1.493 | H39: 76288.773 | I39: 0.88931548 | J39: 98.2603 | K39: 7.0572 | L39: 7.0382 | M39: 19.16 | N39: 27.22 | O39: 38.68 | P39: 88663 | Q39: 236558 | R39: 107.98 | S39: 5549.8 | T39: 42.440886 | U39: 73.81 | V39: 75.86 | W39: 1153.1 | X39: 1979 | Y39: 35.7 | Z39: 1104.5 | AA39: 3122 | AB39: 102.9 | AC39: 3493.62 | AD39: 3.44 | AE39: 4.17 | AF39: 48362.68 | AG39: 6878.49 | AH39: 23428.83 | AI39: 4611.6235 | AJ39: 3917.3638 | AK39: 1335.2451 | AL39: 5526.83 | AM39: 4480.6 | AN39: 94320 | AO39: 61.54 | AP39: 1.5152865 | AQ39: =VLOOKUP(A39,[1]净融资函数!$B:$E,4,0) -> 718.99911 | AR39: -122.8 | AS39: -64.9 | AT39: 425.4 | AU39: 98.8 | AV39: 153.9 | AW39: 34600
A40: 46012 | B40: 1.2706 | C40: 1.4413 | D40: 1.3517 | E40: 1.5148 | F40: 1.7898 | G40: 1.4929 | H40: 77283.041 | I40: 0.90341443 | J40: 98.7125 | K40: 7.055 | L40: 7.041 | M40: 19.65 | N40: 28.14 | O40: 40.17 | P40: 58808 | Q40: 240925 | R40: 108.15 | S40: 19846.27 | T40: 26.372704 | U40: 73.81 | V40: 75.86 | W40: 1153.1 | X40: 2023 | Y40: 45.9 | Z40: 1110 | AA40: 3114 | AB40: 102.94 | AC40: 3460.46 | AD40: 3.48 | AE40: 4.16 | AF40: 48134.89 | AG40: 6834.5 | AH40: 23307.62 | AI40: 4568.1781 | AJ40: 3890.4475 | AK40: 1308.5889 | AL40: 5479.04 | AM40: 4368.7 | AN40: 93180 | AO40: 60.12 | AP40: 1.5349574 | AQ40: =VLOOKUP(A40,[1]净融资函数!$B:$E,4,0) -> -315.90899
A41: 46011 | B41: 1.2706 | C41: 1.4413 | D41: 1.3517 | E41: 1.5148 | F41: 1.7898 | G41: 1.4929 | H41: 77283.041 | I41: 0.90341443 | J41: 98.7125 | K41: 7.055 | L41: 7.041 | M41: 19.65 | N41: 28.14 | O41: 40.17 | P41: 58808 | Q41: 240925 | R41: 108.15 | S41: 27947.09 | T41: 35.411295 | U41: 73.81 | V41: 75.86 | W41: 1153.1 | X41: 2023 | Y41: 38.7 | Z41: 1110 | AA41: 3114 | AB41: 102.94 | AC41: 3460.46 | AD41: 3.48 | AE41: 4.16 | AF41: 48134.89 | AG41: 6834.5 | AH41: 23307.62 | AI41: 4568.1781 | AJ41: 3890.4475 | AK41: 1308.5889 | AL41: 5479.04 | AM41: 4368.7 | AN41: 93180 | AO41: 60.12 | AP41: 1.5682762 | AQ41: =VLOOKUP(A41,[1]净融资函数!$B:$E,4,0) -> -468.17584
A42: 46010 | B42: 1.2706 | C42: 1.4413 | D42: 1.3517 | E42: 1.5148 | F42: 1.7898 | G42: 1.4929 | H42: 77283.041 | I42: 0.90341443 | J42: 98.7125 | K42: 7.055 | L42: 7.041 | M42: 19.65 | N42: 28.14 | O42: 40.17 | P42: 58808 | Q42: 240925 | R42: 108.15 | S42: 13607.93 | T42: 53.309001 | U42: 73.81 | V42: 75.86 | W42: 1165.8 | X42: 2023 | Y42: 31.1 | Z42: 1110 | AA42: 3114 | AB42: 102.94 | AC42: 3460.46 | AD42: 3.48 | AE42: 4.16 | AF42: 48134.89 | AG42: 6834.5 | AH42: 23307.62 | AI42: 4568.1781 | AJ42: 3890.4475 | AK42: 1308.5889 | AL42: 5479.04 | AM42: 4368.7 | AN42: 93180 | AO42: 60.12 | AP42: 1.5682762 | AQ42: =VLOOKUP(A42,[1]净融资函数!$B:$E,4,0) -> 1378.8328 | AR42: -66.3 | AS42: 119.4 | AT42: 486 | AU42: 59.3 | AV42: 249.1 | AW42: 36300
A43: 46009 | B43: 1.2717 | C43: 1.4392 | D43: 1.352 | E43: 1.5226 | F43: 1.8083 | G43: 1.5108 | H43: 77238.474 | I43: 0.8950157 | J43: 98.4401 | K43: 7.0583 | L43: 7.0419 | M43: 17.75 | N43: 27.16 | O43: 37.88 | P43: 78777 | Q43: 236594 | R43: 108.01 | S43: 4259.22 | T43: 29.490372 | U43: 73.81 | V43: 75.86 | W43: 1165.8 | X43: 2071 | Y43: 42.6 | Z43: 1108 | AA43: 3119 | AB43: 103.14 | AC43: 3463.38 | AD43: 3.46 | AE43: 4.12 | AF43: 47951.85 | AG43: 6774.76 | AH43: 23006.36 | AI43: 4552.7926 | AJ43: 3876.3705 | AK43: 1305.9664 | AL43: 5418.29 | AM43: 4363.9 | AN43: 92600 | AO43: 59.71 | AP43: 1.5371541 | AQ43: 55.296786 | AR43: -7.73 | AS43: -55.74 | AT43: 446.8 | AU43: 78.22 | AV43: 252.65 | AW43: 50800
A44: 46008 | B44: 1.2731 | C44: 1.4423 | D44: 1.3449 | E44: 1.4978 | F44: 1.7975 | G44: 1.5296 | H44: 77020.143 | I44: 0.90062912 | J44: 98.3983 | K44: 7.0573 | L44: 7.046 | M44: 16.85 | N44: 26.08 | O44: 36.9 | P44: 75278 | Q44: 233621 | R44: 108.005 | S44: 3374.4 | T44: 39.070226 | U44: 73.81 | V44: 75.86 | W44: 1165.8 | X44: 2121 | Y44: 40 | Z44: 1062 | AA44: 3082 | AB44: 103.14 | AC44: 3430.24 | AD44: 3.49 | AE44: 4.16 | AF44: 47885.97 | AG44: 6721.43 | AH44: 22693.32 | AI44: 4579.875 | AJ44: 3870.2775 | AK44: 1325.3349 | AL44: 5457.95 | AM44: 4371.4 | AN44: 92820 | AO44: 60.66 | AP44: 1.5248637 | AQ44: 1603.9434 | AR44: 110.02 | AS44: 86.85 | AT44: 19.09 | AU44: -20.97 | AV44: 86.85 | AW44: 62000
A45: 46007 | B45: 1.2744 | C45: 1.4488 | D45: 1.3448 | E45: 1.5003 | F45: 1.7265 | G45: 1.5388 | H45: 75164.002 | I45: 0.90259578 | J45: 98.2199 | K45: 7.0602 | L45: 7.0425 | M45: 18.16 | N45: 26.41 | O45: 33.76 | P45: 81239 | Q45: 232138 | R45: 107.905 | S45: 3020.01 | T45: 36.974383 | U45: 73.81 | V45: 75.86 | W45: 1165.8 | X45: 2204 | Y45: 36.6 | Z45: 1058.5 | AA45: 3081 | AB45: 102.5 | AC45: 3420.43 | AD45: 3.48 | AE45: 4.15 | AF45: 48114.26 | AG45: 6800.26 | AH45: 23111.46 | AI45: 4497.5545 | AJ45: 3824.8119 | AK45: 1293.3824 | AL45: 5402.51 | AM45: 4332.2 | AN45: 91920 | AO45: 58.84 | AP45: 1.5327771 | AQ45: 42.579804 | AR45: -151.23 | AS45: 211.4 | AT45: -382.84 | AU45: 28.8 | AV45: -92.39 | AW45: 44200
A46: 46006 | B46: 1.274 | C46: 1.444 | D46: 1.3466 | E46: 1.5123 | F46: 1.7721 | G46: 1.5401 | H46: 75026.755 | I46: 0.89837607 | J46: 98.2797 | K46: 7.0656 | L46: 7.0505 | M46: 17.93 | N46: 25.85 | O46: 33.32 | P46: 107793 | Q46: 231298 | R46: 107.87 | S46: 3013.94 | T46: 28.344498 | U46: 73.81 | V46: 75.86 | W46: 1165.8 | X46: 2193 | Y46: 38.4 | Z46: 1053.5 | AA46: 3064 | AB46: 102.5 | AC46: 3436.31 | AD46: 3.51 | AE46: 4.18 | AF46: 48416.56 | AG46: 6816.51 | AH46: 23057.41 | AI46: 4552.0596 | AJ46: 3867.9209 | AK46: 1318.9064 | AL46: 5498.42 | AM46: 4334.3 | AN46: 92400 | AO46: 60.36 | AP46: 1.5150909 | AQ46: -1980.1609 | AR46: -372.86 | AS46: 169.4 | AT46: -193.52 | AU46: 62.67 | AV46: -84 | AW46: 72200
A47: 46005 | B47: 1.2747 | C47: 1.4691 | D47: 1.3473 | E47: 1.5075 | F47: 1.7292 | G47: 1.5353 | H47: 74356.747 | I47: 0.90158457 | J47: 98.4012 | K47: 7.0638 | L47: 7.0554 | M47: 17.62 | N47: 25.37 | O47: 34.07 | P47: 101259 | Q47: 229975 | R47: 107.985 | S47: 16720.12 | T47: 26.404913 | U47: 73.81 | V47: 75.86 | W47: 1165.8 | X47: 2205 | Y47: 55 | Z47: 1028.5 | AA47: 3070 | AB47: 102.58 | AC47: 3427.15 | AD47: 3.52 | AE47: 4.19 | AF47: 48458.05 | AG47: 6827.41 | AH47: 23195.17 | AI47: 4580.95 | AJ47: 3889.3457 | AK47: 1348.8808 | AL47: 5638.05 | AM47: 4329.8 | AN47: 94080 | AO47: 61.22 | AP47: 1.4584692 | AQ47: -774.82924
A48: 46004 | B48: 1.2747 | C48: 1.4691 | D48: 1.3473 | E48: 1.5075 | F48: 1.7292 | G48: 1.5353 | H48: 74356.747 | I48: 0.90158457 | J48: 98.4012 | K48: 7.0638 | L48: 7.0554 | M48: 17.62 | N48: 25.37 | O48: 34.07 | P48: 101259 | Q48: 229975 | R48: 107.985 | S48: 24856.5 | T48: 23.0032 | U48: 73.81 | V48: 75.86 | W48: 1165.8 | X48: 2205 | Y48: 53.4 | Z48: 1028.5 | AA48: 3070 | AB48: 102.58 | AC48: 3427.15 | AD48: 3.52 | AE48: 4.19 | AF48: 48458.05 | AG48: 6827.41 | AH48: 23195.17 | AI48: 4580.95 | AJ48: 3889.3457 | AK48: 1348.8808 | AL48: 5638.05 | AM48: 4329.8 | AN48: 94080 | AO48: 61.22 | AP48: 1.4603718 | AQ48: -893.81389
A49: 46003 | B49: 1.2747 | C49: 1.4691 | D49: 1.3473 | E49: 1.5075 | F49: 1.7292 | G49: 1.5353 | H49: 74356.747 | I49: 0.90158457 | J49: 98.4012 | K49: 7.0638 | L49: 7.0554 | M49: 17.62 | N49: 25.37 | O49: 34.07 | P49: 101259 | Q49: 229975 | R49: 107.985 | S49: 8266.85 | T49: 35.54807 | U49: 73.81 | V49: 75.86 | W49: 1165.8 | X49: 2205 | Y49: 39.4 | Z49: 1028.5 | AA49: 3070 | AB49: 102.58 | AC49: 3427.15 | AD49: 3.52 | AE49: 4.19 | AF49: 48458.05 | AG49: 6827.41 | AH49: 23195.17 | AI49: 4580.95 | AJ49: 3889.3457 | AK49: 1348.8808 | AL49: 5638.05 | AM49: 4329.8 | AN49: 94080 | AO49: 61.22 | AP49: 1.4609698 | AQ49: 1915.9436 | AR49: -315.39 | AS49: 187.38 | AT49: 568.89 | AU49: 83.41 | AV49: 31.87 | AW49: 102200
A50: 46002 | B50: 1.2768 | C50: 1.4516 | D50: 1.3509 | E50: 1.497 | F50: 1.8256 | G50: 1.5401 | H50: 73738.307 | I50: 0.8946555 | J50: 98.3448 | K50: 7.0686 | L50: 7.058 | M50: 17.71 | N50: 27.3 | O50: 36.4 | P50: 78143 | Q50: 237713 | R50: 108.1 | S50: 4715.49 | T50: 32.570218 | U50: 73.81 | V50: 75.86 | W50: 1148.9 | X50: 2294 | Y50: 55.1 | Z50: 1062.5 | AA50: 3087 | AB50: 102.54 | AC50: 3434.53 | AD50: 3.52 | AE50: 4.14 | AF50: 48704.01 | AG50: 6901 | AH50: 23593.86 | AI50: 4552.1848 | AJ50: 3873.3176 | AK50: 1325.8307 | AL50: 5534.59 | AM50: 4309.3 | AN50: 92210 | AO50: 61.55 | AP50: 1.4632145 | AQ50: -503.70632 | AR50: 113.91 | AS50: 108.31 | AT50: 466.74 | AU50: 57.18 | AV50: -54.8 | AW50: 62000
A51: 46001 | B51: 1.2882 | C51: 1.4521 | D51: 1.3543 | E51: 1.488 | F51: 1.7718 | G51: 1.5407 | H51: 72420.519 | I51: 0.89227986 | J51: 98.6403 | K51: 7.0753 | L51: 7.0638 | M51: 17.52 | N51: 28.62 | O51: 35.43 | P51: 72244 | Q51: 233400 | R51: 108.03 | S51: 4949.88 | T51: 35.915989 | U51: 73.81 | V51: 75.86 | W51: 1148.9 | X51: 2430 | Y51: 54 | Z51: 1082.5 | AA51: 3110 | AB51: 102.54 | AC51: 3458.08 | AD51: 3.54 | AE51: 4.13 | AF51: 48057.75 | AG51: 6886.68 | AH51: 23654.16 | AI51: 4591.8273 | AJ51: 3900.496 | AK51: 1346.7028 | AL51: 5581.1 | AM51: 4258.3 | AN51: 91850 | AO51: 62.52 | AP51: 1.4203394 | AQ51: 3591.5445 | AR51: 2 | AS51: 116.51 | AT51: 373.82 | AU51: 71.89 | AV51: 71.07 | AW51: 71900
A52: 46000 | B52: 1.2984 | C52: 1.4512 | D52: 1.365 | E52: 1.4889 | F52: 1.7113 | G52: 1.541 | H52: 71252.925 | I52: 0.89376535 | J52: 99.2407 | K52: 7.0773 | L52: 7.0693 | M52: 16.82 | N52: 28.62 | O52: 34.12 | P52: 78025 | Q52: 233694 | R52: 107.98 | S52: 5512.19 | T52: 26.429227 | U52: 73.81 | V52: 75.86 | W52: 1148.9 | X52: 2557 | Y52: 51.8 | Z52: 1084 | AA52: 3087 | AB52: 102.26 | AC52: 3453.72 | AD52: 3.61 | AE52: 4.18 | AF52: 47560.29 | AG52: 6840.51 | AH52: 23576.49 | AI52: 4598.2232 | AJ52: 3909.5216 | AK52: 1347.1052 | AL52: 5554.68 | AM52: 4236.6 | AN52: 91090 | AO52: 62.12 | AP52: 1.4162822 | AQ52: -1767.7306 | AR52: -76.17 | AS52: 152.16 | AT52: -47.88 | AU52: 124.6 | AV52: -147.07 | AW52: 72300
A53: 45999 | B53: 1.3022 | C53: 1.4459 | D53: 1.3718 | E53: 1.494 | F53: 1.7419 | G53: 1.5441 | H53: 69496.098 | I53: 0.88912615 | J53: 99.1026 | K53: 7.0764 | L53: 7.0713 | M53: 16.29 | N53: 26.97 | O53: 33.7 | P53: 102800 | Q53: 234037 | R53: 107.91 | S53: 6685.66 | T53: 27.640864 | U53: 73.81 | V53: 75.86 | W53: 1148.9 | X53: 2694 | Y53: 51.3 | Z53: 1107 | AA53: 3128 | AB53: 102.06 | AC53: 3509.33 | AD53: 3.57 | AE53: 4.17 | AF53: 47739.32 | AG53: 6846.51 | AH53: 23545.9 | AI53: 4621.7545 | AJ53: 3924.0778 | AK53: 1350.795 | AL53: 5662.55 | AM53: 4219.9 | AN53: 92970 | AO53: 62.53 | AP53: 1.4056435 | AQ53: 2340.1978 | AR53: -163.16 | AS53: 166.06 | AT53: 50.07 | AU53: 71.11 | AV53: -68.63 | AW53: 58800
A54: 45998 | B54: 1.3003 | C54: 1.438 | D54: 1.3719 | E54: 1.4963 | F54: 1.7752 | G54: 1.5391 | H54: 69973.124 | I54: 0.89750401 | J54: 98.983 | K54: 7.0749 | L54: 7.0706 | M54: 16.23 | N54: 25.47 | O54: 32.83 | P54: 105759 | Q54: 237153 | R54: 107.87 | S54: 35513.83 | T54: 18.499401 | U54: 73.81 | V54: 75.86 | W54: 1148.9 | X54: 2727 | Y54: 27.1 | Z54: 1165 | AA54: 3164 | AB54: 101.71 | AC54: 3511.97 | AD54: 3.56 | AE54: 4.14 | AF54: 47954.99 | AG54: 6870.4 | AH54: 23578.13 | AI54: 4584.5368 | AJ54: 3902.8076 | AK54: 1326.1014 | AL54: 5662.46 | AM54: 4227.7 | AN54: 92780 | AO54: 63.86 | AP54: 1.4146645 | AQ54: -409.74
A55: 45997 | B55: 1.3003 | C55: 1.438 | D55: 1.3719 | E55: 1.4963 | F55: 1.7752 | G55: 1.5391 | H55: 69973.124 | I55: 0.89750401 | J55: 98.983 | K55: 7.0749 | L55: 7.0706 | M55: 16.23 | N55: 25.47 | O55: 32.83 | P55: 105759 | Q55: 237153 | R55: 107.87 | S55: 54355.63 | T55: 17.996912 | U55: 73.81 | V55: 75.86 | W55: 1148.9 | X55: 2727 | Y55: 28.7 | Z55: 1165 | AA55: 3164 | AB55: 101.71 | AC55: 3511.97 | AD55: 3.56 | AE55: 4.14 | AF55: 47954.99 | AG55: 6870.4 | AH55: 23578.13 | AI55: 4584.5368 | AJ55: 3902.8076 | AK55: 1326.1014 | AL55: 5662.46 | AM55: 4227.7 | AN55: 92780 | AO55: 63.86 | AP55: 1.4146645 | AQ55: -2419.74
A56: 45996 | B56: 1.3003 | C56: 1.438 | D56: 1.3719 | E56: 1.4963 | F56: 1.7752 | G56: 1.5391 | H56: 69973.124 | I56: 0.89750401 | J56: 98.983 | K56: 7.0749 | L56: 7.0706 | M56: 16.23 | N56: 25.47 | O56: 32.83 | P56: 105759 | Q56: 237153 | R56: 107.87 | S56: 15998.83 | T56: 37.030767 | U56: 73.81 | V56: 75.86 | W56: 1148.9 | X56: 2727 | Y56: 42.1 | Z56: 1165 | AA56: 3164 | AB56: 101.71 | AC56: 3511.97 | AD56: 3.56 | AE56: 4.14 | AF56: 47954.99 | AG56: 6870.4 | AH56: 23578.13 | AI56: 4584.5368 | AJ56: 3902.8076 | AK56: 1326.1014 | AL56: 5662.46 | AM56: 4227.7 | AN56: 92780 | AO56: 63.86 | AP56: 1.4158009 | AQ56: -194.39863 | AR56: -308.97 | AS56: 133.91 | AT56: -399.8 | AU56: 48 | AV56: -201.48 | AW56: 70000
A57: 45995 | B57: 1.2997 | C57: 1.4376 | D57: 1.3611 | E57: 1.4852 | F57: 1.8505 | G57: 1.5423 | H57: 72624.492 | I57: 0.88609208 | J57: 99.0602 | K57: 7.0733 | L57: 7.069 | M57: 13.86 | N57: 25.49 | O57: 29.68 | P57: 155591 | Q57: 239718 | R57: 107.67 | S57: 6696.06 | T57: 28.504376 | U57: 73.81 | V57: 75.86 | W57: 1148.9 | X57: 2814 | Y57: 43.4 | Z57: 1075 | AA57: 3161 | AB57: 101.88 | AC57: 3523.97 | AD57: 3.52 | AE57: 4.11 | AF57: 47850.94 | AG57: 6857.12 | AH57: 23505.14 | AI57: 4546.5664 | AJ57: 3875.7933 | AK57: 1326.1646 | AL57: 5615.43 | AM57: 4237.9 | AN57: 90980 | AO57: 63.37 | AP57: 1.4051715 | AQ57: -247.53661 | AR57: -309.09 | AS57: 96.7 | AT57: -529.72 | AU57: 91.8 | AV57: -200.04 | AW57: 102200
A58: 45994 | B58: 1.2992 | C58: 1.4409 | D58: 1.3578 | E58: 1.4837 | F58: 1.7607 | G58: 1.5376 | H58: 72490.445 | I58: 0.89484201 | J58: 98.8659 | K58: 7.0754 | L58: 7.0661 | M58: 14.23 | N58: 28.1 | O58: 31.68 | P58: 81575 | Q58: 246791 | R58: 108.04 | S58: 7786.38 | T58: 28.748665 | U58: 73.81 | V58: 75.86 | W58: 1175.9 | X58: 2845 | Y58: 58.8 | Z58: 1079.5 | AA58: 3164 | AB58: 101.87 | AC58: 3509.24 | AD58: 3.49 | AE58: 4.06 | AF58: 47882.9 | AG58: 6849.72 | AH58: 23454.09 | AI58: 4531.0486 | AJ58: 3877.9996 | AK58: 1308.3672 | AL58: 5534.92 | AM58: 4234.8 | AN58: 89210 | AO58: 62.75 | AP58: 1.422377 | AQ58: 2944.3242 | AR58: -69.7 | AS58: 158.64 | AT58: -248.55 | AU58: 80.08 | AV58: -179.4 | AW58: 46000
A59: 45993 | B59: 1.2973 | C59: 1.441 | D59: 1.3611 | E59: 1.4862 | F59: 1.7379 | G59: 1.5415 | H59: 71070.469 | I59: 0.89820842 | J59: 99.3208 | K59: 7.0794 | L59: 7.0712 | M59: 14.77 | N59: 29.12 | O59: 31.11 | P59: 77699 | Q59: 236302 | R59: 107.98 | S59: 8682.33 | T59: 24.721561 | U59: 73.81 | V59: 75.86 | W59: 1175.9 | X59: 2600 | Y59: 48.4 | Z59: 1094.5 | AA59: 3135 | AB59: 101.85 | AC59: 3525.18 | AD59: 3.51 | AE59: 4.09 | AF59: 47474.46 | AG59: 6829.37 | AH59: 23413.67 | AI59: 4554.3347 | AJ59: 3897.7116 | AK59: 1320.1564 | AL59: 5624.04 | AM59: 4238.7 | AN59: 88920 | AO59: 62.39 | AP59: 1.4211582 | AQ59: 1716.5934 | AR59: -129.39 | AS59: 107.64 | AT59: -20.95 | AU59: 79.79 | AV59: -132.15 | AW59: 36600
A60: 45992 | B60: 1.3062 | C60: 1.458 | D60: 1.3713 | E60: 1.4931 | F60: 1.699 | G60: 1.5393 | H60: 68611.205 | I60: 0.89916341 | J60: 99.4081 | K60: 7.0759 | L60: 7.0725 | M60: 14.59 | N60: 29.11 | O60: 32.14 | P60: 86167 | Q60: 230610 | R60: 108.04 | S60: 11195.47 | T60: 20.023659 | U60: 73.81 | V60: 75.86 | W60: 1175.9 | X60: 2583 | Y60: 40.7 | Z60: 1076.5 | AA60: 3122 | AB60: 101.82 | AC60: 3526.23 | AD60: 3.54 | AE60: 4.09 | AF60: 47289.33 | AG60: 6812.63 | AH60: 23275.92 | AI60: 4576.4856 | AJ60: 3914.0061 | AK60: 1336.7561 | AL60: 5644.76 | AM60: 4265 | AN60: 89280 | AO60: 63.33 | AP60: 1.4227377 | AQ60: -290.23183 | AR60: -39.79 | AS60: 38.34 | AT60: 202.76 | AU60: 16.04 | AV60: -340.27 | AW60: 45200
A61: 45991 | B61: 1.3033 | C61: 1.4668 | D61: 1.4252 | E61: 1.5222 | F61: 1.735 | G61: 1.5503 | H61: 52395.905 | I61: 0.91060031 | J61: 99.4391 | K61: 7.0789 | L61: 7.0794 | M61: 14.6 | N61: 28.13 | O61: 31.67 | P61: 66598 | Q61: 234480 | R61: 107.94 | S61: 54602.87 | T61: 25.478163 | U61: 73.81 | V61: 75.86 | W61: 1175.9 | X61: 2560 | Y61: 32 | Z61: 1064 | AA61: 3098 | AB61: 101.81 | AC61: 3499.25 | AD61: 3.47 | AE61: 4.02 | AF61: 47716.42 | AG61: 6849.09 | AH61: 23365.69 | AI61: 4526.6616 | AJ61: 3888.5962 | AK61: 1327.1493 | AL61: 5599.11 | AM61: 4256.4 | AN61: 87430 | AO61: 62.32 | AP61: 1.4315121 | AQ61: -588.22891
A62: 45990 | B62: 1.3033 | C62: 1.4668 | D62: 1.4252 | E62: 1.5222 | F62: 1.735 | G62: 1.5503 | H62: 52395.905 | I62: 0.91060031 | J62: 99.4391 | K62: 7.0789 | L62: 7.0794 | M62: 14.6 | N62: 28.13 | O62: 31.67 | P62: 66598 | Q62: 234480 | R62: 107.94 | S62: 77870.19 | T62: 45.90869 | U62: 73.81 | V62: 75.86 | W62: 1175.9 | X62: 2560 | Y62: 48.6 | Z62: 1064 | AA62: 3098 | AB62: 101.81 | AC62: 3499.25 | AD62: 3.47 | AE62: 4.02 | AF62: 47716.42 | AG62: 6849.09 | AH62: 23365.69 | AI62: 4526.6616 | AJ62: 3888.5962 | AK62: 1327.1493 | AL62: 5599.11 | AM62: 4256.4 | AN62: 87430 | AO62: 62.32 | AP62: 1.4342277 | AQ62: -516.97
A63: 45989 | B63: 1.3033 | C63: 1.4668 | D63: 1.4252 | E63: 1.5222 | F63: 1.735 | G63: 1.5503 | H63: 52395.905 | I63: 0.91060031 | J63: 99.4391 | K63: 7.0789 | L63: 7.0794 | M63: 14.6 | N63: 28.13 | O63: 31.67 | P63: 66598 | Q63: 234480 | R63: 107.94 | S63: 30748.66 | T63: 37.171889 | U63: 73.81 | V63: 75.86 | W63: 1175.9 | X63: 2560 | Y63: 45.7 | Z63: 1064 | AA63: 3098 | AB63: 101.81 | AC63: 3499.25 | AD63: 3.47 | AE63: 4.02 | AF63: 47716.42 | AG63: 6849.09 | AH63: 23365.69 | AI63: 4526.6616 | AJ63: 3888.5962 | AK63: 1327.1493 | AL63: 5599.11 | AM63: 4256.4 | AN63: 87430 | AO63: 62.32 | AP63: 1.439333 | AQ63: -720.58045 | AR63: -322.46 | AS63: 183.03 | AT63: -75.06 | AU63: 102.25 | AV63: -37.39 | AW63: 66000
A64: 45988 | B64: 1.3114 | C64: 1.4464 | D64: 1.3706 | E64: 1.5185 | F64: 1.7622 | G64: 1.5546 | H64: 60259.947 | I64: 0.83696175 | J64: 99.5527 | K64: 7.0779 | L64: 7.0806 | M64: 13.08 | N64: 26.53 | O64: 31.64 | P64: 104576 | Q64: 237119 | R64: 107.895 | S64: 16073.18 | T64: 37.32521 | U64: 73.81 | V64: 75.86 | W64: 1175.9 | X64: 2480 | Y64: 56 | Z64: 1075.5 | AA64: 3088 | AB64: 101.73 | AC64: 3481.81 | AD64: 3.45 | AE64: 4 | AF64: 47427.12 | AG64: 6812.61 | AH64: 23214.69 | AI64: 4515.4027 | AJ64: 3875.2594 | AK64: 1310.7005 | AL64: 5598.05 | AM64: 4196.1 | AN64: 86990 | AO64: 62.92 | AP64: 1.4290878 | AQ64: 1772.6147 | AR64: -282.35 | AS64: 152.55 | AT64: -467.84 | AU64: 41.63 | AV64: -57.43 | AW64: 51700
A65: 45987 | B65: 1.3127 | C65: 1.4744 | D65: 1.3672 | E65: 1.5205 | F65: 1.7171 | G65: 1.5537 | H65: 63878.942 | I65: 0.86023735 | J65: 99.5885 | K65: 7.0796 | L65: 7.0802 | M65: 11.88 | N65: 23.86 | O65: 31.73 | P65: 138461 | Q65: 264767 | R65: 107.85 | S65: 24557.35 | T65: 29.627198 | U65: 73.81 | V65: 75.86 | W65: 1175.9 | X65: 2401 | Y65: 46.9 | Z65: 1073 | AA65: 3097 | AB65: 101.93 | AC65: 3478 | AD65: 3.45 | AE65: 4 | AF65: 47427.12 | AG65: 6812.61 | AH65: 23214.69 | AI65: 4517.6255 | AJ65: 3864.1844 | AK65: 1315.0411 | AL65: 5618.36 | AM65: 4196.1 | AN65: 86590 | AO65: 62.44 | AP65: 1.4380349 | AQ65: 1496.8102 | AR65: -556.51 | AS65: 130.4 | AT65: -398.39 | AU65: 105.98 | AV65: 168.93 | AW65: 80400
A66: 45986 | B66: 1.318 | C66: 1.4541 | D66: 1.3843 | E66: 1.5238 | F66: 1.7424 | G66: 1.5471 | H66: 64833.027 | I66: 0.86173597 | J66: 99.8123 | K66: 7.0826 | L66: 7.0938 | M66: 12.42 | N66: 23.13 | O66: 31.15 | P66: 180831 | Q66: 281059 | R66: 108.22 | S66: 4168.09 | T66: 34.434868 | U66: 71.17 | V66: 75.86 | W66: 1175.9 | X66: 2309 | Y66: 62.8 | Z66: 1097 | AA66: 3101 | AB66: 101.98 | AC66: 3482.63 | AD66: 3.43 | AE66: 4.01 | AF66: 47112.45 | AG66: 6765.88 | AH66: 23025.59 | AI66: 4490.4047 | AJ66: 3870.0228 | AK66: 1302.1669 | AL66: 5612.03 | AM66: 4126.3 | AN66: 86600 | AO66: 61.9 | AP66: 1.4547839 | AQ66: -278.04897 | AR66: -115.58 | AS66: 66.74 | AT66: -83.65 | AU66: 71.1 | AV66: 40.82 | AW66: 36200
A67: 45985 | B67: 1.3187 | C67: 1.4703 | D67: 1.3894 | E67: 1.5566 | F67: 1.7155 | G67: 1.5445 | H67: 65241.573 | I67: 0.86323111 | J67: 100.2026 | K67: 7.0847 | L67: 7.1056 | M67: 12.29 | N67: 21.96 | O67: 31.24 | P67: 172573 | Q67: 284471 | R67: 108.505 | S67: 3079.47 | T67: 34.119409 | U67: 71.17 | V67: 75.86 | W67: 1175.9 | X67: 2295 | Y67: 51.7 | Z67: 1097 | AA67: 3084 | AB67: 101.59 | AC67: 3480.25 | AD67: 3.46 | AE67: 4.04 | AF67: 46448.27 | AG67: 6705.12 | AH67: 22872.01 | AI67: 4448.0478 | AJ67: 3836.7655 | AK67: 1296.6023 | AL67: 5545.56 | AM67: 4133.8 | AN67: 86080 | AO67: 62.73 | AP67: 1.4733114 | AQ67: 4544.4291 | AR67: -106.91 | AS67: 77.29 | AT67: 4.76 | AU67: 144.23 | AV67: -1.26 | AW67: 22000
A68: 45984 | B68: 1.3209 | C68: 1.4408 | D68: 1.3877 | E68: 1.4952 | F68: 1.7605 | G68: 1.542 | H68: 67662.775 | I68: 0.90074525 | J68: 100.1527 | K68: 7.0875 | L68: 7.1103 | M68: 12.61 | N68: 21.29 | O68: 30.07 | P68: 196506 | Q68: 279585 | R68: 108.43 | S68: 9626.88 | T68: 21.431157 | U68: 71.17 | V68: 75.86 | W68: 1175.9 | X68: 2275 | Y68: 59.4 | Z68: 1113 | AA68: 3060 | AB68: 101.59 | AC68: 3456.21 | AD68: 3.51 | AE68: 4.06 | AF68: 46245.41 | AG68: 6602.99 | AH68: 22273.08 | AI68: 4453.6076 | AJ68: 3834.8908 | AK68: 1285.8303 | AL68: 5395.49 | AM68: 4062.8 | AN68: 85660 | AO68: 62.51 | AP68: 1.4699439 | AQ68: -1131.2569
A69: 45983 | B69: 1.3209 | C69: 1.4408 | D69: 1.3877 | E69: 1.4952 | F69: 1.7605 | G69: 1.542 | H69: 67662.775 | I69: 0.90074525 | J69: 100.1527 | K69: 7.0875 | L69: 7.1103 | M69: 12.61 | N69: 21.29 | O69: 30.07 | P69: 196506 | Q69: 279585 | R69: 108.43 | S69: 16946.82 | T69: 23.639452 | U69: 71.17 | V69: 75.86 | W69: 1175.9 | X69: 2275 | Y69: 59.9 | Z69: 1113 | AA69: 3060 | AB69: 101.59 | AC69: 3456.21 | AD69: 3.51 | AE69: 4.06 | AF69: 46245.41 | AG69: 6602.99 | AH69: 22273.08 | AI69: 4453.6076 | AJ69: 3834.8908 | AK69: 1285.8303 | AL69: 5395.49 | AM69: 4062.8 | AN69: 85660 | AO69: 62.51 | AP69: 1.4699989 | AQ69: -386.48
A70: 45982 | B70: 1.3209 | C70: 1.4408 | D70: 1.3877 | E70: 1.4952 | F70: 1.7605 | G70: 1.542 | H70: 67662.775 | I70: 0.90074525 | J70: 100.1527 | K70: 7.0875 | L70: 7.1103 | M70: 12.61 | N70: 21.29 | O70: 30.07 | P70: 196506 | Q70: 279585 | R70: 108.43 | S70: 4702 | T70: 32.105243 | U70: 71.17 | V70: 75.86 | W70: 1175.9 | X70: 2275 | Y70: 56.9 | Z70: 1113 | AA70: 3060 | AB70: 101.59 | AC70: 3456.21 | AD70: 3.51 | AE70: 4.06 | AF70: 46245.41 | AG70: 6602.99 | AH70: 22273.08 | AI70: 4453.6076 | AJ70: 3834.8908 | AK70: 1285.8303 | AL70: 5395.49 | AM70: 4062.8 | AN70: 85660 | AO70: 62.51 | AP70: 1.4717604 | AQ70: -1241.4977 | AR70: -307.33 | AS70: 192.25 | AT70: 59.49 | AU70: 151.89 | AV70: 104.35 | AW70: 39000
A71: 45981 | B71: 1.3652 | C71: 1.4857 | D71: 1.4357 | E71: 1.5101 | F71: 1.739 | G71: 1.5406 | H71: 66178.466 | I71: 0.88662784 | J71: 100.2193 | K71: 7.0905 | L71: 7.1167 | M71: 11.98 | N71: 20.98 | O71: 28.53 | P71: 144171 | Q71: 280931 | R71: 108.485 | S71: 2894.24 | T71: 36.425571 | U71: 73.49 | V71: 75.86 | W71: 1200.6 | X71: 2270 | Y71: 58.8 | Z71: 1123.5 | AA71: 3055 | AB71: 101.61 | AC71: 3479.64 | AD71: 3.55 | AE71: 4.1 | AF71: 45752.26 | AG71: 6538.76 | AH71: 22078.05 | AI71: 4564.9483 | AJ71: 3931.0512 | AK71: 1328.1856 | AL71: 5574.59 | AM71: 4076.7 | AN71: 86130 | AO71: 63.19 | AP71: 1.4356217 | AQ71: -1082.0084 | AR71: -176.4 | AS71: 131.57 | AT71: -35.41 | AU71: 96 | AV71: 160.05 | AW71: 62300
A72: 45980 | B72: 1.4221 | C72: 1.5131 | D72: 1.4851 | E72: 1.5242 | F72: 1.7323 | G72: 1.5443 | H72: 65585.503 | I72: 0.89419301 | J72: 100.1249 | K72: 7.0872 | L72: 7.1096 | M72: 12.53 | N72: 21.37 | O72: 28.51 | P72: 108780 | Q72: 276083 | R72: 108.425 | S72: 3533.35 | T72: 29.33845 | U72: 73.49 | V72: 75.86 | W72: 1200.6 | X72: 2260 | Y72: 59.7 | Z72: 1150 | AA72: 3081 | AB72: 102.17 | AC72: 3509.36 | AD72: 3.58 | AE72: 4.13 | AF72: 46138.77 | AG72: 6642.16 | AH72: 22564.23 | AI72: 4588.2922 | AJ72: 3946.7424 | AK72: 1344.7956 | AL72: 5606.9 | AM72: 4078.3 | AN72: 86080 | AO72: 63.66 | AP72: 1.4207052 | AQ72: 2926.7273 | AR72: -204.26 | AS72: 160.05 | AT72: 125.24 | AU72: 48.62 | AV72: 8.4 | AW72: 30800
A73: 45979 | B73: 1.5285 | C73: 1.5239 | D73: 1.5711 | E73: 1.5294 | F73: 1.7339 | G73: 1.545 | H73: 62225.804 | I73: 0.88472688 | J73: 99.5932 | K73: 7.0856 | L73: 7.1125 | M73: 12.78 | N73: 21.52 | O73: 28.28 | P73: 94663 | Q73: 285339 | R73: 108.5 | S73: 4067.33 | T73: 29.024155 | U73: 73.49 | V73: 75.86 | W73: 1200.6 | X73: 2216 | Y73: 59.8 | Z73: 1172.5 | AA73: 3085 | AB73: 101.98 | AC73: 3505.01 | AD73: 3.58 | AE73: 4.12 | AF73: 46091.74 | AG73: 6617.32 | AH73: 22432.85 | AI73: 4568.1928 | AJ73: 3939.8131 | AK73: 1357.9264 | AL73: 5645.73 | AM73: 4067.4 | AN73: 85650 | AO73: 64.82 | AP73: 1.4356272 | AQ73: 852.35483 | AR73: 40.08 | AS73: 173.81 | AT73: 112.9 | AU73: 113.29 | AV73: -143.41 | AW73: 34100
A74: 45978 | B74: 1.5119 | C74: 1.5236 | D74: 1.5596 | E74: 1.5321 | F74: 1.7461 | G74: 1.5389 | H74: 62502.452 | I74: 0.87676378 | J74: 99.5317 | K74: 7.0816 | L74: 7.1048 | M74: 12.79 | N74: 22.43 | O74: 28.92 | P74: 87990 | Q74: 285503 | R74: 108.485 | S74: 4567.36 | T74: 31.739994 | U74: 73.49 | V74: 75.86 | W74: 1200.6 | X74: 2153 | Y74: 45.9 | Z74: 1205.5 | AA74: 3076 | AB74: 102 | AC74: 3531.97 | AD74: 3.6 | AE74: 4.13 | AF74: 46590.24 | AG74: 6672.41 | AH74: 22708.07 | AI74: 4598.0525 | AJ74: 3972.0348 | AK74: 1354.0376 | AL74: 5756.88 | AM74: 4045.1 | AN74: 86450 | AO74: 64.03 | AP74: 1.421227 | AQ74: 1596.1467 | AR74: -120.62 | AS74: 106.15 | AT74: 138.13 | AU74: 60.42 | AV74: 75.84 | AW74: 34700
A75: 45977 | B75: 1.3729 | C75: 1.4673 | D75: 1.4296 | E75: 1.4945 | F75: 1.7369 | G75: 1.54 | H75: 64747.17 | I75: 0.88911353 | J75: 99.2845 | K75: 7.0825 | L75: 7.1007 | M75: 13.71 | N75: 21.81 | O75: 29.04 | P75: 88662 | Q75: 281658 | R75: 108.415 | S75: 15052.37 | T75: 19.901807 | U75: 76.13 | V75: 75.86 | W75: 1200.6 | X75: 2125 | Y75: 57.3 | Z75: 1201 | AA75: 3047 | AB75: 102.07 | AC75: 3523.03 | AD75: 3.62 | AE75: 4.14 | AF75: 47147.48 | AG75: 6734.11 | AH75: 22900.589 | AI75: 4628.1398 | AJ75: 3990.4921 | AK75: 1361.2323 | AL75: 5812.8 | AM75: 4084.4 | AN75: 86900 | AO75: 64.29 | AP75: 1.408269 | AQ75: -657.6471
A76: 45976 | B76: 1.3729 | C76: 1.4673 | D76: 1.4296 | E76: 1.4945 | F76: 1.7369 | G76: 1.54 | H76: 64747.17 | I76: 0.88911353 | J76: 99.2845 | K76: 7.0825 | L76: 7.1007 | M76: 13.71 | N76: 21.81 | O76: 29.04 | P76: 88662 | Q76: 281658 | R76: 108.415 | S76: 23898.33 | T76: 21.044772 | U76: 76.13 | V76: 75.86 | W76: 1200.6 | X76: 2125 | Y76: 56.2 | Z76: 1201 | AA76: 3047 | AB76: 102.07 | AC76: 3523.03 | AD76: 3.62 | AE76: 4.14 | AF76: 47147.48 | AG76: 6734.11 | AH76: 22900.589 | AI76: 4628.1398 | AJ76: 3990.4921 | AK76: 1361.2323 | AL76: 5812.8 | AM76: 4084.4 | AN76: 86900 | AO76: 64.29 | AP76: 1.4089305 | AQ76: -485.89
A77: 45975 | B77: 1.3729 | C77: 1.4673 | D77: 1.4296 | E77: 1.4945 | F77: 1.7369 | G77: 1.54 | H77: 64747.17 | I77: 0.88911353 | J77: 99.2845 | K77: 7.0825 | L77: 7.1007 | M77: 13.71 | N77: 21.81 | O77: 29.04 | P77: 88662 | Q77: 281658 | R77: 108.415 | S77: 17663.23 | T77: 25.859957 | U77: 76.13 | V77: 75.86 | W77: 1200.6 | X77: 2125 | Y77: 57.8 | Z77: 1201 | AA77: 3047 | AB77: 102.07 | AC77: 3523.03 | AD77: 3.62 | AE77: 4.14 | AF77: 47147.48 | AG77: 6734.11 | AH77: 22900.589 | AI77: 4628.1398 | AJ77: 3990.4921 | AK77: 1361.2323 | AL77: 5812.8 | AM77: 4084.4 | AN77: 86900 | AO77: 64.29 | AP77: 1.4089305 | AQ77: 491.23773 | AR77: -281.46 | AS77: 168.65 | AT77: 168.4 | AU77: 109.05 | AV77: 60.21 | AW77: 44700
A78: 45974 | B78: 1.3199 | C78: 1.4782 | D78: 1.3887 | E78: 1.5005 | F78: 1.825 | G78: 1.5438 | H78: 69648.089 | I78: 0.89230993 | J78: 99.176 | K78: 7.0865 | L78: 7.0959 | M78: 13.87 | N78: 20.9 | O78: 29.04 | P78: 95049 | Q78: 283711 | R78: 108.41 | S78: 3585.9 | T78: 23.205579 | U78: 75.42 | V78: 75.86 | W78: 1212.3 | X78: 2077 | Y78: 63.9 | Z78: 1213.5 | AA78: 3040 | AB78: 102.2 | AC78: 3534.28 | AD78: 3.58 | AE78: 4.11 | AF78: 47457.22 | AG78: 6737.49 | AH78: 22870.36 | AI78: 4702.0738 | AJ78: 4029.5012 | AK78: 1399.2916 | AL78: 5981.3 | AM78: 4174.5 | AN78: 87550 | AO78: 63.11 | AP78: 1.3997021 | AQ78: 2123.4587 | AR78: -158.24 | AS78: 125.98 | AT78: -588.43 | AU78: 914.51 | AV78: 60.29 | AW78: 50300
A79: 45973 | B79: 1.4192 | C79: 1.4904 | D79: 1.4662 | E79: 1.505 | F79: 1.7506 | G79: 1.5402 | H79: 65941.133 | I79: 0.89606028 | J79: 99.4771 | K79: 7.0833 | L79: 7.1172 | M79: 14.34 | N79: 21.7 | O79: 28.46 | P79: 73730 | Q79: 291371 | R79: 108.52 | S79: 1827.07 | T79: 21.106986 | U79: 75.42 | V79: 75.86 | W79: 1212.3 | X79: 2030 | Y79: 58.6 | Z79: 1217.5 | AA79: 3039 | AB79: 102.47 | AC79: 3545.02 | AD79: 3.56 | AE79: 4.08 | AF79: 48254.82 | AG79: 6850.92 | AH79: 23406.46 | AI79: 4645.9079 | AJ79: 4000.1396 | AK79: 1379.4518 | AL79: 5933.99 | AM79: 4201.4 | AN79: 86840 | AO79: 62.68 | AP79: 1.4154723 | AQ79: 1513.1135 | AR79: -46.42 | AS79: 121.74 | AT79: 241.74 | AU79: 110.97 | AV79: 145.02 | AW79: 37100
A80: 45972 | B80: 1.5094 | C80: 1.5126 | D80: 1.5361 | E80: 1.5145 | F80: 1.7278 | G80: 1.5353 | H80: 64527.165 | I80: 0.88564194 | J80: 99.4792 | K80: 7.0866 | L80: 7.1207 | M80: 13.88 | N80: 21.07 | O80: 28.04 | P80: 65844 | Q80: 288671 | R80: 108.475 | S80: 1754.02 | T80: 32.165121 | U80: 75.42 | V80: 75.86 | W80: 1212.3 | X80: 2072 | Y80: 47.5 | Z80: 1242 | AA80: 3034 | AB80: 102.83 | AC80: 3521.79 | AD80: 3.58 | AE80: 4.13 | AF80: 47927.96 | AG80: 6846.61 | AH80: 23468.3 | AI80: 4652.1655 | AJ80: 4002.7576 | AK80: 1387.5337 | AL80: 5924.39 | AM80: 4133.2 | AN80: 86630 | AO80: 65.09 | AP80: 1.4126056 | AQ80: -284.84717 | AR80: -44.26 | AS80: 101.81 | AT80: 101.88 | AU80: 126.64 | AV80: -123.82 | AW80: 54900
A81: 45971 | B81: 1.4842 | C81: 1.4993 | D81: 1.5226 | E81: 1.5039 | F81: 1.7283 | G81: 1.5384 | H81: 66589.601 | I81: 0.88918193 | J81: 99.6167 | K81: 7.0856 | L81: 7.1175 | M81: 13.53 | N81: 21.19 | O81: 28.62 | P81: 75170 | Q81: 291294 | R81: 108.485 | S81: 1813.33 | T81: 21.740155 | U81: 75.42 | V81: 75.86 | W81: 1212.3 | X81: 2084 | Y81: 48.9 | Z81: 1261 | AA81: 3035 | AB81: 102.95 | AC81: 3543.72 | AD81: 3.58 | AE81: 4.13 | AF81: 47368.63 | AG81: 6832.43 | AH81: 23527.17 | AI81: 4695.0507 | AJ81: 4018.5972 | AK81: 1407.5576 | AL81: 5915.56 | AM81: 4123.4 | AN81: 86480 | AO81: 63.94 | AP81: 1.4009041 | AQ81: 1449.2693 | AR81: -21.54 | AS81: 137.31 | AT81: -264.61 | AU81: 95.91 | AV81: 54.58 | AW81: 45000
A82: 45970 | B82: 1.3321 | C82: 1.413 | D82: 1.3916 | E82: 1.4677 | F82: 1.7264 | G82: 1.5378 | H82: 69200.685 | I82: 0.89614152 | J82: 99.5477 | K82: 7.0836 | L82: 7.1225 | M82: 13.85 | N82: 20.08 | O82: 27.73 | P82: 64117 | Q82: 289749 | R82: 108.445 | S82: 4841.96 | T82: 14.308457 | U82: 77.19 | V82: 75.86 | W82: 1212.3 | X82: 2104 | Y82: 55.9 | Z82: 1278.5 | AA82: 3036 | AB82: 102.85 | AC82: 3531.08 | AD82: 3.55 | AE82: 4.11 | AF82: 46987.1 | AG82: 6728.8 | AH82: 23004.54 | AI82: 4678.7944 | AJ82: 3997.5557 | AK82: 1415.6855 | AL82: 5837.36 | AM82: 4007.8 | AN82: 85940 | AO82: 63.7 | AP82: 1.391302 | AQ82: -555.935
A83: 45969 | B83: 1.3321 | C83: 1.413 | D83: 1.3916 | E83: 1.4677 | F83: 1.7264 | G83: 1.5378 | H83: 69200.685 | I83: 0.89614152 | J83: 99.5477 | K83: 7.0836 | L83: 7.1225 | M83: 13.85 | N83: 20.08 | O83: 27.73 | P83: 64117 | Q83: 289749 | R83: 108.445 | S83: 6601.06 | T83: 14.58173 | U83: 77.19 | V83: 75.86 | W83: 1212.3 | X83: 2104 | Y83: 54 | Z83: 1278.5 | AA83: 3036 | AB83: 102.85 | AC83: 3531.08 | AD83: 3.55 | AE83: 4.11 | AF83: 46987.1 | AG83: 6728.8 | AH83: 23004.54 | AI83: 4678.7944 | AJ83: 3997.5557 | AK83: 1415.6855 | AL83: 5837.36 | AM83: 4007.8 | AN83: 85940 | AO83: 63.7 | AP83: 1.391302 | AQ83: -315.5061
A84: 45968 | B84: 1.3321 | C84: 1.413 | D84: 1.3916 | E84: 1.4677 | F84: 1.7264 | G84: 1.5378 | H84: 69200.685 | I84: 0.89614152 | J84: 99.5477 | K84: 7.0836 | L84: 7.1225 | M84: 13.85 | N84: 20.08 | O84: 27.73 | P84: 64117 | Q84: 289749 | R84: 108.445 | S84: 3910.06 | T84: 23.414061 | U84: 77.19 | V84: 75.86 | W84: 1212.3 | X84: 2104 | Y84: 59.3 | Z84: 1278.5 | AA84: 3036 | AB84: 102.85 | AC84: 3531.08 | AD84: 3.55 | AE84: 4.11 | AF84: 46987.1 | AG84: 6728.8 | AH84: 23004.54 | AI84: 4678.7944 | AJ84: 3997.5557 | AK84: 1415.6855 | AL84: 5837.36 | AM84: 4007.8 | AN84: 85940 | AO84: 63.7 | AP84: 1.4001213 | AQ84: 1868.0738 | AR84: -125.03 | AS84: 158.47 | AT84: -216.03 | AU84: 124.43 | AV84: 310.58 | AW84: 65700
A85: 45967 | B85: 1.3166 | C85: 1.4254 | D85: 1.3621 | E85: 1.4635 | F85: 1.7524 | G85: 1.542 | H85: 74854.418 | I85: 0.8893864 | J85: 99.6968 | K85: 7.0865 | L85: 7.1219 | M85: 12.82 | N85: 20.98 | O85: 28.31 | P85: 78071 | Q85: 290586 | R85: 108.535 | S85: 1419.96 | T85: 17.690656 | U85: 77.09 | V85: 75.86 | W85: 1212.3 | X85: 2063 | Y85: 59.7 | Z85: 1282.5 | AA85: 3028 | AB85: 102.89 | AC85: 3546.5 | AD85: 3.57 | AE85: 4.11 | AF85: 46912.3 | AG85: 6720.32 | AH85: 23053.99 | AI85: 4693.4032 | AJ85: 4007.7599 | AK85: 1436.858 | AL85: 5944.22 | AM85: 3984.8 | AN85: 86320 | AO85: 63.57 | AP85: 1.399116 | AQ85: 1848.4105 | AR85: -140.44 | AS85: 134.27 | AT85: 18.02 | AU85: 118.25 | AV85: -16.5 | AW85: 81500
A86: 45966 | B86: 1.3151 | C86: 1.4378 | D86: 1.3615 | E86: 1.4629 | F86: 1.7207 | G86: 1.5369 | H86: 72983.446 | I86: 0.90161425 | J86: 100.1593 | K86: 7.0901 | L86: 7.1246 | M86: 12.5 | N86: 21.87 | O86: 29.63 | P86: 65077 | Q86: 290425 | R86: 108.62 | S86: 1389.6 | T86: 23.512638 | U86: 77.09 | V86: 75.86 | W86: 1212.3 | X86: 2003 | Y86: 62.3 | Z86: 1260.5 | AA86: 3025 | AB86: 102.89 | AC86: 3533.38 | AD86: 3.63 | AE86: 4.17 | AF86: 47311 | AG86: 6796.29 | AH86: 23499.8 | AI86: 4627.257 | AJ86: 3969.2483 | AK86: 1390.3946 | AL86: 5785.85 | AM86: 3990.4 | AN86: 85670 | AO86: 63.55 | AP86: 1.4260187 | AQ86: 2201.7553 | AR86: -218.69 | AS86: 142.89 | AT86: 111.7 | AU86: 123.62 | AV86: -19.8 | AW86: 84500
A87: 45965 | B87: 1.3148 | C87: 1.4262 | D87: 1.3621 | E87: 1.4584 | F87: 1.6992 | G87: 1.5391 | H87: 71345.766 | I87: 0.89979951 | J87: 100.2092 | K87: 7.0885 | L87: 7.1233 | M87: 13.38 | N87: 22.62 | O87: 31.73 | P87: 79144 | Q87: 290431 | R87: 108.66 | S87: 1482.97 | T87: 22.140053 | U87: 78.34 | V87: 75.86 | W87: 1212.3 | X87: 1958 | Y87: 45.5 | Z87: 1274.5 | AA87: 3061 | AB87: 102.72 | AC87: 3534.2 | AD87: 3.58 | AE87: 4.1 | AF87: 47085.24 | AG87: 6771.55 | AH87: 23348.64 | AI87: 4618.699 | AJ87: 3960.186 | AK87: 1387.2392 | AL87: 5818.29 | AM87: 3941.3 | AN87: 85740 | AO87: 64.35 | AP87: 1.4251001 | AQ87: 823.99399 | AR87: -92.94 | AS87: 130.15 | AT87: 134.68 | AU87: 95.43 | AV87: 89.54 | AW87: 68000
A88: 45964 | B88: 1.3127 | C88: 1.4187 | D88: 1.3646 | E88: 1.4604 | F88: 1.694 | G88: 1.5341 | H88: 68692.487 | I88: 0.89279875 | J88: 99.8762 | K88: 7.0867 | L88: 7.1225 | M88: 14.15 | N88: 22.55 | O88: 33.05 | P88: 76364 | Q88: 288156 | R88: 108.68 | S88: 1525.7 | T88: 16.60223 | U88: 78.34 | V88: 75.86 | W88: 1212.3 | X88: 1945 | Y88: 57.1 | Z88: 1285.5 | AA88: 3088 | AB88: 102.28 | AC88: 3565.86 | AD88: 3.6 | AE88: 4.13 | AF88: 47336.68 | AG88: 6851.97 | AH88: 23834.72 | AI88: 4653.4028 | AJ88: 3976.5207 | AK88: 1400.8585 | AL88: 5922.48 | AM88: 4013.7 | AN88: 87300 | AO88: 64.84 | AP88: 1.4215337 | AQ88: 571.56089 | AR88: -96.39 | AS88: 115.43 | AT88: 708.68 | AU88: 129.29 | AV88: 225.63 | AW88: 64300
A89: 45963 | B89: 1.3184 | C89: 1.4551 | D89: 1.4069 | E89: 1.4923 | F89: 1.7093 | G89: 1.5302 | H89: 52833.485 | I89: 0.92587105 | J89: 99.7308 | K89: 7.088 | L89: 7.1135 | M89: 15.15 | N89: 23.71 | O89: 35.53 | P89: 78680 | Q89: 284696 | R89: 108.68 | S89: 4418.32 | T89: 11.40813 | U89: 77.63 | V89: 75.86 | W89: 1212.3 | X89: 1966 | Y89: 59.2 | Z89: 1295.5 | AA89: 3109 | AB89: 102.81 | AC89: 3556.67 | AD89: 3.6 | AE89: 4.11 | AF89: 47562.87 | AG89: 6840.2 | AH89: 23724.96 | AI89: 4640.6676 | AJ89: 3954.79 | AK89: 1415.5254 | AL89: 5908.08 | AM89: 4013.4 | AN89: 87010 | AO89: 64.58 | AP89: 1.4261446 | AQ89: -287.57434
A90: 45962 | B90: 1.3184 | C90: 1.4551 | D90: 1.4069 | E90: 1.4923 | F90: 1.7093 | G90: 1.5302 | H90: 52833.485 | I90: 0.92587105 | J90: 99.7308 | K90: 7.088 | L90: 7.1135 | M90: 15.15 | N90: 23.71 | O90: 35.53 | P90: 78680 | Q90: 284696 | R90: 108.68 | S90: 6595.58 | T90: 11.640736 | U90: 77.63 | V90: 75.86 | W90: 1212.3 | X90: 1966 | Y90: 46.8 | Z90: 1295.5 | AA90: 3109 | AB90: 102.81 | AC90: 3556.67 | AD90: 3.6 | AE90: 4.11 | AF90: 47562.87 | AG90: 6840.2 | AH90: 23724.96 | AI90: 4640.6676 | AJ90: 3954.79 | AK90: 1415.5254 | AL90: 5908.08 | AM90: 4013.4 | AN90: 87010 | AO90: 64.58 | AP90: 1.4299877 | AQ90: -621.065
A91: 45961 | B91: 1.3184 | C91: 1.4551 | D91: 1.4069 | E91: 1.4923 | F91: 1.7093 | G91: 1.5302 | H91: 52833.485 | I91: 0.92587105 | J91: 99.7308 | K91: 7.088 | L91: 7.1135 | M91: 15.15 | N91: 23.71 | O91: 35.53 | P91: 78680 | Q91: 284696 | R91: 108.68 | S91: 3885.71 | T91: 46.674089 | U91: 77.63 | V91: 75.86 | W91: 1212.3 | X91: 1966 | Y91: 54.7 | Z91: 1295.5 | AA91: 3109 | AB91: 102.81 | AC91: 3556.67 | AD91: 3.6 | AE91: 4.11 | AF91: 47562.87 | AG91: 6840.2 | AH91: 23724.96 | AI91: 4640.6676 | AJ91: 3954.79 | AK91: 1415.5254 | AL91: 5908.08 | AM91: 4013.4 | AN91: 87010 | AO91: 64.58 | AP91: 1.4324942 | AQ91: 293.74072 | AR91: -76.38 | AS91: 175.95 | AT91: 447.51 | AU91: 197.73 | AV91: 445.72 | AW91: 108500
A92: 45960 | B92: 1.3115 | C92: 1.5018 | D92: 1.3688 | E92: 1.5555 | F92: 1.7909 | G92: 1.5382 | H92: 57614.154 | I92: 0.82298455 | J92: 99.5456 | K92: 7.0864 | L92: 7.1107 | M92: 14.35 | N92: 25.11 | O92: 35.52 | P92: 76263 | Q92: 282218 | R92: 108.63 | S92: 1810.22 | T92: 34.401828 | U92: 78.38 | V92: 75.86 | W92: 1290 | X92: 1983 | Y92: 55.2 | Z92: 1298 | AA92: 3121 | AB92: 102.21 | AC92: 3572.89 | AD92: 3.61 | AE92: 4.11 | AF92: 47522.12 | AG92: 6822.34 | AH92: 23581.14 | AI92: 4709.911 | AJ92: 3986.9008 | AK92: 1461.3001 | AL92: 6051.76 | AM92: 4038.3 | AN92: 87960 | AO92: 64.03 | AP92: 1.4043541 | AQ92: 1599.5689 | AR92: -132.14 | AS92: 160.51 | AT92: 211.46 | AU92: 203.59 | AV92: 310.11 | AW92: 77900
A93: 45959 | B93: 1.4045 | C93: 1.5452 | D93: 1.4371 | E93: 1.5855 | F93: 1.7471 | G93: 1.5342 | H93: 59601.849 | I93: 0.85977815 | J93: 99.1495 | K93: 7.0843 | L93: 7.0991 | M93: 14.83 | N93: 25.48 | O93: 35.3 | P93: 101545 | Q93: 282522 | R93: 108.57 | S93: 1790.2 | T93: 29.047579 | U93: 78.38 | V93: 75.86 | W93: 1290 | X93: 1961 | Y93: 55.9 | Z93: 1267.5 | AA93: 3118 | AB93: 102.08 | AC93: 3606.61 | AD93: 3.59 | AE93: 4.08 | AF93: 47632 | AG93: 6890.59 | AH93: 23958.47 | AI93: 4747.8378 | AJ93: 4016.331 | AK93: 1489.1233 | AL93: 6093.44 | AM93: 3941.7 | AN93: 88710 | AO93: 64.3 | AP93: 1.3860391 | AQ93: 641.11921 | AR93: 47.37 | AS93: 150.57 | AT93: 355.58 | AU93: 204.03 | AV93: 301.69 | AW93: 104900
A94: 45958 | B94: 1.4687 | C94: 1.558 | D94: 1.5059 | E94: 1.6111 | F94: 1.7444 | G94: 1.5349 | H94: 57560.665 | I94: 0.84582193 | J94: 98.7215 | K94: 7.0856 | L94: 7.1006 | M94: 14.59 | N94: 25.03 | O94: 38.04 | P94: 82160 | Q94: 274231 | R94: 108.415 | S94: 1600.7 | T94: 32.334206 | U94: 78.38 | V94: 75.86 | W94: 1290 | X94: 1950 | Y94: 59.6 | Z94: 1258 | AA94: 3102 | AB94: 102.6 | AC94: 3570.13 | AD94: 3.47 | AE94: 3.99 | AF94: 47706.37 | AG94: 6890.89 | AH94: 23827.49 | AI94: 4691.973 | AJ94: 3988.2239 | AK94: 1471.7309 | AL94: 6093.44 | AM94: 3968.1 | AN94: 86980 | AO94: 63.86 | AP94: 1.3987568 | AQ94: 1706.9151 | AR94: 486.44 | AS94: 141.48 | AT94: 209.5 | AU94: 177.17 | AV94: 148.12 | AW94: 98600
A95: 45957 | B95: 1.4529 | C95: 1.5818 | D95: 1.5124 | E95: 1.6451 | F95: 1.7375 | G95: 1.5456 | H95: 59682.345 | I95: 0.84294791 | J95: 98.8207 | K95: 7.0881 | L95: 7.1109 | M95: 12.88 | N95: 24.62 | O95: 41.81 | P95: 82310 | Q95: 263730 | R95: 108.175 | S95: 1422.85 | T95: 31.066029 | U95: 78.38 | V95: 75.86 | W95: 1290 | X95: 1976 | Y95: 58 | Z95: 1251.5 | AA95: 3076 | AB95: 102.49 | AC95: 3595.45 | AD95: 3.48 | AE95: 4.01 | AF95: 47544.59 | AG95: 6875.16 | AH95: 23637.46 | AI95: 4716.0186 | AJ95: 3996.9445 | AK95: 1484.2064 | AL95: 6171.08 | AM95: 3997 | AN95: 88370 | AO95: 65.04 | AP95: 1.3714379 | AQ95: 1212.5851 | AR95: -155.81 | AS95: 141.23 | AT95: -77.74 | AU95: 154.13 | AV95: 109.4 | AW95: 127100
A96: 45956 | B96: 1.3221 | C96: 1.411 | D96: 1.3802 | E96: 1.4649 | F96: 1.7472 | G96: 1.5463 | H96: 67285.833 | I96: 0.88886429 | J96: 98.9417 | K96: 7.0928 | L96: 7.123 | M96: 13.32 | N96: 24.43 | O96: 43.18 | P96: 73721 | Q96: 261298 | R96: 108.005 | S96: 4630.98 | T96: 19.262329 | U96: 78.38 | V96: 75.86 | W96: 1290 | X96: 1991 | Y96: 55.8 | Z96: 1251.5 | AA96: 3053 | AB96: 102.57 | AC96: 3562.25 | AD96: 3.48 | AE96: 4.02 | AF96: 47207.12 | AG96: 6791.69 | AH96: 23204.87 | AI96: 4660.6835 | AJ96: 3950.3115 | AK96: 1462.222 | AL96: 6059.89 | AM96: 4126.9 | AN96: 87720 | AO96: 64.92 | AP96: 1.3815861 | AQ96: -1441.0997
A97: 45955 | B97: 1.3221 | C97: 1.411 | D97: 1.3802 | E97: 1.4649 | F97: 1.7472 | G97: 1.5463 | H97: 67285.833 | I97: 0.88886429 | J97: 98.9417 | K97: 7.0928 | L97: 7.123 | M97: 13.32 | N97: 24.43 | O97: 43.18 | P97: 73721 | Q97: 261298 | R97: 108.005 | S97: 6469.24 | T97: 23.944524 | U97: 78.38 | V97: 75.86 | W97: 1290 | X97: 1991 | Y97: 52.6 | Z97: 1251.5 | AA97: 3053 | AB97: 102.57 | AC97: 3562.25 | AD97: 3.48 | AE97: 4.02 | AF97: 47207.12 | AG97: 6791.69 | AH97: 23204.87 | AI97: 4660.6835 | AJ97: 3950.3115 | AK97: 1462.222 | AL97: 6059.89 | AM97: 4126.9 | AN97: 87720 | AO97: 64.92 | AP97: 1.3844531 | AQ97: -3589.9
A98: 45954 | B98: 1.3221 | C98: 1.411 | D98: 1.3802 | E98: 1.4649 | F98: 1.7472 | G98: 1.5463 | H98: 67285.833 | I98: 0.88886429 | J98: 98.9417 | K98: 7.0928 | L98: 7.123 | M98: 13.32 | N98: 24.43 | O98: 43.18 | P98: 73721 | Q98: 261298 | R98: 108.005 | S98: 2707.9 | T98: 29.544473 | U98: 78.38 | V98: 75.86 | W98: 1290 | X98: 1991 | Y98: 59.9 | Z98: 1251.5 | AA98: 3053 | AB98: 102.57 | AC98: 3562.25 | AD98: 3.48 | AE98: 4.02 | AF98: 47207.12 | AG98: 6791.69 | AH98: 23204.87 | AI98: 4660.6835 | AJ98: 3950.3115 | AK98: 1462.222 | AL98: 6059.89 | AM98: 4126.9 | AN98: 87720 | AO98: 64.92 | AP98: 1.3870497 | AQ98: 2830.7799 | AR98: -120.51 | AS98: 220.04 | AT98: -47.84 | AU98: 201.61 | AV98: 15.33 | AW98: 66000
A99: 45953 | B99: 1.3169 | C99: 1.4267 | D99: 1.3721 | E99: 1.4715 | F99: 1.8243 | G99: 1.5438 | H99: 70671.659 | I99: 0.87919241 | J99: 98.9334 | K99: 7.0918 | L99: 7.1221 | M99: 13.24 | N99: 25.02 | O99: 43.32 | P99: 83847 | Q99: 262198 | R99: 108.035 | S99: 1730.93 | T99: 22.981785 | U99: 75.98 | V99: 75.86 | W99: 1254.6 | X99: 2057 | Y99: 49.2 | Z99: 1231 | AA99: 3069 | AB99: 102.56 | AC99: 3555.56 | AD99: 3.48 | AE99: 4.01 | AF99: 46734.61 | AG99: 6738.44 | AH99: 22941.8 | AI99: 4606.3447 | AJ99: 3922.4101 | AK99: 1401.2558 | AL99: 5951.45 | AM99: 4143.2 | AN99: 86070 | AO99: 65.96 | AP99: 1.384264 | AQ99: 1330.3485 | AR99: -32.31 | AS99: 143.54 | AT99: 168.15 | AU99: 225.45 | AV99: 126.14 | AW99: 84700
A100: 45952 | B100: 1.3167 | C100: 1.4327 | D100: 1.3687 | E100: 1.4688 | F100: 1.7632 | G100: 1.5393 | H100: 70109.562 | I100: 0.90788614 | J100: 98.9071 | K100: 7.0954 | L100: 7.1245 | M100: 13.23 | N100: 25.74 | O100: 45.55 | P100: 71037 | Q100: 269637 | R100: 108.145 | S100: 1774.46 | T100: 31.693912 | U100: 75.98 | V100: 75.86 | W100: 1254.6 | X100: 2092 | Y100: 52.3 | Z100: 1197 | AA100: 3058 | AB100: 102.47 | AC100: 3514.73 | AD100: 3.45 | AE100: 3.97 | AF100: 46590.41 | AG100: 6699.4 | AH100: 22740.4 | AI100: 4592.57 | AJ100: 3913.7576 | AK100: 1405.407 | AL100: 5923.09 | AM100: 4116.6 | AN100: 85420 | AO100: 64.35 | AP100: 1.3967091 | AQ100: 337.08608 | AR100: -137.94 | AS100: 142.69 | AT100: 65.99 | AU100: 182.29 | AV100: 134.28 | AW100: 93600
...

Sheet Sheet2
A1: =[2]!edb() -> Wind
A2: 指标名称 | B2: 上证科创板50成份指数 | C2: 恒生科技指数 | D2: 期货收盘价(连续):COMEX黄金 | E2: 中国:现货领先价格:阴极铜 | F2: 全球:现货价:原油(英国布伦特Dtd) | G2: 期货成交量:国债期货:10年期
A3: 27396 | B3: 0 | C3: 0 | D3: 175.1 | E3: 0 | F3: 0 | G3: 0
A4: 27397 | B4: 0 | C4: 0 | D4: 174.7 | E4: 0 | F4: 0 | G4: 0
A5: 27400 | B5: 0 | C5: 0 | D5: 174.4 | E5: 0 | F5: 0 | G5: 0
A6: 27401 | B6: 0 | C6: 0 | D6: 173.4 | E6: 0 | F6: 0 | G6: 0
A7: 27402 | B7: 0 | C7: 0 | D7: 177.4 | E7: 0 | F7: 0 | G7: 0 | K7: =(69-61)/61 -> 0.13114754
A8: 27403 | B8: 0 | C8: 0 | D8: 178.3 | E8: 0 | F8: 0 | G8: 0
A9: 27404 | B9: 0 | C9: 0 | D9: 181.3 | E9: 0 | F9: 0 | G9: 0
A10: 27407 | B10: 0 | C10: 0 | D10: 178.6 | E10: 0 | F10: 0 | G10: 0
A11: 27408 | B11: 0 | C11: 0 | D11: 178.6 | E11: 0 | F11: 0 | G11: 0
A12: 27409 | B12: 0 | C12: 0 | D12: 177.3 | E12: 0 | F12: 0 | G12: 0
A13: 27410 | B13: 0 | C13: 0 | D13: 175.1 | E13: 0 | F13: 0 | G13: 0
A14: 27411 | B14: 0 | C14: 0 | D14: 172.1 | E14: 0 | F14: 0 | G14: 0
A15: 27414 | B15: 0 | C15: 0 | D15: 176.2 | E15: 0 | F15: 0 | G15: 0
A16: 27415 | B16: 0 | C16: 0 | D16: 173.7 | E16: 0 | F16: 0 | G16: 0
A17: 27416 | B17: 0 | C17: 0 | D17: 174.3 | E17: 0 | F17: 0 | G17: 0
A18: 27417 | B18: 0 | C18: 0 | D18: 176.4 | E18: 0 | F18: 0 | G18: 0
A19: 27418 | B19: 0 | C19: 0 | D19: 179.5 | E19: 0 | F19: 0 | G19: 0
... A12958: 46063 | B12958: 1471.4978 | C12958: 5451.03 | D12958: 0 | E12958: 101734 | F12958: 0 | G12958: 105722

Sheet Sheet3
A1: 指标名称 | B1: 上证科创板50成份指数 | C1: 恒生科技指数 | D1: 期货收盘价(连续):COMEX黄金 | E1: 中国:现货领先价格:阴极铜 | F1: 全球:现货价:原油(英国布伦特Dtd) | G1: 期货成交量:国债期货:10年期
A2: 44418 | B2: 1588.1948 | C2: 6830.15 | D2: 1727.9 | E2: 0 | F2: 71.98 | G2: 85360
A3: 44419 | B3: 1578.7892 | C3: 6820.68 | D3: 1750.7 | E3: 0 | F3: 70.87 | G3: 80028
A4: 44420 | B4: 1586.5006 | C4: 6719.19 | D4: 1751.4 | E4: 0 | F4: 71.74 | G4: 79937
A5: 44421 | B5: 1552.7807 | C5: 6589.54 | D5: 1777.3 | E5: 0 | F5: 71.67 | G5: 92034
A6: 44424 | B6: 1547.931 | C6: 6420.14 | D6: 1786.4 | E6: 0 | F6: 70.2 | G6: 106961
A7: 44425 | B7: 1509.2474 | C7: 6218.89 | D7: 1783 | E7: 0 | F7: 70.65 | G7: 90919
A8: 44426 | B8: 1507.9886 | C8: 6226.69 | D8: 1787.2 | E8: 0 | F8: 69.85 | G8: 111209
A9: 44427 | B9: 1546.11 | C9: 6044.03 | D9: 1780.9 | E9: 0 | F9: 66.19 | G9: 90701
A10: 44428 | B10: 1529.0863 | C10: 5895.06 | D10: 1781.6 | E10: 0 | F10: 66.73 | G10: 66131
A11: 44431 | B11: 1564.1108 | C11: 6021.27 | D11: 1804.5 | E11: 0 | F11: 69.13 | G11: 60038
A12: 44432 | B12: 1578.0306 | C12: 6446.18 | D12: 1803.5 | E12: 0 | F12: 71.12 | G12: 63844
A13: 44433 | B13: 1542.7755 | C13: 6458.97 | D13: 1788.4 | E13: 0 | F13: 71.41 | G13: 66875
... A1172: 46063 | B1172: 1471.4978 | C1172: 5451.03 | D1172: 0 | E1172: 101734 | F1172: 0 | G1172: 105722

Sheet 差值历史稳健标准化
B1: 逆回购利率:7天 | C1: 存款准备金率:中小金融机构(变动公告日期)
A2: 46050 | B2: 1.4 | C2: 6
A3: 46049 | B3: 1.4 | C3: 6
A4: 46048 | B4: 1.4 | C4: 6
A5: 46047 | B5: 1.4 | C5: 6
A6: 46046 | B6: 1.4 | C6: 6
A7: 46045 | B7: 1.4 | C7: 6
A8: 46044 | B8: 1.4 | C8: 6
A9: 46043 | B9: 1.4 | C9: 6
A10: 46042 | B10: 1.4 | C10: 6
A11: 46041 | B11: 1.4 | C11: 6
A12: 46040 | B12: 1.4 | C12: 6
A13: 46039 | B13: 1.4 | C13: 6
... A5867: 40179 | B5867: 3.7561 | C5867: 13.5

Sheet 时代变量
B1: 中国各领导人时期 | C1: 美国各总统时期 | D1: 基本面主题变量
A2: 46050 | B2: 2 | C2: 5 | D2: 4
A3: 46049 | B3: 2 | C3: 5 | D3: 4
A4: 46048 | B4: 2 | C4: 5 | D4: 4
A5: 46047 | B5: 2 | C5: 5 | D5: 4
A6: 46046 | B6: 2 | C6: 5 | D6: 4
A7: 46045 | B7: 2 | C7: 5 | D7: 4
A8: 46044 | B8: 2 | C8: 5 | D8: 4
A9: 46043 | B9: 2 | C9: 5 | D9: 4
A10: 46042 | B10: 2 | C10: 5 | D10: 4
A11: 46041 | B11: 2 | C11: 5 | D11: 4
A12: 46040 | B12: 2 | C12: 5 | D12: 4
A13: 46039 | B13: 2 | C13: 5 | D13: 4
... A5867: 40179 | B5867: 1 | C5867: 1 | D5867: 1

Sheet 时代变量整理明细
A1: 时间 | B1: 中国 | D1: 美国 | F1: 基本面主题变量
B2: 形成共识时间 | C2: 正式当选时间 | D2: 形成共识时间 | E2: 领导人换届时间
A3: 2012 | B3: 2012.11.15 中共十八届一中全会 确认习近平当选中共中央总书记 | D3: 2012.11.7 奥巴马选举结果确定
A4: 2013 | C4: 2013.3.14 十二届全国人大 习近平正式当选国家主席 | E4: 2013.1.20 奥巴马正式就任
A5: 2014 | F5: 2014.9.12 中央经济工作会议 经济进入“新常态”
A6: 2015 | F6: 2015.12.21 中央经济工作会议 供给侧结构性改革
A7: 2016 | D7: 2016.11.8 特朗普选举结果确定 | F7: 2016.12.16 中央经济工作会议 “房住不炒”，地产转向
A8: 2017 | E8: 2017.1.20 特朗普正式就任 | F8: 2017.10.8 十九届全国人大 高速发展→高质量发展
A9: 2018 | F9: 2018.3.22 中美贸易战
A10: 2019 | F10: 2019.12.8 新冠疫情
A11: 2020 | D11: 2020.11.7 拜登选举结果确定
A12: 2021 | E12: 2021.1.20 拜登正式就任
A13: 2022 | F13: 2022.12.9 疫后复苏
A14: 2024 | D14: 2024.11.6 特朗普选举结果确定
A15: 2025 | E15: 2025.1.20（即将） 特朗普正式就任

Sheet 切券时间
A1: 切券起始日 | B1: 切券截止日
A2: 45502
A3: 45377 | B3: 45499
A4: 45285 | B4: 45376
A5: 45189 | B5: 45282
A6: 45090 | B6: 45188
A7: 44999 | B7: 45089
A8: 44916 | B8: 44998
A9: 44844 | B9: 44915
A10: 44823 | B10: 44843
A11: 44725 | B11: 44820
A12: 44642 | B12: 44722
A13: 44545 | B13: 44641
A14: 44382 | B14: 44544
... A54: 40386 | B54: 40448
